Workbook
Name WDI_RAW: Table2[#All]

Sheet Raw Data
A1: Country Name | B1: Country Code | C1: Series Name | D1: Series Code | E1: 2000 [YR2000] | F1: 2001 [YR2001] | G1: 2002 [YR2002] | H1: 2003 [YR2003] | I1: 2004 [YR2004] | J1: 2005 [YR2005] | K1: 2006 [YR2006] | L1: 2007 [YR2007] | M1: 2008 [YR2008] | N1: 2017 [YR2017] | O1: 2018 [YR2018] | P1: 2019 [YR2019] | Q1: 2020 [YR2020] | R1: 2021 [YR2021] | S1: 2022 [YR2022] | T1: 2023 [YR2023] | U1: 2024 [YR2024] | V1: 2025 [YR2025]
A2: Afghanistan | B2: AFG | C2: Broad money (% of GDP) | D2: FM.LBL.BMNY.GD.ZS | E2: .. | F2: .. | G2: .. | H2: .. | I2: .. | J2: .. | K2: 23.343865 | L2: 23.833664 | M2: 29.512281 | N2: 36.861261 | O2: 36.607494 | P2: 34.959214 | Q2: 37.508189 | R2: .. | S2: .. | T2: .. | U2: .. | V2: ..
A3: Afghanistan | B3: AFG | C3: Access to electricity, rural (% of rural population) | D3: EG.ELC.ACCS.RU.ZS | E3: .. | F3: .. | G3: .. | H3: 2.1 | I3: 7.8 | J3: 15.4 | K3: 19.3 | L3: 25 | M3: 28 | N3: 97.1 | O3: 91.6 | P3: 97.1 | Q3: 97.1 | R3: 97.1 | S3: 81.7 | T3: 81.4 | U3: .. | V3: ..
A4: Afghanistan | B4: AFG | C4: Inflation, consumer prices (annual %) | D4: FP.CPI.TOTL.ZG | E4: .. | F4: .. | G4: .. | H4: .. | I4: .. | J4: 12.686269 | K4: 6.7845966 | L4: 8.6805708 | M4: 26.418664 | N4: 4.9759515 | O4: 0.62614915 | P4: 2.3023725 | Q4: 5.6018879 | R4: 5.1332034 | S4: 13.712102 | T4: -4.6447087 | U4: -6.6011856 | V4: ..
A5: Afghanistan | B5: AFG | C5: Inflation, GDP deflator (annual %) | D5: NY.GDP.DEFL.KD.ZG | E5: .. | F5: -11.774536 | G5: 6.125522 | H5: 11.655238 | I5: 11.271432 | J5: 10.912774 | K5: 7.1997513 | L5: 22.527756 | M5: 2.0962888 | N5: 2.4036562 | O5: 2.0713486 | P5: 6.5214798 | Q5: 6.9629463 | R5: 2.8389963 | S5: 9.4062393 | T5: 2.9236621 | U5: .. | V5: ..
A6: Afghanistan | B6: AFG | C6: Trade in services (% of GDP) | D6: BG.GSR.NFSV.GD.ZS | E6: .. | F6: .. | G6: .. | H6: .. | I6: .. | J6: .. | K6: .. | L6: .. | M6: 20.211726 | N6: 8.5806823 | O6: 11.638305 | P6: 9.918134 | Q6: 9.0438455 | R6: .. | S6: .. | T6: .. | U6: .. | V6: ..
A7: Albania | B7: ALB | C7: Broad money (% of GDP) | D7: FM.LBL.BMNY.GD.ZS | E7: 63.559947 | F7: 67.466477 | G7: 64.380525 | H7: 63.296713 | I7: 66.17596 | J7: 69.648068 | K7: 74.242141 | L7: 75.362987 | M7: 73.333402 | N7: 80.23339 | O7: 76.114797 | P7: 77.022846 | Q7: 87.983312 | R7: 84.766385 | S7: 77.185728 | T7: 71.828751 | U7: 70.9046 | V7: ..
A8: Albania | B8: ALB | C8: Access to electricity, rural (% of rural population) | D8: EG.ELC.ACCS.RU.ZS | E8: 100 | F8: 100 | G8: 100 | H8: 100 | I8: 100 | J8: 100 | K8: 100 | L8: 100 | M8: 100 | N8: 99.7 | O8: 100 | P8: 100 | Q8: 100 | R8: 100 | S8: 100 | T8: 100 | U8: .. | V8: ..
A9: Albania | B9: ALB | C9: Inflation, consumer prices (annual %) | D9: FP.CPI.TOTL.ZG | E9: 0.050018136 | F9: 3.1075883 | G9: 7.7705258 | H9: 0.48400261 | I9: 2.2800192 | J9: 2.366582 | K9: 2.3707283 | L9: 2.9326825 | M9: 3.3208709 | N9: 1.9866613 | O9: 2.0280596 | P9: 1.4110908 | Q9: 1.6208866 | R9: 2.0414716 | S9: 6.7252027 | T9: 4.7583456 | U9: 2.2158738 | V9: ..
A10: Albania | B10: ALB | C10: Inflation, GDP deflator (annual %) | D10: NY.GDP.DEFL.KD.ZG | E10: 5.9195735 | F10: 3.7659453 | G10: 3.9038814 | H10: 4.9374926 | I10: 3.0953665 | J10: 3.1437051 | K10: 2.6847683 | L10: 5.1495678 | M10: 3.4986391 | N10: 2.7250692 | O10: 1.4532872 | P10: 1.0006329 | Q10: 0.041064999 | R10: 3.4442568 | S10: 9.8616099 | T10: 5.733907 | U10: 2.3531809 | V10: ..
A11: Albania | B11: ALB | C11: Trade in services (% of GDP) | D11: BG.GSR.NFSV.GD.ZS | E11: 24.789583 | F11: 24.458841 | G11: 25.962551 | H11: 26.693325 | I11: 29.103663 | J11: 32.089796 | K11: 35.181631 | L11: 36.241931 | M11: 38.528108 | N11: 39.667021 | O11: 38.560048 | P11: 39.790381 | Q11: 25.556111 | R11: 33.896916 | S11: 39.58999 | T11: 45.057723 | U11: 43.852188 | V11: ..
A12: Algeria | B12: DZA | C12: Broad money (% of GDP) | D12: FM.LBL.BMNY.GD.ZS | E12: 37.829725 | F12: 52.381764 | G12: 57.87508 | H12: 58.015964 | I12: 55.021864 | J12: 51.892561 | K12: 54.464995 | L12: 60.717363 | M12: 59.709446 | N12: 71.063395 | O12: 73.341678 | P12: 71.505472 | Q12: 84.871789 | R12: 79.826032 | S12: 71.665003 | T12: 72.243913 | U12: 73.4802 | V12: ..
A13: Algeria | B13: DZA | C13: Access to electricity, rural (% of rural population) | D13: EG.ELC.ACCS.RU.ZS | E13: 97.4 | F13: 97.4 | G13: 97.4 | H13: 97.4 | I13: 97.4 | J13: 97.4 | K13: 97.4 | L13: 97.4 | M13: 97.9 | N13: 98.6 | O13: 98.9 | P13: 98.7 | Q13: 99.1 | R13: 99.3 | S13: 99.3 | T13: 100 | U13: .. | V13: ..
A14: Algeria | B14: DZA | C14: Inflation, consumer prices (annual %) | D14: FP.CPI.TOTL.ZG | E14: 0.33916319 | F14: 4.2259883 | G14: 1.4183019 | H14: 4.268954 | I14: 3.9618003 | J14: 1.3824466 | K14: 2.3114992 | L14: 3.6789957 | M14: 4.8585906 | N14: 5.5911159 | O14: 4.2699902 | P14: 1.9517682 | Q14: 2.4151309 | R14: 7.2260631 | S14: 9.2655155 | T14: 9.3221738 | U14: 4.0461146 | V14: ..
A15: Algeria | B15: DZA | C15: Inflation, GDP deflator (annual %) | D15: NY.GDP.DEFL.KD.ZG | E15: 22.678009 | F15: 8.014363 | G15: 1.3728559 | H15: 8.9424622 | I15: 11.446504 | J15: 12.361593 | K15: 10.781184 | L15: 7.0955158 | M15: 15.117882 | N15: 4.9380073 | O15: 6.1646784 | P15: 0.88299283 | Q15: -4.7113839 | R15: 15.9326 | S15: 22.920306 | T15: 1.0015314 | U15: 3.3749774 | V15: ..
A16: Algeria | B16: DZA | C16: Trade in services (% of GDP) | D16: BG.GSR.NFSV.GD.ZS | E16: .. | F16: .. | G16: .. | H16: .. | I16: .. | J16: 6.8474839 | K16: 6.0129541 | L16: 6.7620351 | M16: 8.0772087 | N16: 7.5752446 | O16: 7.7450915 | P16: 6.8114722 | Q16: 6.3240803 | R16: 5.4285891 | S16: 5.0696726 | T16: 4.8733878 | U16: 4.9582377 | V16: ..
A17: American Samoa | B17: ASM | C17: Broad money (% of GDP) | D17: FM.LBL.BMNY.GD.ZS | E17: .. | F17: .. | G17: .. | H17: .. | I17: .. | J17: .. | K17: .. | L17: .. | M17: .. | N17: .. | O17: .. | P17: .. | Q17: .. | R17: .. | S17: .. | T17: .. | U17: .. | V17: ..
A18: American Samoa | B18: ASM | C18: Access to electricity, rural (% of rural population) | D18: EG.ELC.ACCS.RU.ZS | E18: .. | F18: .. | G18: .. | H18: .. | I18: .. | J18: .. | K18: .. | L18: .. | M18: .. | N18: .. | O18: .. | P18: .. | Q18: .. | R18: .. | S18: .. | T18: .. | U18: .. | V18: ..
A19: American Samoa | B19: ASM | C19: Inflation, consumer prices (annual %) | D19: FP.CPI.TOTL.ZG | E19: .. | F19: .. | G19: .. | H19: .. | I19: .. | J19: .. | K19: .. | L19: .. | M19: .. | N19: .. | O19: .. | P19: .. | Q19: .. | R19: .. | S19: .. | T19: .. | U19: .. | V19: ..
A20: American Samoa | B20: ASM | C20: Inflation, GDP deflator (annual %) | D20: NY.GDP.DEFL.KD.ZG | E20: .. | F20: .. | G20: .. | H20: 1.3650529 | I20: -3.2590746 | J20: -1.3655834 | K20: 2.8136752 | L20: 3.1606122 | M20: 11.059335 | N20: -1.9408901 | O20: 1.6953611 | P20: 1.7482893 | Q20: 6.7287807 | R20: 4.8425557 | S20: 14.152765 | T20: .. | U20: .. | V20: ..
A21: American Samoa | B21: ASM | C21: Trade in services (% of GDP) | D21: BG.GSR.NFSV.GD.ZS | E21: .. | F21: .. | G21: .. | H21: .. | I21: .. | J21: .. | K21: .. | L21: .. | M21: .. | N21: .. | O21: .. | P21: .. | Q21: .. | R21: .. | S21: .. | T21: .. | U21: .. | V21: ..
A22: Andorra | B22: AND | C22: Broad money (% of GDP) | D22: FM.LBL.BMNY.GD.ZS | E22: .. | F22: .. | G22: .. | H22: .. | I22: .. | J22: .. | K22: .. | L22: .. | M22: .. | N22: .. | O22: .. | P22: .. | Q22: .. | R22: .. | S22: .. | T22: .. | U22: .. | V22: ..
A23: Andorra | B23: AND | C23: Access to electricity, rural (% of rural population) | D23: EG.ELC.ACCS.RU.ZS | E23: 100 | F23: 100 | G23: 100 | H23: 100 | I23: 100 | J23: 100 | K23: 100 | L23: 100 | M23: 100 | N23: 100 | O23: 100 | P23: 100 | Q23: 100 | R23: 100 | S23: 100 | T23: 100 | U23: .. | V23: ..
A24: Andorra | B24: AND | C24: Inflation, consumer prices (annual %) | D24: FP.CPI.TOTL.ZG | E24: .. | F24: .. | G24: .. | H24: .. | I24: .. | J24: .. | K24: .. | L24: .. | M24: .. | N24: .. | O24: .. | P24: .. | Q24: .. | R24: .. | S24: .. | T24: .. | U24: .. | V24: ..
A25: Andorra | B25: AND | C25: Inflation, GDP deflator (annual %) | D25: NY.GDP.DEFL.KD.ZG | E25: 28.741553 | F25: 3.0805352 | G25: 3.2395318 | H25: 3.1774842 | I25: 3.042424 | J25: 3.3961021 | K25: 3.4571841 | L25: 3.2112273 | M25: 2.2743383 | N25: 1.1365093 | O25: 1.0124785 | P25: 1.3747535 | Q25: 1.1137861 | R25: 2.5588607 | S25: 4.2366523 | T25: 6.2956008 | U25: 3.1436554 | V25: ..
A26: Andorra | B26: AND | C26: Trade in services (% of GDP) | D26: BG.GSR.NFSV.GD.ZS | E26: .. | F26: .. | G26: .. | H26: .. | I26: .. | J26: .. | K26: .. | L26: .. | M26: .. | N26: .. | O26: .. | P26: 87.579553 | Q26: 75.315498 | R26: 87.495948 | S26: 94.434915 | T26: 99.506414 | U26: 109.27757 | V26: ..
A27: Angola | B27: AGO | C27: Broad money (% of GDP) | D27: FM.LBL.BMNY.GD.ZS | E27: 17.280556 | F27: 21.135714 | G27: 14.171608 | H27: 11.828681 | I27: 11.823712 | J27: 11.877928 | K27: 14.532997 | L27: 18.271273 | M27: 28.249531 | N27: 28.10993 | O27: 27.201483 | P27: 29.587702 | Q27: 33.022497 | R27: 21.619274 | S27: 17.31393 | T27: 19.973799 | U27: 16.112562 | V27: ..
A28: Angola | B28: AGO | C28: Access to electricity, rural (% of rural population) | D28: EG.ELC.ACCS.RU.ZS | E28: 3.5 | F28: 9.5 | G28: 2.8 | H28: 2.3 | I28: 1.7 | J28: 1 | K28: 0.7 | L28: .. | M28: 6.6 | N28: .. | O28: 7.3 | P28: .. | Q28: .. | R28: .. | S28: .. | T28: .. | U28: .. | V28: ..
A29: Angola | B29: AGO | C29: Inflation, consumer prices (annual %) | D29: FP.CPI.TOTL.ZG | E29: 324.99687 | F29: 152.56102 | G29: 108.89744 | H29: 98.224144 | I29: 43.542107 | J29: 22.953514 | K29: 13.30521 | L29: 12.251497 | M29: 12.475829 | N29: 29.84448 | O29: 19.628938 | P29: 17.080954 | Q29: 22.271539 | R29: 25.754295 | S29: 21.35529 | T29: 13.644102 | U29: 28.240495 | V29: ..
A30: Angola | B30: AGO | C30: Inflation, GDP deflator (annual %) | D30: NY.GDP.DEFL.KD.ZG | E30: 418.01899 | F30: 106.35213 | G30: 236.34574 | H30: 94.607261 | I30: 33.382324 | J30: 40.136451 | K30: 16.814418 | L30: 5.1745141 | M30: 19.427383 | N30: 23.712806 | O30: 25.194156 | P30: 19.865888 | Q30: 16.063581 | R30: 35.653692 | S30: 18.121772 | T30: 17.929233 | U30: 24.604584 | V30: ..
A31: Angola | B31: AGO | C31: Trade in services (% of GDP) | D31: BG.GSR.NFSV.GD.ZS | E31: 32.495965 | F31: 41.636046 | G31: 20.384059 | H31: 17.314894 | I31: 18.98474 | J31: 16.831823 | K31: 15.336499 | L31: 17.735958 | M31: 22.743898 | N31: 17.514116 | O31: 11.976649 | P31: 10.685468 | Q31: 9.6335065 | R31: 8.9792802 | S31: 8.6722768 | T31: 8.0983565 | U31: 8.5358912 | V31: ..
A32: Antigua and Barbuda | B32: ATG | C32: Broad money (% of GDP) | D32: FM.LBL.BMNY.GD.ZS | E32: 72.41106 | F32: 77.993139 | G32: 80.309875 | H32: 87.924802 | I32: 86.205501 | J32: 84.187929 | K32: 82.432029 | L32: 80.462846 | M32: 79.371188 | N32: 87.31163 | O32: 86.469038 | P32: 82.844155 | Q32: 92.484771 | R32: 92.787136 | S32: 83.302316 | T32: 80.109967 | U32: 76.142397 | V32: ..
A33: Antigua and Barbuda | B33: ATG | C33: Access to electricity, rural (% of rural population) | D33: EG.ELC.ACCS.RU.ZS | E33: 96.6 | F33: 96.7 | G33: 100 | H33: 97 | I33: 97.1 | J33: 100 | K33: 100 | L33: 100 | M33: 100 | N33: 100 | O33: 100 | P33: 100 | Q33: 100 | R33: 100 | S33: 100 | T33: 100 | U33: .. | V33: ..
A34: Antigua and Barbuda | B34: ATG | C34: Inflation, consumer prices (annual %) | D34: FP.CPI.TOTL.ZG | E34: 0.7717798 | F34: 1.4027966 | G34: 2.407658 | H34: 1.9935306 | I34: 2.0300776 | J34: 2.098752 | K34: 1.7877854 | L34: 1.4160526 | M34: 5.3338064 | N34: 2.4324879 | O34: 1.2071579 | P34: 1.431356 | Q34: 0.62598971 | R34: 2.0629964 | S34: 7.5310783 | T34: 5.0671387 | U34: 6.198867 | V34: ..
A35: Antigua and Barbuda | B35: ATG | C35: Inflation, GDP deflator (annual %) | D35: NY.GDP.DEFL.KD.ZG | E35: 1.5355154 | F35: 2.063778 | G35: 1.2744512 | H35: -0.47933004 | I35: 2.3486479 | J35: 4.6784983 | K35: 1.1176722 | L35: 4.3693205 | M35: 4.7383582 | N35: 0.31653179 | O35: 1.4442184 | P35: 0.71233504 | Q35: 0.78165357 | R35: 4.9192746 | S35: 6.7802747 | T35: 4.9119408 | U35: 6.1804095 | V35: ..
A36: Antigua and Barbuda | B36: ATG | C36: Trade in services (% of GDP) | D36: BG.GSR.NFSV.GD.ZS | E36: 91.233804 | F36: 93.789824 | G36: 95.669204 | H36: 100.42616 | I36: 102.10806 | J36: 98.060973 | K36: 90.729591 | L36: 80.34372 | M36: 88.065746 | N36: 93.064846 | O36: 90.467962 | P36: 98.392769 | Q36: 61.566428 | R36: 62.27681 | S36: 81.339268 | T36: 80.300848 | U36: 81.448729 | V36: ..
A37: Argentina | B37: ARG | C37: Broad money (% of GDP) | D37: FM.LBL.BMNY.GD.ZS | E37: 31.848621 | F37: 27.139252 | G37: 27.92707 | H37: 30.104057 | I37: 28.325646 | J37: 28.66331 | K37: 28.049612 | L37: 27.864316 | M37: 23.493673 | N37: 28.49528 | O37: 30.410756 | P37: 26.183039 | Q37: 34.505263 | R37: 30.730954 | S37: 32.191836 | T37: 35.821852 | U37: 26.333931 | V37: ..
A38: Argentina | B38: ARG | C38: Access to electricity, rural (% of rural population) | D38: EG.ELC.ACCS.RU.ZS | E38: 91.8 | F38: 88.6 | G38: 92.6 | H38: 92.9 | I38: 93.2 | J38: 93.4 | K38: 93.6 | L38: 93.8 | M38: 94 | N38: 100 | O38: 99.9 | P38: 100 | Q38: 100 | R38: 100 | S38: 100 | T38: 100 | U38: .. | V38: ..
A39: Argentina | B39: ARG | C39: Inflation, consumer prices (annual %) | D39: FP.CPI.TOTL.ZG | E39: .. | F39: .. | G39: .. | H39: .. | I39: .. | J39: .. | K39: .. | L39: .. | M39: .. | N39: .. | O39: 34.277224 | P39: 53.548304 | Q39: 42.015095 | R39: 48.409379 | S39: 72.430758 | T39: 133.48894 | U39: 219.88393 | V39: ..
A40: Argentina | B40: ARG | C40: Inflation, GDP deflator (annual %) | D40: NY.GDP.DEFL.KD.ZG | E40: 1.0372871 | F40: -1.0957677 | G40: 30.555204 | H40: 10.495703 | I40: 18.363354 | J40: 10.317511 | K40: 13.741052 | L40: 14.939925 | M40: 23.171165 | N40: 26.006379 | O40: 42.033669 | P40: 49.195579 | Q40: 40.083088 | R40: 53.802088 | S40: 68.993827 | T40: 136.74236 | U40: 207.60524 | V40: ..
A41: Argentina | B41: ARG | C41: Trade in services (% of GDP) | D41: BG.GSR.NFSV.GD.ZS | E41: 4.9539896 | F41: 4.8478054 | G41: 8.4772621 | H41: 7.8189173 | I41: 7.094095 | J41: 7.0218144 | K41: 7.1315716 | L41: 7.3289458 | M41: 6.934055 | N41: 6.3247431 | O41: 7.5491792 | P41: 7.6935019 | Q41: 5.5788172 | R41: 4.7018602 | S41: 5.616236 | T41: 6.0210788 | U41: 6.2791023 | V41: ..
A42: Armenia | B42: ARM | C42: Broad money (% of GDP) | D42: FM.LBL.BMNY.GD.ZS | E42: 14.704511 | F42: 13.449648 | G42: 15.551599 | H42: 14.391959 | I42: 14.986981 | J42: 16.298392 | K42: 18.28698 | L42: 21.952399 | M42: 19.835837 | N42: 46.415424 | O42: 46.12064 | P42: 47.154402 | Q42: 54.385167 | R42: 54.386826 | S42: 51.931999 | T42: 54.600939 | U42: 57.791584 | V42: ..
A43: Armenia | B43: ARM | C43: Access to electricity, rural (% of rural population) | D43: EG.ELC.ACCS.RU.ZS | E43: 98.5 | F43: 100 | G43: 95.8 | H43: 98.9 | I43: 98.9 | J43: 99.6 | K43: 98.9 | L43: 98.9 | M43: 98.9 | N43: 99.5 | O43: 99.9 | P43: 100 | Q43: 100 | R43: 100 | S43: 100 | T43: 100 | U43: .. | V43: ..
A44: Armenia | B44: ARM | C44: Inflation, consumer prices (annual %) | D44: FP.CPI.TOTL.ZG | E44: -0.79088377 | F44: 3.1459046 | G44: 1.0600493 | H44: 4.7215534 | I44: 6.9612614 | J44: 0.638928 | K44: 2.8923566 | L44: 4.4073609 | M44: 8.9499534 | N44: 0.96955327 | O44: 2.5202338 | P44: 1.4434466 | Q44: 1.2114358 | R44: 7.1848363 | S44: 8.6409111 | T44: 1.9804188 | U44: 0.26951198 | V44: ..
A45: Armenia | B45: ARM | C45: Inflation, GDP deflator (annual %) | D45: NY.GDP.DEFL.KD.ZG | E45: -1.373676 | F45: 4.0279695 | G45: 2.357399 | H45: 4.5985157 | I45: 6.2785941 | J45: 3.2087567 | K45: 4.6180125 | L45: 4.2778755 | M45: 5.9895624 | N45: 2.1506419 | O45: 2.7877095 | P45: 1.0656226 | Q45: 1.8065927 | R45: 6.9005137 | S45: 7.9858785 | T45: 3.1002763 | U45: 1.4010608 | V45: ..
A46: Armenia | B46: ARM | C46: Trade in services (% of GDP) | D46: BG.GSR.NFSV.GD.ZS | E46: 18.083026 | F46: 23.040664 | G46: 20.876744 | H46: 21.73343 | I46: 23.725101 | J46: 20.573962 | K46: 19.982312 | L46: 18.665737 | M46: 17.028239 | N46: 33.693061 | O46: 35.27009 | P46: 36.809172 | Q46: 17.02325 | R46: 22.602958 | S46: 36.652843 | T46: 39.769746 | U46: 39.479105 | V46: ..
A47: Aruba | B47: ABW | C47: Broad money (% of GDP) | D47: FM.LBL.BMNY.GD.ZS | E47: 51.834542 | F47: 54.220484 | G47: 57.909275 | H47: 60.51173 | I47: 56.620832 | J47: 57.44679 | K47: 56.196562 | L47: 53.544999 | M47: 58.783489 | N47: 76.595454 | O47: 74.635392 | P47: 76.278006 | Q47: 108.44424 | R47: 104.04676 | S47: 93.17277 | T47: 81.401003 | U47: .. | V47: ..
A48: Aruba | B48: ABW | C48: Access to electricity, rural (% of rural population) | D48: EG.ELC.ACCS.RU.ZS | E48: 100 | F48: 100 | G48: 100 | H48: 100 | I48: 100 | J48: 100 | K48: 100 | L48: 100 | M48: 100 | N48: 100 | O48: 100 | P48: 100 | Q48: 100 | R48: 100 | S48: 100 | T48: 100 | U48: .. | V48: ..
A49: Aruba | B49: ABW | C49: Inflation, consumer prices (annual %) | D49: FP.CPI.TOTL.ZG | E49: 4.0440213 | F49: 2.8836043 | G49: 3.3152468 | H49: 3.6563651 | I49: 2.5291295 | J49: 3.3977868 | K49: 3.6080244 | L49: 5.3925678 | M49: 8.9559871 | N49: -1.0282818 | O49: 3.6260414 | P49: 4.257462 | Q49: .. | R49: .. | S49: .. | T49: .. | U49: .. | V49: ..
A50: Aruba | B50: ABW | C50: Inflation, GDP deflator (annual %) | D50: NY.GDP.DEFL.KD.ZG | E50: 1.0361008 | F50: -2.8355024 | G50: 4.4346881 | H50: 3.0490462 | I50: 2.8099097 | J50: 5.0674972 | K50: 3.4843462 | L50: 5.166893 | M50: 4.262449 | N50: 0.14764948 | O50: 2.6448143 | P50: 0.91361696 | Q50: -2.9616355 | R50: 1.6021428 | S50: 4.2890599 | T50: 7.1090373 | U50: 4.1442906 | V50: ..
A51: Aruba | B51: ABW | C51: Trade in services (% of GDP) | D51: BG.GSR.NFSV.GD.ZS | E51: 118.96388 | F51: 128.63151 | G51: 93.659196 | H51: 114.19502 | I51: 84.203573 | J51: 85.570077 | K51: 83.587522 | L51: 84.277458 | M51: 84.311028 | N51: 99.769031 | O51: 104.30372 | P51: 103.58523 | Q51: 86.504446 | R51: 102.90089 | S51: 111.48201 | T51: 108.70079 | U51: .. | V51: ..
A52: Australia | B52: AUS | C52: Broad money (% of GDP) | D52: FM.LBL.BMNY.GD.ZS | E52: 67.401739 | F52: 70.030318 | G52: 70.117851 | H52: 74.471442 | I52: 77.124004 | J52: 78.131886 | K52: 83.223036 | L52: 90.303231 | M52: 97.50994 | N52: 116.18259 | O52: 113.5217 | P52: 122.44551 | Q52: 136.81501 | R52: 138.8592 | S52: 133.99141 | T52: 126.28599 | U52: 129.41494 | V52: ..
A53: Australia | B53: AUS | C53: Access to electricity, rural (% of rural population) | D53: EG.ELC.ACCS.RU.ZS | E53: 100 | F53: 100 | G53: 100 | H53: 100 | I53: 100 | J53: 100 | K53: 100 | L53: 100 | M53: 100 | N53: 100 | O53: 100 | P53: 100 | Q53: 100 | R53: 100 | S53: 100 | T53: 100 | U53: .. | V53: ..
A54: Australia | B54: AUS | C54: Inflation, consumer prices (annual %) | D54: FP.CPI.TOTL.ZG | E54: 4.4574371 | F54: 4.40713 | G54: 2.9815712 | H54: 2.7325975 | I54: 2.3432569 | J54: 2.6918295 | K54: 3.555287 | L54: 2.3276144 | M54: 4.3502973 | N54: 1.9486431 | O54: 1.9114 | P54: 1.6107709 | Q54: 0.84690073 | R54: 2.8639128 | S54: 6.5940966 | T54: 5.5970179 | U54: 3.1665667 | V54: ..
A55: Australia | B55: AUS | C55: Inflation, GDP deflator (annual %) | D55: NY.GDP.DEFL.KD.ZG | E55: 2.5539837 | F55: 4.6410706 | G55: 2.8403056 | H55: 2.987661 | I55: 3.2309789 | J55: 3.8250404 | K55: 5.1116639 | L55: 4.9846061 | M55: 4.5677065 | N55: 3.6462336 | O55: 1.8461756 | P55: 3.4766003 | Q55: 1.8658341 | R55: 3.0606698 | S55: 7.1995443 | T55: 6.4594411 | U55: 2.5883843 | V55: ..
A56: Australia | B56: AUS | C56: Trade in services (% of GDP) | D56: BG.GSR.NFSV.GD.ZS | E56: 9.4239941 | F56: 9.3017987 | G56: 9.5581644 | H56: 9.7856803 | I56: 9.1152351 | J56: 8.8348398 | K56: 9.5649144 | L56: 10.478092 | M56: 9.7062707 | N56: 10.330207 | O56: 10.3696 | P56: 10.590088 | Q56: 7.2657978 | R56: 6.1475913 | S56: 7.8232263 | T56: 10.259152 | U56: 11.025718 | V56: ..
A57: Austria | B57: AUT | C57: Broad money (% of GDP) | D57: FM.LBL.BMNY.GD.ZS | E57: .. | F57: .. | G57: .. | H57: .. | I57: .. | J57: .. | K57: .. | L57: .. | M57: .. | N57: .. | O57: .. | P57: .. | Q57: .. | R57: .. | S57: .. | T57: .. | U57: .. | V57: ..
A58: Austria | B58: AUT | C58: Access to electricity, rural (% of rural population) | D58: EG.ELC.ACCS.RU.ZS | E58: 100 | F58: 100 | G58: 100 | H58: 100 | I58: 100 | J58: 100 | K58: 100 | L58: 100 | M58: 100 | N58: 100 | O58: 100 | P58: 100 | Q58: 100 | R58: 100 | S58: 100 | T58: 100 | U58: .. | V58: ..
A59: Austria | B59: AUT | C59: Inflation, consumer prices (annual %) | D59: FP.CPI.TOTL.ZG | E59: 2.3448629 | F59: 2.6500008 | G59: 1.8103579 | H59: 1.3555537 | I59: 2.0612062 | J59: 2.2991379 | K59: 1.4415485 | L59: 2.1685553 | M59: 3.2159503 | N59: 2.0812691 | O59: 1.9983798 | P59: 1.5308956 | Q59: 1.3819106 | R59: 2.7666667 | S59: 8.5468699 | T59: 7.8141342 | U59: 2.9379157 | V59: ..
A60: Austria | B60: AUT | C60: Inflation, GDP deflator (annual %) | D60: NY.GDP.DEFL.KD.ZG | E60: 1.3673138 | F60: 1.9372838 | G60: 1.1042153 | H60: 1.2670027 | I60: 1.727962 | J60: 2.5319678 | K60: 2.04462 | L60: 2.2592709 | M60: 1.9337907 | N60: 0.97531791 | O60: 1.81048 | P60: 1.473685 | Q60: 2.5931325 | R60: 1.801873 | S60: 5.0234316 | T60: 7.1747129 | U60: 4.0868124 | V60: ..
A61: Austria | B61: AUT | C61: Trade in services (% of GDP) | D61: BG.GSR.NFSV.GD.ZS | E61: .. | F61: .. | G61: .. | H61: .. | I61: .. | J61: 25.711587 | K61: 24.204649 | L61: 24.692772 | M61: 25.24307 | N61: 29.709443 | O61: 30.970268 | P61: 32.224107 | Q61: 27.860711 | R61: 28.771994 | S61: 33.599617 | T61: 33.812291 | U61: 35.000518 | V61: ..
A62: Azerbaijan | B62: AZE | C62: Broad money (% of GDP) | D62: FM.LBL.BMNY.GD.ZS | E62: 16.290824 | F62: 12.931625 | G62: 12.979951 | H62: 14.28476 | I62: 17.653559 | J62: 14.683353 | K62: 18.323536 | L62: 20.793923 | M62: 21.162979 | N62: 32.375295 | O62: 30.040944 | P62: 35.24743 | Q62: 40.212967 | R62: 37.173232 | S62: 31.965415 | T62: 36.606871 | U62: 36.802242 | V62: ..
A63: Azerbaijan | B63: AZE | C63: Access to electricity, rural (% of rural population) | D63: EG.ELC.ACCS.RU.ZS | E63: 98.1 | F63: 97.6 | G63: 100 | H63: 98.1 | I63: 98.4 | J63: 98.6 | K63: 99.2 | L63: 99.2 | M63: 99.5 | N63: 100 | O63: 100 | P63: 100 | Q63: 100 | R63: 100 | S63: 100 | T63: 100 | U63: .. | V63: ..
A64: Azerbaijan | B64: AZE | C64: Inflation, consumer prices (annual %) | D64: FP.CPI.TOTL.ZG | E64: 1.805003 | F64: 1.5471959 | G64: 2.7711647 | H64: 2.2338649 | I64: 6.7089304 | J64: 9.6795073 | K64: 8.3289248 | L64: 16.699755 | M64: 20.849087 | N64: 12.935918 | O64: 2.2685469 | P64: 2.6105718 | Q64: 2.7598095 | R64: 6.6502991 | S64: 13.852259 | T64: 8.7854305 | U64: 2.2121719 | V64: ..
A65: Azerbaijan | B65: AZE | C65: Inflation, GDP deflator (annual %) | D65: NY.GDP.DEFL.KD.ZG | E65: 12.492774 | F65: 2.5150102 | G65: 4.2143862 | H65: 6.9614657 | I65: 9.2519651 | J65: 14.723497 | K65: 11.329188 | L65: 20.582483 | M65: 27.971036 | N65: 16.226205 | O65: 12.184433 | P65: -0.22165278 | Q65: -7.4936335 | R65: 21.588837 | S65: 37.270721 | T65: -9.322615 | U65: -1.4081721 | V65: ..
A66: Azerbaijan | B66: AZE | C66: Trade in services (% of GDP) | D66: BG.GSR.NFSV.GD.ZS | E66: 14.115897 | F66: 16.726703 | G66: 26.714714 | H66: 34.006206 | I66: 37.699206 | J66: 25.671209 | K66: 18.606034 | L66: 14.646605 | M66: 11.431132 | N66: 31.214201 | O66: 24.480099 | P66: 21.430483 | Q66: 19.163302 | R66: 17.901672 | S66: 16.283493 | T66: 20.579101 | U66: 24.614662 | V66: ..
A67: Bahamas, The | B67: BHS | C67: Broad money (% of GDP) | D67: FM.LBL.BMNY.GD.ZS | E67: 42.919741 | F67: 43.720538 | G67: 42.167915 | H67: 43.772949 | I67: 46.831189 | J67: 47.784714 | K67: 49.816814 | L67: 52.72293 | M67: 55.980429 | N67: 60.361912 | O67: 59.225454 | P67: 63.240797 | Q67: 80.805236 | R67: 72.587304 | S67: 68.758905 | T67: .. | U67: .. | V67: ..
A68: Bahamas, The | B68: BHS | C68: Access to electricity, rural (% of rural population) | D68: EG.ELC.ACCS.RU.ZS | E68: 100 | F68: 100 | G68: 100 | H68: 100 | I68: 100 | J68: 100 | K68: 100 | L68: 100 | M68: 100 | N68: 100 | O68: 100 | P68: 100 | Q68: 100 | R68: 100 | S68: 100 | T68: 100 | U68: .. | V68: ..
A69: Bahamas, The | B69: BHS | C69: Inflation, consumer prices (annual %) | D69: FP.CPI.TOTL.ZG | E69: 1.6063294 | F69: 2.0449898 | G69: 2.1735779 | H69: 3.0250453 | I69: 0.98191404 | J69: 1.5916062 | K69: 2.3898263 | L69: 2.4925779 | M69: 4.48956 | N69: 1.518207 | O69: 2.2658635 | P69: 2.4912353 | Q69: 0.038521098 | R69: 2.9049126 | S69: 5.6054063 | T69: 3.0529158 | U69: 0.40916249 | V69: ..
A70: Bahamas, The | B70: BHS | C70: Inflation, GDP deflator (annual %) | D70: NY.GDP.DEFL.KD.ZG | E70: 0.92270743 | F70: 0.3531507 | G70: 3.9604743 | H70: 1.1548791 | I70: 1.1949976 | J70: 5.0560084 | K70: 0.82819451 | L70: 2.9479658 | M70: 1.4886107 | N70: 1.3471328 | O70: 0.5792607 | P70: 4.4470842 | Q70: -2.3236661 | R70: -1.2201754 | S70: 4.1241697 | T70: 6.6401176 | U70: 0.28842138 | V70: ..
A71: Bahamas, The | B71: BHS | C71: Trade in services (% of GDP) | D71: BG.GSR.NFSV.GD.ZS | E71: 37.131321 | F71: 33.393325 | G71: 34.656976 | H71: 35.479685 | I71: 38.379555 | J71: 38.605489 | K71: 39.803782 | L71: 39.355773 | M71: 37.400974 | N71: 40.207181 | O71: 46.099908 | P71: 47.44241 | Q71: 25.512049 | R71: 36.339383 | S71: 47.308994 | T71: 48.106209 | U71: 52.863799 | V71: ..
A72: Bahrain | B72: BHR | C72: Broad money (% of GDP) | D72: FM.LBL.BMNY.GD.ZS | E72: 63.289951 | F72: 69.806373 | G72: 72.067056 | H72: 66.396318 | I72: 58.236756 | J72: 58.504141 | K72: 58.005487 | L72: 68.808687 | M72: 69.599578 | N72: .. | O72: .. | P72: .. | Q72: .. | R72: .. | S72: .. | T72: .. | U72: .. | V72: ..
A73: Bahrain | B73: BHR | C73: Access to electricity, rural (% of rural population) | D73: EG.ELC.ACCS.RU.ZS | E73: 100 | F73: 100 | G73: 100 | H73: 100 | I73: 100 | J73: 100 | K73: 100 | L73: 100 | M73: 100 | N73: 100 | O73: 100 | P73: 100 | Q73: 100 | R73: 100 | S73: 100 | T73: 100 | U73: .. | V73: ..
A74: Bahrain | B74: BHR | C74: Inflation, consumer prices (annual %) | D74: FP.CPI.TOTL.ZG | E74: -0.70485295 | F74: -1.2075718 | G74: -0.49554014 | H74: 1.5936255 | I74: 2.3529412 | J74: 2.5862069 | K74: 2.0074697 | L74: 3.2566667 | M74: 3.5260032 | N74: 1.3867183 | O74: 2.0876694 | P74: 1.00582 | Q74: -2.3177063 | R74: -0.60631939 | S74: 3.625741 | T74: 0.074620678 | U74: 0.91963546 | V74: ..
A75: Bahrain | B75: BHR | C75: Inflation, GDP deflator (annual %) | D75: NY.GDP.DEFL.KD.ZG | E75: 14.322524 | F75: -3.3638285 | G75: 3.4143496 | H75: 8.6025813 | I75: 10.991083 | J75: 13.734968 | K75: 8.8424373 | L75: 8.4356319 | M75: 11.365092 | N75: 4.6158342 | O75: 4.2127135 | P75: 0.1648022 | Q75: -5.8288485 | R75: 9.2084026 | S75: 7.1348888 | T75: -4.2843722 | U75: -0.60191753 | V75: ..
A76: Bahrain | B76: BHR | C76: Trade in services (% of GDP) | D76: BG.GSR.NFSV.GD.ZS | E76: 19.176375 | F76: 20.011963 | G76: 21.954672 | H76: 20.370201 | I76: 30.617739 | J76: 28.625506 | K76: 27.384898 | L76: 24.766599 | M76: 23.125381 | N76: 51.4654 | O76: 50.176911 | P76: 50.387954 | Q76: 59.015432 | R76: 58.312364 | S76: 54.894357 | T76: 59.735299 | U76: 62.405226 | V76: ..
A77: Bangladesh | B77: BGD | C77: Broad money (% of GDP) | D77: FM.LBL.BMNY.GD.ZS | E77: 30.553989 | F77: 40.267148 | G77: 42.740177 | H77: 43.988577 | I77: 45.622994 | J77: 47.421068 | K77: 50.475999 | L77: 50.281912 | M77: 51.187627 | N77: 55.837542 | O77: 54.832556 | P77: 54.870254 | Q77: 57.763065 | R77: 56.637279 | S77: 54.117701 | T77: 51.218563 | U77: 48.797431 | V77: ..
A78: Bangladesh | B78: BGD | C78: Access to electricity, rural (% of rural population) | D78: EG.ELC.ACCS.RU.ZS | E78: 16.8 | F78: 21.5 | G78: 24.3 | H78: 27.1 | I78: 27.9 | J78: 30.2 | K78: 40.2 | L78: 32.5 | M78: 41.7 | N78: 81.6 | O78: 81.3 | P78: 88.9 | Q78: 95.2 | R78: 98.5 | S78: 99.2 | T78: 99.6 | U78: .. | V78: ..
A79: Bangladesh | B79: BGD | C79: Inflation, consumer prices (annual %) | D79: FP.CPI.TOTL.ZG | E79: 2.2082562 | F79: 2.0071737 | G79: 3.3325649 | H79: 5.6687077 | I79: 7.5875364 | J79: 7.0466182 | K79: 6.7652612 | L79: 9.106985 | M79: 8.9019449 | N79: 5.7020702 | O79: 5.5436214 | P79: 5.5919964 | Q79: 5.6910747 | R79: 5.5456543 | S79: 7.6969544 | T79: 9.883503 | U79: 10.465748 | V79: ..
A80: Bangladesh | B80: BGD | C80: Inflation, GDP deflator (annual %) | D80: NY.GDP.DEFL.KD.ZG | E80: 3.4466593 | F80: 3.2611601 | G80: 3.8928674 | H80: 5.8158166 | I80: 4.5621364 | J80: 4.5863607 | K80: 5.8759358 | L80: 6.4712601 | M80: 7.8609661 | N80: 5.0475976 | O80: 5.8055388 | P80: 3.6581376 | Q80: 3.8410634 | R80: 4.1211747 | S80: 5.0490219 | T80: 6.897124 | U80: 6.8828546 | V80: ..
A81: Bangladesh | B81: BGD | C81: Trade in services (% of GDP) | D81: BG.GSR.NFSV.GD.ZS | E81: 4.6159307 | F81: 4.2441863 | G81: 4.2140007 | H81: 4.70573 | I81: 4.7469024 | J81: 5.5579433 | K81: 5.8386502 | L81: 6.3257435 | M81: 6.4967124 | N81: 4.2106393 | O81: 4.6879434 | P81: 4.4903496 | Q81: 3.7292011 | R81: 4.4059073 | S81: 4.289407 | T81: 3.595622 | U81: 4.3911633 | V81: ..
A82: Barbados | B82: BRB | C82: Broad money (% of GDP) | D82: FM.LBL.BMNY.GD.ZS | E82: 65.254944 | F82: 87.733639 | G82: 99.528135 | H82: 100.78157 | I82: 104.92016 | J82: 110.59622 | K82: 105.51753 | L82: 115.0745 | M82: 113.61676 | N82: 99.737794 | O82: 94.318599 | P82: 94.593207 | Q82: 115.62175 | R82: 111.39023 | S82: 101.36865 | T82: 97.526438 | U82: .. | V82: ..
A83: Barbados | B83: BRB | C83: Access to electricity, rural (% of rural population) | D83: EG.ELC.ACCS.RU.ZS | E83: 100 | F83: 100 | G83: 100 | H83: 100 | I83: 100 | J83: 99.9 | K83: 100 | L83: 100 | M83: 100 | N83: 100 | O83: 100 | P83: 100 | Q83: 100 | R83: 100 | S83: 100 | T83: 100 | U83: .. | V83: ..
A84: Barbados | B84: BRB | C84: Inflation, consumer prices (annual %) | D84: FP.CPI.TOTL.ZG | E84: 2.435813 | F84: 2.5778349 | G84: 0.12524946 | H84: 1.6194332 | I84: 1.3944223 | J84: 6.0821873 | K84: 7.3076626 | L84: 4.0342298 | M84: 8.1081081 | N84: 4.6601846 | O84: 3.1060057 | P84: 1.6766247 | Q84: .. | R84: .. | S84: .. | T84: 3.1871891 | U84: 1.4464366 | V84: ..
A85: Barbados | B85: BRB | C85: Inflation, GDP deflator (annual %) | D85: NY.GDP.DEFL.KD.ZG | E85: -1.3228392 | F85: 2.2553897 | G85: 0.90785578 | H85: 1.1158721 | I85: 5.8281445 | J85: 6.667725 | K85: 4.0963702 | L85: 8.6122611 | M85: 1.8069353 | N85: -0.55379233 | O85: 6.9745867 | P85: 2.4308866 | Q85: 2.4699444 | R85: 10.102764 | S85: -1.2507344 | T85: 1.9433833 | U85: 1.290096 | V85: ..
A86: Barbados | B86: BRB | C86: Trade in services (% of GDP) | D86: BG.GSR.NFSV.GD.ZS | E86: 47.949535 | F86: 44.939249 | G86: 45.175969 | H86: 48.881924 | I86: 44.328752 | J86: 46.517855 | K86: 45.242806 | L86: 43.462468 | M86: 45.535744 | N86: 38.88392 | O86: .. | P86: .. | Q86: .. | R86: .. | S86: .. | T86: .. | U86: .. | V86: ..
A87: Belarus | B87: BLR | C87: Broad money (% of GDP) | D87: FM.LBL.BMNY.GD.ZS | E87: 17.667502 | F87: 14.920271 | G87: 14.608985 | H87: 16.118616 | I87: 17.6819 | J87: 19.319424 | K87: 22.084683 | L87: 25.220956 | M87: 23.854619 | N87: 37.68248 | O87: 35.344191 | P87: 36.004556 | Q87: 33.930261 | R87: 30.728037 | S87: .. | T87: .. | U87: .. | V87: ..
A88: Belarus | B88: BLR | C88: Access to electricity, rural (% of rural population) | D88: EG.ELC.ACCS.RU.ZS | E88: 79.4 | F88: 80.2 | G88: 81 | H88: 81.8 | I88: 82.6 | J88: 83.3 | K88: 84.2 | L88: 85 | M88: 85.9 | N88: 96.6 | O88: 98.2 | P88: 100 | Q88: 100 | R88: 100 | S88: 100 | T88: 100 | U88: .. | V88: ..
A89: Belarus | B89: BLR | C89: Inflation, consumer prices (annual %) | D89: FP.CPI.TOTL.ZG | E89: 168.62024 | F89: 61.134933 | G89: 42.537548 | H89: 28.39784 | I89: 18.108242 | J89: 10.338879 | K89: 6.997129 | L89: 8.4267527 | M89: 14.837876 | N89: 6.0318373 | O89: 4.8723022 | P89: 5.598156 | Q89: 5.5481436 | R89: 9.4602839 | S89: 15.209675 | T89: 5.000599 | U89: 5.7853191 | V89: ..
A90: Belarus | B90: BLR | C90: Inflation, GDP deflator (annual %) | D90: NY.GDP.DEFL.KD.ZG | E90: 185.29076 | F90: 79.534572 | G90: 44.893739 | H90: 30.685322 | I90: 22.675122 | J90: 18.972161 | K90: 10.748616 | L90: 12.872702 | M90: 21.213536 | N90: 8.6231474 | O90: 12.13923 | P90: 8.5769891 | Q90: 11.877465 | R90: 15.326574 | S90: 14.884862 | T90: 8.0467622 | U90: 8.7678713 | V90: ..
A91: Belarus | B91: BLR | C91: Trade in services (% of GDP) | D91: BG.GSR.NFSV.GD.ZS | E91: 12.28325 | F91: 15.807596 | G91: 15.121034 | H91: 14.451813 | I91: 12.80164 | J91: 11.530253 | K91: 11.862487 | L91: 12.506043 | M91: 12.15678 | N91: 23.264149 | O91: 23.727897 | P91: 24.055362 | Q91: 22.216438 | R91: 22.977149 | S91: 20.019321 | T91: 20.463076 | U91: 22.408696 | V91: ..
A92: Belgium | B92: BEL | C92: Broad money (% of GDP) | D92: FM.LBL.BMNY.GD.ZS | E92: .. | F92: .. | G92: .. | H92: .. | I92: .. | J92: .. | K92: .. | L92: .. | M92: .. | N92: .. | O92: .. | P92: .. | Q92: .. | R92: .. | S92: .. | T92: .. | U92: .. | V92: ..
A93: Belgium | B93: BEL | C93: Access to electricity, rural (% of rural population) | D93: EG.ELC.ACCS.RU.ZS | E93: 100 | F93: 100 | G93: 100 | H93: 100 | I93: 100 | J93: 100 | K93: 100 | L93: 100 | M93: 100 | N93: 100 | O93: 100 | P93: 100 | Q93: 100 | R93: 100 | S93: 100 | T93: 100 | U93: .. | V93: ..
A94: Belgium | B94: BEL | C94: Inflation, consumer prices (annual %) | D94: FP.CPI.TOTL.ZG | E94: 2.5445178 | F94: 2.4692582 | G94: 1.6452144 | H94: 1.588964 | I94: 2.0972831 | J94: 2.7814326 | K94: 1.7912077 | L94: 1.8230563 | M94: 4.4894442 | N94: 2.1259709 | O94: 2.053165 | P94: 1.4368196 | Q94: 0.74079181 | R94: 2.4402485 | S94: 9.5975117 | T94: 4.0490108 | U94: 3.1434914 | V94: ..
A95: Belgium | B95: BEL | C95: Inflation, GDP deflator (annual %) | D95: NY.GDP.DEFL.KD.ZG | E95: 2.0145921 | F95: 1.9828181 | G95: 1.6399981 | H95: 1.8501163 | I95: 1.9149886 | J95: 2.0830733 | K95: 2.2647162 | L95: 1.9316784 | M95: 1.9088694 | N95: 1.9831634 | O95: 1.7172824 | P95: 1.8542408 | Q95: 1.5961167 | R95: 2.6973188 | S95: 6.6990376 | T95: 5.5077931 | U95: 1.8802362 | V95: ..
A96: Belgium | B96: BEL | C96: Trade in services (% of GDP) | D96: BG.GSR.NFSV.GD.ZS | E96: .. | F96: .. | G96: 29.594875 | H96: 28.521764 | I96: 28.348006 | J96: 28.446724 | K96: 28.133863 | L96: 30.56666 | M96: 36.015103 | N96: 46.518834 | O96: 45.747488 | P96: 47.28094 | Q96: 45.028297 | R96: 45.668777 | S96: 47.751013 | T96: 46.50356 | U96: 46.878752 | V96: ..
A97: Belize | B97: BLZ | C97: Broad money (% of GDP) | D97: FM.LBL.BMNY.GD.ZS | E97: 39.540149 | F97: 42.313643 | G97: 41.039959 | H97: 40.944744 | I97: 43.288718 | J97: 43.815655 | K97: 47.306861 | L97: 50.876505 | M97: 56.562765 | N97: 64.857323 | O97: 65.998068 | P97: 66.298033 | Q97: 86.30461 | R97: 81.768975 | S97: 72.190371 | T97: 72.854354 | U97: 75.911327 | V97: ..
A98: Belize | B98: BLZ | C98: Access to electricity, rural (% of rural population) | D98: EG.ELC.ACCS.RU.ZS | E98: 65.7 | F98: 67.5 | G98: 68.9 | H98: 70.3 | I98: 71.7 | J98: 73.1 | K98: 85.1 | L98: 76 | M98: 77.5 | N98: 90.9 | O98: 86.5 | P98: 87.8 | Q98: 95.5 | R98: 97.1 | S98: 97.1 | T98: 99.4 | U98: .. | V98: ..
A99: Belize | B99: BLZ | C99: Inflation, consumer prices (annual %) | D99: FP.CPI.TOTL.ZG | E99: 3.0674397 | F99: 3.6514179 | G99: 4.2402666 | H99: 2.3180827 | I99: 6.394431 | J99: -1.1043104 | K99: -7.1137677 | L99: 2.3180827 | M99: 6.394431 | N99: 1.1476534 | O99: 0.26998262 | P99: 0.18706939 | Q99: 0.12143464 | R99: 3.2356366 | S99: 6.2768932 | T99: 4.3898402 | U99: 3.2895599 | V99: ..
A100: Belize | B100: BLZ | C100: Inflation, GDP deflator (annual %) | D100: NY.GDP.DEFL.KD.ZG | E100: 1.4307354 | F100: -1.9185878 | G100: 0.69514713 | H100: -4.0947969 | I100: 2.1430349 | J100: 3.0059384 | K100: 3.2224852 | L100: 3.8097116 | M100: 3.5766333 | N100: 3.069325 | O100: 0.05508458 | P100: -0.085143952 | Q100: -0.57778303 | R100: 0.53886215 | S100: 7.2868549 | T100: 6.6945921 | U100: 1.4020054 | V100: ..
...

Sheet Working
A1: Country Name | B1: Country Code | C1: Series Name | D1: Series Code | E1: 2000 | F1: 2001 | G1: 2002 | H1: 2003 | I1: 2004 | J1: 2005 | K1: 2006 | L1: 2007 | M1: 2008 | N1: 2017 | O1: 2018 | P1: 2019 | Q1: 2020 | R1: 2021 | S1: 2022 | T1: 2023 | U1: 2024
A2: Afghanistan | B2: AFG | C2: Broad money (% of GDP) | D2: FM.LBL.BMNY.GD.ZS | K2: 23.343865 | L2: 23.833664 | M2: 29.512281 | N2: 36.861261 | O2: 36.607494 | P2: 34.959214 | Q2: 37.508189
A3: Afghanistan | B3: AFG | C3: Access to electricity, rural (% of rural population) | D3: EG.ELC.ACCS.RU.ZS | H3: 2.1 | I3: 7.8 | J3: 15.4 | K3: 19.3 | L3: 25 | M3: 28 | N3: 97.1 | O3: 91.6 | P3: 97.1 | Q3: 97.1 | R3: 97.1 | S3: 81.7 | T3: 81.4
A4: Afghanistan | B4: AFG | C4: Inflation, consumer prices (annual %) | D4: FP.CPI.TOTL.ZG | J4: 12.686269 | K4: 6.7845966 | L4: 8.6805708 | M4: 26.418664 | N4: 4.9759515 | O4: 0.62614915 | P4: 2.3023725 | Q4: 5.6018879 | R4: 5.1332034 | S4: 13.712102 | T4: -4.6447087 | U4: -6.6011856
A5: Afghanistan | B5: AFG | C5: Inflation, GDP deflator (annual %) | D5: NY.GDP.DEFL.KD.ZG | F5: -11.774536 | G5: 6.125522 | H5: 11.655238 | I5: 11.271432 | J5: 10.912774 | K5: 7.1997513 | L5: 22.527756 | M5: 2.0962888 | N5: 2.4036562 | O5: 2.0713486 | P5: 6.5214798 | Q5: 6.9629463 | R5: 2.8389963 | S5: 9.4062393 | T5: 2.9236621
A6: Afghanistan | B6: AFG | C6: Trade in services (% of GDP) | D6: BG.GSR.NFSV.GD.ZS | M6: 20.211726 | N6: 8.5806823 | O6: 11.638305 | P6: 9.918134 | Q6: 9.0438455
A7: Albania | B7: ALB | C7: Broad money (% of GDP) | D7: FM.LBL.BMNY.GD.ZS | E7: 63.559947 | F7: 67.466477 | G7: 64.380525 | H7: 63.296713 | I7: 66.17596 | J7: 69.648068 | K7: 74.242141 | L7: 75.362987 | M7: 73.333402 | N7: 80.23339 | O7: 76.114797 | P7: 77.022846 | Q7: 87.983312 | R7: 84.766385 | S7: 77.185728 | T7: 71.828751 | U7: 70.9046
A8: Albania | B8: ALB | C8: Access to electricity, rural (% of rural population) | D8: EG.ELC.ACCS.RU.ZS | E8: 100 | F8: 100 | G8: 100 | H8: 100 | I8: 100 | J8: 100 | K8: 100 | L8: 100 | M8: 100 | N8: 99.7 | O8: 100 | P8: 100 | Q8: 100 | R8: 100 | S8: 100 | T8: 100
A9: Albania | B9: ALB | C9: Inflation, consumer prices (annual %) | D9: FP.CPI.TOTL.ZG | E9: 0.050018136 | F9: 3.1075883 | G9: 7.7705258 | H9: 0.48400261 | I9: 2.2800192 | J9: 2.366582 | K9: 2.3707283 | L9: 2.9326825 | M9: 3.3208709 | N9: 1.9866613 | O9: 2.0280596 | P9: 1.4110908 | Q9: 1.6208866 | R9: 2.0414716 | S9: 6.7252027 | T9: 4.7583456 | U9: 2.2158738
A10: Albania | B10: ALB | C10: Inflation, GDP deflator (annual %) | D10: NY.GDP.DEFL.KD.ZG | E10: 5.9195735 | F10: 3.7659453 | G10: 3.9038814 | H10: 4.9374926 | I10: 3.0953665 | J10: 3.1437051 | K10: 2.6847683 | L10: 5.1495678 | M10: 3.4986391 | N10: 2.7250692 | O10: 1.4532872 | P10: 1.0006329 | Q10: 0.041064999 | R10: 3.4442568 | S10: 9.8616099 | T10: 5.733907 | U10: 2.3531809
A11: Albania | B11: ALB | C11: Trade in services (% of GDP) | D11: BG.GSR.NFSV.GD.ZS | E11: 24.789583 | F11: 24.458841 | G11: 25.962551 | H11: 26.693325 | I11: 29.103663 | J11: 32.089796 | K11: 35.181631 | L11: 36.241931 | M11: 38.528108 | N11: 39.667021 | O11: 38.560048 | P11: 39.790381 | Q11: 25.556111 | R11: 33.896916 | S11: 39.58999 | T11: 45.057723 | U11: 43.852188
A12: Algeria | B12: DZA | C12: Broad money (% of GDP) | D12: FM.LBL.BMNY.GD.ZS | E12: 37.829725 | F12: 52.381764 | G12: 57.87508 | H12: 58.015964 | I12: 55.021864 | J12: 51.892561 | K12: 54.464995 | L12: 60.717363 | M12: 59.709446 | N12: 71.063395 | O12: 73.341678 | P12: 71.505472 | Q12: 84.871789 | R12: 79.826032 | S12: 71.665003 | T12: 72.243913 | U12: 73.4802
A13: Algeria | B13: DZA | C13: Access to electricity, rural (% of rural population) | D13: EG.ELC.ACCS.RU.ZS | E13: 97.4 | F13: 97.4 | G13: 97.4 | H13: 97.4 | I13: 97.4 | J13: 97.4 | K13: 97.4 | L13: 97.4 | M13: 97.9 | N13: 98.6 | O13: 98.9 | P13: 98.7 | Q13: 99.1 | R13: 99.3 | S13: 99.3 | T13: 100
A14: Algeria | B14: DZA | C14: Inflation, consumer prices (annual %) | D14: FP.CPI.TOTL.ZG | E14: 0.33916319 | F14: 4.2259883 | G14: 1.4183019 | H14: 4.268954 | I14: 3.9618003 | J14: 1.3824466 | K14: 2.3114992 | L14: 3.6789957 | M14: 4.8585906 | N14: 5.5911159 | O14: 4.2699902 | P14: 1.9517682 | Q14: 2.4151309 | R14: 7.2260631 | S14: 9.2655155 | T14: 9.3221738 | U14: 4.0461146
A15: Algeria | B15: DZA | C15: Inflation, GDP deflator (annual %) | D15: NY.GDP.DEFL.KD.ZG | E15: 22.678009 | F15: 8.014363 | G15: 1.3728559 | H15: 8.9424622 | I15: 11.446504 | J15: 12.361593 | K15: 10.781184 | L15: 7.0955158 | M15: 15.117882 | N15: 4.9380073 | O15: 6.1646784 | P15: 0.88299283 | Q15: -4.7113839 | R15: 15.9326 | S15: 22.920306 | T15: 1.0015314 | U15: 3.3749774
A16: Algeria | B16: DZA | C16: Trade in services (% of GDP) | D16: BG.GSR.NFSV.GD.ZS | J16: 6.8474839 | K16: 6.0129541 | L16: 6.7620351 | M16: 8.0772087 | N16: 7.5752446 | O16: 7.7450915 | P16: 6.8114722 | Q16: 6.3240803 | R16: 5.4285891 | S16: 5.0696726 | T16: 4.8733878 | U16: 4.9582377
A17: American Samoa | B17: ASM | C17: Broad money (% of GDP) | D17: FM.LBL.BMNY.GD.ZS
A18: American Samoa | B18: ASM | C18: Access to electricity, rural (% of rural population) | D18: EG.ELC.ACCS.RU.ZS
A19: American Samoa | B19: ASM | C19: Inflation, consumer prices (annual %) | D19: FP.CPI.TOTL.ZG
A20: American Samoa | B20: ASM | C20: Inflation, GDP deflator (annual %) | D20: NY.GDP.DEFL.KD.ZG | H20: 1.3650529 | I20: -3.2590746 | J20: -1.3655834 | K20: 2.8136752 | L20: 3.1606122 | M20: 11.059335 | N20: -1.9408901 | O20: 1.6953611 | P20: 1.7482893 | Q20: 6.7287807 | R20: 4.8425557 | S20: 14.152765
A21: American Samoa | B21: ASM | C21: Trade in services (% of GDP) | D21: BG.GSR.NFSV.GD.ZS
A22: Andorra | B22: AND | C22: Broad money (% of GDP) | D22: FM.LBL.BMNY.GD.ZS
A23: Andorra | B23: AND | C23: Access to electricity, rural (% of rural population) | D23: EG.ELC.ACCS.RU.ZS | E23: 100 | F23: 100 | G23: 100 | H23: 100 | I23: 100 | J23: 100 | K23: 100 | L23: 100 | M23: 100 | N23: 100 | O23: 100 | P23: 100 | Q23: 100 | R23: 100 | S23: 100 | T23: 100
A24: Andorra | B24: AND | C24: Inflation, consumer prices (annual %) | D24: FP.CPI.TOTL.ZG
A25: Andorra | B25: AND | C25: Inflation, GDP deflator (annual %) | D25: NY.GDP.DEFL.KD.ZG | E25: 28.741553 | F25: 3.0805352 | G25: 3.2395318 | H25: 3.1774842 | I25: 3.042424 | J25: 3.3961021 | K25: 3.4571841 | L25: 3.2112273 | M25: 2.2743383 | N25: 1.1365093 | O25: 1.0124785 | P25: 1.3747535 | Q25: 1.1137861 | R25: 2.5588607 | S25: 4.2366523 | T25: 6.2956008 | U25: 3.1436554
A26: Andorra | B26: AND | C26: Trade in services (% of GDP) | D26: BG.GSR.NFSV.GD.ZS | P26: 87.579553 | Q26: 75.315498 | R26: 87.495948 | S26: 94.434915 | T26: 99.506414 | U26: 109.27757
A27: Angola | B27: AGO | C27: Broad money (% of GDP) | D27: FM.LBL.BMNY.GD.ZS | E27: 17.280556 | F27: 21.135714 | G27: 14.171608 | H27: 11.828681 | I27: 11.823712 | J27: 11.877928 | K27: 14.532997 | L27: 18.271273 | M27: 28.249531 | N27: 28.10993 | O27: 27.201483 | P27: 29.587702 | Q27: 33.022497 | R27: 21.619274 | S27: 17.31393 | T27: 19.973799 | U27: 16.112562
A28: Angola | B28: AGO | C28: Access to electricity, rural (% of rural population) | D28: EG.ELC.ACCS.RU.ZS | E28: 3.5 | F28: 9.5 | G28: 2.8 | H28: 2.3 | I28: 1.7 | J28: 1 | K28: 0.7 | M28: 6.6 | O28: 7.3
A29: Angola | B29: AGO | C29: Inflation, consumer prices (annual %) | D29: FP.CPI.TOTL.ZG | E29: 324.99687 | F29: 152.56102 | G29: 108.89744 | H29: 98.224144 | I29: 43.542107 | J29: 22.953514 | K29: 13.30521 | L29: 12.251497 | M29: 12.475829 | N29: 29.84448 | O29: 19.628938 | P29: 17.080954 | Q29: 22.271539 | R29: 25.754295 | S29: 21.35529 | T29: 13.644102 | U29: 28.240495
A30: Angola | B30: AGO | C30: Inflation, GDP deflator (annual %) | D30: NY.GDP.DEFL.KD.ZG | E30: 418.01899 | F30: 106.35213 | G30: 236.34574 | H30: 94.607261 | I30: 33.382324 | J30: 40.136451 | K30: 16.814418 | L30: 5.1745141 | M30: 19.427383 | N30: 23.712806 | O30: 25.194156 | P30: 19.865888 | Q30: 16.063581 | R30: 35.653692 | S30: 18.121772 | T30: 17.929233 | U30: 24.604584
A31: Angola | B31: AGO | C31: Trade in services (% of GDP) | D31: BG.GSR.NFSV.GD.ZS | E31: 32.495965 | F31: 41.636046 | G31: 20.384059 | H31: 17.314894 | I31: 18.98474 | J31: 16.831823 | K31: 15.336499 | L31: 17.735958 | M31: 22.743898 | N31: 17.514116 | O31: 11.976649 | P31: 10.685468 | Q31: 9.6335065 | R31: 8.9792802 | S31: 8.6722768 | T31: 8.0983565 | U31: 8.5358912
A32: Antigua and Barbuda | B32: ATG | C32: Broad money (% of GDP) | D32: FM.LBL.BMNY.GD.ZS | E32: 72.41106 | F32: 77.993139 | G32: 80.309875 | H32: 87.924802 | I32: 86.205501 | J32: 84.187929 | K32: 82.432029 | L32: 80.462846 | M32: 79.371188 | N32: 87.31163 | O32: 86.469038 | P32: 82.844155 | Q32: 92.484771 | R32: 92.787136 | S32: 83.302316 | T32: 80.109967 | U32: 76.142397
A33: Antigua and Barbuda | B33: ATG | C33: Access to electricity, rural (% of rural population) | D33: EG.ELC.ACCS.RU.ZS | E33: 96.6 | F33: 96.7 | G33: 100 | H33: 97 | I33: 97.1 | J33: 100 | K33: 100 | L33: 100 | M33: 100 | N33: 100 | O33: 100 | P33: 100 | Q33: 100 | R33: 100 | S33: 100 | T33: 100
A34: Antigua and Barbuda | B34: ATG | C34: Inflation, consumer prices (annual %) | D34: FP.CPI.TOTL.ZG | E34: 0.7717798 | F34: 1.4027966 | G34: 2.407658 | H34: 1.9935306 | I34: 2.0300776 | J34: 2.098752 | K34: 1.7877854 | L34: 1.4160526 | M34: 5.3338064 | N34: 2.4324879 | O34: 1.2071579 | P34: 1.431356 | Q34: 0.62598971 | R34: 2.0629964 | S34: 7.5310783 | T34: 5.0671387 | U34: 6.198867
A35: Antigua and Barbuda | B35: ATG | C35: Inflation, GDP deflator (annual %) | D35: NY.GDP.DEFL.KD.ZG | E35: 1.5355154 | F35: 2.063778 | G35: 1.2744512 | H35: -0.47933004 | I35: 2.3486479 | J35: 4.6784983 | K35: 1.1176722 | L35: 4.3693205 | M35: 4.7383582 | N35: 0.31653179 | O35: 1.4442184 | P35: 0.71233504 | Q35: 0.78165357 | R35: 4.9192746 | S35: 6.7802747 | T35: 4.9119408 | U35: 6.1804095
A36: Antigua and Barbuda | B36: ATG | C36: Trade in services (% of GDP) | D36: BG.GSR.NFSV.GD.ZS | E36: 91.233804 | F36: 93.789824 | G36: 95.669204 | H36: 100.42616 | I36: 102.10806 | J36: 98.060973 | K36: 90.729591 | L36: 80.34372 | M36: 88.065746 | N36: 93.064846 | O36: 90.467962 | P36: 98.392769 | Q36: 61.566428 | R36: 62.27681 | S36: 81.339268 | T36: 80.300848 | U36: 81.448729
A37: Argentina | B37: ARG | C37: Broad money (% of GDP) | D37: FM.LBL.BMNY.GD.ZS | E37: 31.848621 | F37: 27.139252 | G37: 27.92707 | H37: 30.104057 | I37: 28.325646 | J37: 28.66331 | K37: 28.049612 | L37: 27.864316 | M37: 23.493673 | N37: 28.49528 | O37: 30.410756 | P37: 26.183039 | Q37: 34.505263 | R37: 30.730954 | S37: 32.191836 | T37: 35.821852 | U37: 26.333931
A38: Argentina | B38: ARG | C38: Access to electricity, rural (% of rural population) | D38: EG.ELC.ACCS.RU.ZS | E38: 91.8 | F38: 88.6 | G38: 92.6 | H38: 92.9 | I38: 93.2 | J38: 93.4 | K38: 93.6 | L38: 93.8 | M38: 94 | N38: 100 | O38: 99.9 | P38: 100 | Q38: 100 | R38: 100 | S38: 100 | T38: 100
A39: Argentina | B39: ARG | C39: Inflation, consumer prices (annual %) | D39: FP.CPI.TOTL.ZG | O39: 34.277224 | P39: 53.548304 | Q39: 42.015095 | R39: 48.409379 | S39: 72.430758 | T39: 133.48894 | U39: 219.88393
A40: Argentina | B40: ARG | C40: Inflation, GDP deflator (annual %) | D40: NY.GDP.DEFL.KD.ZG | E40: 1.0372871 | F40: -1.0957677 | G40: 30.555204 | H40: 10.495703 | I40: 18.363354 | J40: 10.317511 | K40: 13.741052 | L40: 14.939925 | M40: 23.171165 | N40: 26.006379 | O40: 42.033669 | P40: 49.195579 | Q40: 40.083088 | R40: 53.802088 | S40: 68.993827 | T40: 136.74236 | U40: 207.60524
A41: Argentina | B41: ARG | C41: Trade in services (% of GDP) | D41: BG.GSR.NFSV.GD.ZS | E41: 4.9539896 | F41: 4.8478054 | G41: 8.4772621 | H41: 7.8189173 | I41: 7.094095 | J41: 7.0218144 | K41: 7.1315716 | L41: 7.3289458 | M41: 6.934055 | N41: 6.3247431 | O41: 7.5491792 | P41: 7.6935019 | Q41: 5.5788172 | R41: 4.7018602 | S41: 5.616236 | T41: 6.0210788 | U41: 6.2791023
A42: Armenia | B42: ARM | C42: Broad money (% of GDP) | D42: FM.LBL.BMNY.GD.ZS | E42: 14.704511 | F42: 13.449648 | G42: 15.551599 | H42: 14.391959 | I42: 14.986981 | J42: 16.298392 | K42: 18.28698 | L42: 21.952399 | M42: 19.835837 | N42: 46.415424 | O42: 46.12064 | P42: 47.154402 | Q42: 54.385167 | R42: 54.386826 | S42: 51.931999 | T42: 54.600939 | U42: 57.791584
A43: Armenia | B43: ARM | C43: Access to electricity, rural (% of rural population) | D43: EG.ELC.ACCS.RU.ZS | E43: 98.5 | F43: 100 | G43: 95.8 | H43: 98.9 | I43: 98.9 | J43: 99.6 | K43: 98.9 | L43: 98.9 | M43: 98.9 | N43: 99.5 | O43: 99.9 | P43: 100 | Q43: 100 | R43: 100 | S43: 100 | T43: 100
A44: Armenia | B44: ARM | C44: Inflation, consumer prices (annual %) | D44: FP.CPI.TOTL.ZG | E44: -0.79088377 | F44: 3.1459046 | G44: 1.0600493 | H44: 4.7215534 | I44: 6.9612614 | J44: 0.638928 | K44: 2.8923566 | L44: 4.4073609 | M44: 8.9499534 | N44: 0.96955327 | O44: 2.5202338 | P44: 1.4434466 | Q44: 1.2114358 | R44: 7.1848363 | S44: 8.6409111 | T44: 1.9804188 | U44: 0.26951198
A45: Armenia | B45: ARM | C45: Inflation, GDP deflator (annual %) | D45: NY.GDP.DEFL.KD.ZG | E45: -1.373676 | F45: 4.0279695 | G45: 2.357399 | H45: 4.5985157 | I45: 6.2785941 | J45: 3.2087567 | K45: 4.6180125 | L45: 4.2778755 | M45: 5.9895624 | N45: 2.1506419 | O45: 2.7877095 | P45: 1.0656226 | Q45: 1.8065927 | R45: 6.9005137 | S45: 7.9858785 | T45: 3.1002763 | U45: 1.4010608
A46: Armenia | B46: ARM | C46: Trade in services (% of GDP) | D46: BG.GSR.NFSV.GD.ZS | E46: 18.083026 | F46: 23.040664 | G46: 20.876744 | H46: 21.73343 | I46: 23.725101 | J46: 20.573962 | K46: 19.982312 | L46: 18.665737 | M46: 17.028239 | N46: 33.693061 | O46: 35.27009 | P46: 36.809172 | Q46: 17.02325 | R46: 22.602958 | S46: 36.652843 | T46: 39.769746 | U46: 39.479105
A47: Aruba | B47: ABW | C47: Broad money (% of GDP) | D47: FM.LBL.BMNY.GD.ZS | E47: 51.834542 | F47: 54.220484 | G47: 57.909275 | H47: 60.51173 | I47: 56.620832 | J47: 57.44679 | K47: 56.196562 | L47: 53.544999 | M47: 58.783489 | N47: 76.595454 | O47: 74.635392 | P47: 76.278006 | Q47: 108.44424 | R47: 104.04676 | S47: 93.17277 | T47: 81.401003
A48: Aruba | B48: ABW | C48: Access to electricity, rural (% of rural population) | D48: EG.ELC.ACCS.RU.ZS | E48: 100 | F48: 100 | G48: 100 | H48: 100 | I48: 100 | J48: 100 | K48: 100 | L48: 100 | M48: 100 | N48: 100 | O48: 100 | P48: 100 | Q48: 100 | R48: 100 | S48: 100 | T48: 100
A49: Aruba | B49: ABW | C49: Inflation, consumer prices (annual %) | D49: FP.CPI.TOTL.ZG | E49: 4.0440213 | F49: 2.8836043 | G49: 3.3152468 | H49: 3.6563651 | I49: 2.5291295 | J49: 3.3977868 | K49: 3.6080244 | L49: 5.3925678 | M49: 8.9559871 | N49: -1.0282818 | O49: 3.6260414 | P49: 4.257462
A50: Aruba | B50: ABW | C50: Inflation, GDP deflator (annual %) | D50: NY.GDP.DEFL.KD.ZG | E50: 1.0361008 | F50: -2.8355024 | G50: 4.4346881 | H50: 3.0490462 | I50: 2.8099097 | J50: 5.0674972 | K50: 3.4843462 | L50: 5.166893 | M50: 4.262449 | N50: 0.14764948 | O50: 2.6448143 | P50: 0.91361696 | Q50: -2.9616355 | R50: 1.6021428 | S50: 4.2890599 | T50: 7.1090373 | U50: 4.1442906
A51: Aruba | B51: ABW | C51: Trade in services (% of GDP) | D51: BG.GSR.NFSV.GD.ZS | E51: 118.96388 | F51: 128.63151 | G51: 93.659196 | H51: 114.19502 | I51: 84.203573 | J51: 85.570077 | K51: 83.587522 | L51: 84.277458 | M51: 84.311028 | N51: 99.769031 | O51: 104.30372 | P51: 103.58523 | Q51: 86.504446 | R51: 102.90089 | S51: 111.48201 | T51: 108.70079
A52: Australia | B52: AUS | C52: Broad money (% of GDP) | D52: FM.LBL.BMNY.GD.ZS | E52: 67.401739 | F52: 70.030318 | G52: 70.117851 | H52: 74.471442 | I52: 77.124004 | J52: 78.131886 | K52: 83.223036 | L52: 90.303231 | M52: 97.50994 | N52: 116.18259 | O52: 113.5217 | P52: 122.44551 | Q52: 136.81501 | R52: 138.8592 | S52: 133.99141 | T52: 126.28599 | U52: 129.41494
A53: Australia | B53: AUS | C53: Access to electricity, rural (% of rural population) | D53: EG.ELC.ACCS.RU.ZS | E53: 100 | F53: 100 | G53: 100 | H53: 100 | I53: 100 | J53: 100 | K53: 100 | L53: 100 | M53: 100 | N53: 100 | O53: 100 | P53: 100 | Q53: 100 | R53: 100 | S53: 100 | T53: 100
A54: Australia | B54: AUS | C54: Inflation, consumer prices (annual %) | D54: FP.CPI.TOTL.ZG | E54: 4.4574371 | F54: 4.40713 | G54: 2.9815712 | H54: 2.7325975 | I54: 2.3432569 | J54: 2.6918295 | K54: 3.555287 | L54: 2.3276144 | M54: 4.3502973 | N54: 1.9486431 | O54: 1.9114 | P54: 1.6107709 | Q54: 0.84690073 | R54: 2.8639128 | S54: 6.5940966 | T54: 5.5970179 | U54: 3.1665667
A55: Australia | B55: AUS | C55: Inflation, GDP deflator (annual %) | D55: NY.GDP.DEFL.KD.ZG | E55: 2.5539837 | F55: 4.6410706 | G55: 2.8403056 | H55: 2.987661 | I55: 3.2309789 | J55: 3.8250404 | K55: 5.1116639 | L55: 4.9846061 | M55: 4.5677065 | N55: 3.6462336 | O55: 1.8461756 | P55: 3.4766003 | Q55: 1.8658341 | R55: 3.0606698 | S55: 7.1995443 | T55: 6.4594411 | U55: 2.5883843
A56: Australia | B56: AUS | C56: Trade in services (% of GDP) | D56: BG.GSR.NFSV.GD.ZS | E56: 9.4239941 | F56: 9.3017987 | G56: 9.5581644 | H56: 9.7856803 | I56: 9.1152351 | J56: 8.8348398 | K56: 9.5649144 | L56: 10.478092 | M56: 9.7062707 | N56: 10.330207 | O56: 10.3696 | P56: 10.590088 | Q56: 7.2657978 | R56: 6.1475913 | S56: 7.8232263 | T56: 10.259152 | U56: 11.025718
A57: Austria | B57: AUT | C57: Broad money (% of GDP) | D57: FM.LBL.BMNY.GD.ZS
A58: Austria | B58: AUT | C58: Access to electricity, rural (% of rural population) | D58: EG.ELC.ACCS.RU.ZS | E58: 100 | F58: 100 | G58: 100 | H58: 100 | I58: 100 | J58: 100 | K58: 100 | L58: 100 | M58: 100 | N58: 100 | O58: 100 | P58: 100 | Q58: 100 | R58: 100 | S58: 100 | T58: 100
A59: Austria | B59: AUT | C59: Inflation, consumer prices (annual %) | D59: FP.CPI.TOTL.ZG | E59: 2.3448629 | F59: 2.6500008 | G59: 1.8103579 | H59: 1.3555537 | I59: 2.0612062 | J59: 2.2991379 | K59: 1.4415485 | L59: 2.1685553 | M59: 3.2159503 | N59: 2.0812691 | O59: 1.9983798 | P59: 1.5308956 | Q59: 1.3819106 | R59: 2.7666667 | S59: 8.5468699 | T59: 7.8141342 | U59: 2.9379157
A60: Austria | B60: AUT | C60: Inflation, GDP deflator (annual %) | D60: NY.GDP.DEFL.KD.ZG | E60: 1.3673138 | F60: 1.9372838 | G60: 1.1042153 | H60: 1.2670027 | I60: 1.727962 | J60: 2.5319678 | K60: 2.04462 | L60: 2.2592709 | M60: 1.9337907 | N60: 0.97531791 | O60: 1.81048 | P60: 1.473685 | Q60: 2.5931325 | R60: 1.801873 | S60: 5.0234316 | T60: 7.1747129 | U60: 4.0868124
A61: Austria | B61: AUT | C61: Trade in services (% of GDP) | D61: BG.GSR.NFSV.GD.ZS | J61: 25.711587 | K61: 24.204649 | L61: 24.692772 | M61: 25.24307 | N61: 29.709443 | O61: 30.970268 | P61: 32.224107 | Q61: 27.860711 | R61: 28.771994 | S61: 33.599617 | T61: 33.812291 | U61: 35.000518
A62: Azerbaijan | B62: AZE | C62: Broad money (% of GDP) | D62: FM.LBL.BMNY.GD.ZS | E62: 16.290824 | F62: 12.931625 | G62: 12.979951 | H62: 14.28476 | I62: 17.653559 | J62: 14.683353 | K62: 18.323536 | L62: 20.793923 | M62: 21.162979 | N62: 32.375295 | O62: 30.040944 | P62: 35.24743 | Q62: 40.212967 | R62: 37.173232 | S62: 31.965415 | T62: 36.606871 | U62: 36.802242
A63: Azerbaijan | B63: AZE | C63: Access to electricity, rural (% of rural population) | D63: EG.ELC.ACCS.RU.ZS | E63: 98.1 | F63: 97.6 | G63: 100 | H63: 98.1 | I63: 98.4 | J63: 98.6 | K63: 99.2 | L63: 99.2 | M63: 99.5 | N63: 100 | O63: 100 | P63: 100 | Q63: 100 | R63: 100 | S63: 100 | T63: 100
A64: Azerbaijan | B64: AZE | C64: Inflation, consumer prices (annual %) | D64: FP.CPI.TOTL.ZG | E64: 1.805003 | F64: 1.5471959 | G64: 2.7711647 | H64: 2.2338649 | I64: 6.7089304 | J64: 9.6795073 | K64: 8.3289248 | L64: 16.699755 | M64: 20.849087 | N64: 12.935918 | O64: 2.2685469 | P64: 2.6105718 | Q64: 2.7598095 | R64: 6.6502991 | S64: 13.852259 | T64: 8.7854305 | U64: 2.2121719
A65: Azerbaijan | B65: AZE | C65: Inflation, GDP deflator (annual %) | D65: NY.GDP.DEFL.KD.ZG | E65: 12.492774 | F65: 2.5150102 | G65: 4.2143862 | H65: 6.9614657 | I65: 9.2519651 | J65: 14.723497 | K65: 11.329188 | L65: 20.582483 | M65: 27.971036 | N65: 16.226205 | O65: 12.184433 | P65: -0.22165278 | Q65: -7.4936335 | R65: 21.588837 | S65: 37.270721 | T65: -9.322615 | U65: -1.4081721
A66: Azerbaijan | B66: AZE | C66: Trade in services (% of GDP) | D66: BG.GSR.NFSV.GD.ZS | E66: 14.115897 | F66: 16.726703 | G66: 26.714714 | H66: 34.006206 | I66: 37.699206 | J66: 25.671209 | K66: 18.606034 | L66: 14.646605 | M66: 11.431132 | N66: 31.214201 | O66: 24.480099 | P66: 21.430483 | Q66: 19.163302 | R66: 17.901672 | S66: 16.283493 | T66: 20.579101 | U66: 24.614662
A67: Bahamas, The | B67: BHS | C67: Broad money (% of GDP) | D67: FM.LBL.BMNY.GD.ZS | E67: 42.919741 | F67: 43.720538 | G67: 42.167915 | H67: 43.772949 | I67: 46.831189 | J67: 47.784714 | K67: 49.816814 | L67: 52.72293 | M67: 55.980429 | N67: 60.361912 | O67: 59.225454 | P67: 63.240797 | Q67: 80.805236 | R67: 72.587304 | S67: 68.758905
A68: Bahamas, The | B68: BHS | C68: Access to electricity, rural (% of rural population) | D68: EG.ELC.ACCS.RU.ZS | E68: 100 | F68: 100 | G68: 100 | H68: 100 | I68: 100 | J68: 100 | K68: 100 | L68: 100 | M68: 100 | N68: 100 | O68: 100 | P68: 100 | Q68: 100 | R68: 100 | S68: 100 | T68: 100
A69: Bahamas, The | B69: BHS | C69: Inflation, consumer prices (annual %) | D69: FP.CPI.TOTL.ZG | E69: 1.6063294 | F69: 2.0449898 | G69: 2.1735779 | H69: 3.0250453 | I69: 0.98191404 | J69: 1.5916062 | K69: 2.3898263 | L69: 2.4925779 | M69: 4.48956 | N69: 1.518207 | O69: 2.2658635 | P69: 2.4912353 | Q69: 0.038521098 | R69: 2.9049126 | S69: 5.6054063 | T69: 3.0529158 | U69: 0.40916249
A70: Bahamas, The | B70: BHS | C70: Inflation, GDP deflator (annual %) | D70: NY.GDP.DEFL.KD.ZG | E70: 0.92270743 | F70: 0.3531507 | G70: 3.9604743 | H70: 1.1548791 | I70: 1.1949976 | J70: 5.0560084 | K70: 0.82819451 | L70: 2.9479658 | M70: 1.4886107 | N70: 1.3471328 | O70: 0.5792607 | P70: 4.4470842 | Q70: -2.3236661 | R70: -1.2201754 | S70: 4.1241697 | T70: 6.6401176 | U70: 0.28842138
A71: Bahamas, The | B71: BHS | C71: Trade in services (% of GDP) | D71: BG.GSR.NFSV.GD.ZS | E71: 37.131321 | F71: 33.393325 | G71: 34.656976 | H71: 35.479685 | I71: 38.379555 | J71: 38.605489 | K71: 39.803782 | L71: 39.355773 | M71: 37.400974 | N71: 40.207181 | O71: 46.099908 | P71: 47.44241 | Q71: 25.512049 | R71: 36.339383 | S71: 47.308994 | T71: 48.106209 | U71: 52.863799
A72: Bahrain | B72: BHR | C72: Broad money (% of GDP) | D72: FM.LBL.BMNY.GD.ZS | E72: 63.289951 | F72: 69.806373 | G72: 72.067056 | H72: 66.396318 | I72: 58.236756 | J72: 58.504141 | K72: 58.005487 | L72: 68.808687 | M72: 69.599578
A73: Bahrain | B73: BHR | C73: Access to electricity, rural (% of rural population) | D73: EG.ELC.ACCS.RU.ZS | E73: 100 | F73: 100 | G73: 100 | H73: 100 | I73: 100 | J73: 100 | K73: 100 | L73: 100 | M73: 100 | N73: 100 | O73: 100 | P73: 100 | Q73: 100 | R73: 100 | S73: 100 | T73: 100
A74: Bahrain | B74: BHR | C74: Inflation, consumer prices (annual %) | D74: FP.CPI.TOTL.ZG | E74: -0.70485295 | F74: -1.2075718 | G74: -0.49554014 | H74: 1.5936255 | I74: 2.3529412 | J74: 2.5862069 | K74: 2.0074697 | L74: 3.2566667 | M74: 3.5260032 | N74: 1.3867183 | O74: 2.0876694 | P74: 1.00582 | Q74: -2.3177063 | R74: -0.60631939 | S74: 3.625741 | T74: 0.074620678 | U74: 0.91963546
A75: Bahrain | B75: BHR | C75: Inflation, GDP deflator (annual %) | D75: NY.GDP.DEFL.KD.ZG | E75: 14.322524 | F75: -3.3638285 | G75: 3.4143496 | H75: 8.6025813 | I75: 10.991083 | J75: 13.734968 | K75: 8.8424373 | L75: 8.4356319 | M75: 11.365092 | N75: 4.6158342 | O75: 4.2127135 | P75: 0.1648022 | Q75: -5.8288485 | R75: 9.2084026 | S75: 7.1348888 | T75: -4.2843722 | U75: -0.60191753
A76: Bahrain | B76: BHR | C76: Trade in services (% of GDP) | D76: BG.GSR.NFSV.GD.ZS | E76: 19.176375 | F76: 20.011963 | G76: 21.954672 | H76: 20.370201 | I76: 30.617739 | J76: 28.625506 | K76: 27.384898 | L76: 24.766599 | M76: 23.125381 | N76: 51.4654 | O76: 50.176911 | P76: 50.387954 | Q76: 59.015432 | R76: 58.312364 | S76: 54.894357 | T76: 59.735299 | U76: 62.405226
A77: Bangladesh | B77: BGD | C77: Broad money (% of GDP) | D77: FM.LBL.BMNY.GD.ZS | E77: 30.553989 | F77: 40.267148 | G77: 42.740177 | H77: 43.988577 | I77: 45.622994 | J77: 47.421068 | K77: 50.475999 | L77: 50.281912 | M77: 51.187627 | N77: 55.837542 | O77: 54.832556 | P77: 54.870254 | Q77: 57.763065 | R77: 56.637279 | S77: 54.117701 | T77: 51.218563 | U77: 48.797431
A78: Bangladesh | B78: BGD | C78: Access to electricity, rural (% of rural population) | D78: EG.ELC.ACCS.RU.ZS | E78: 16.8 | F78: 21.5 | G78: 24.3 | H78: 27.1 | I78: 27.9 | J78: 30.2 | K78: 40.2 | L78: 32.5 | M78: 41.7 | N78: 81.6 | O78: 81.3 | P78: 88.9 | Q78: 95.2 | R78: 98.5 | S78: 99.2 | T78: 99.6
A79: Bangladesh | B79: BGD | C79: Inflation, consumer prices (annual %) | D79: FP.CPI.TOTL.ZG | E79: 2.2082562 | F79: 2.0071737 | G79: 3.3325649 | H79: 5.6687077 | I79: 7.5875364 | J79: 7.0466182 | K79: 6.7652612 | L79: 9.106985 | M79: 8.9019449 | N79: 5.7020702 | O79: 5.5436214 | P79: 5.5919964 | Q79: 5.6910747 | R79: 5.5456543 | S79: 7.6969544 | T79: 9.883503 | U79: 10.465748
A80: Bangladesh | B80: BGD | C80: Inflation, GDP deflator (annual %) | D80: NY.GDP.DEFL.KD.ZG | E80: 3.4466593 | F80: 3.2611601 | G80: 3.8928674 | H80: 5.8158166 | I80: 4.5621364 | J80: 4.5863607 | K80: 5.8759358 | L80: 6.4712601 | M80: 7.8609661 | N80: 5.0475976 | O80: 5.8055388 | P80: 3.6581376 | Q80: 3.8410634 | R80: 4.1211747 | S80: 5.0490219 | T80: 6.897124 | U80: 6.8828546
A81: Bangladesh | B81: BGD | C81: Trade in services (% of GDP) | D81: BG.GSR.NFSV.GD.ZS | E81: 4.6159307 | F81: 4.2441863 | G81: 4.2140007 | H81: 4.70573 | I81: 4.7469024 | J81: 5.5579433 | K81: 5.8386502 | L81: 6.3257435 | M81: 6.4967124 | N81: 4.2106393 | O81: 4.6879434 | P81: 4.4903496 | Q81: 3.7292011 | R81: 4.4059073 | S81: 4.289407 | T81: 3.595622 | U81: 4.3911633
A82: Barbados | B82: BRB | C82: Broad money (% of GDP) | D82: FM.LBL.BMNY.GD.ZS | E82: 65.254944 | F82: 87.733639 | G82: 99.528135 | H82: 100.78157 | I82: 104.92016 | J82: 110.59622 | K82: 105.51753 | L82: 115.0745 | M82: 113.61676 | N82: 99.737794 | O82: 94.318599 | P82: 94.593207 | Q82: 115.62175 | R82: 111.39023 | S82: 101.36865 | T82: 97.526438
A83: Barbados | B83: BRB | C83: Access to electricity, rural (% of rural population) | D83: EG.ELC.ACCS.RU.ZS | E83: 100 | F83: 100 | G83: 100 | H83: 100 | I83: 100 | J83: 99.9 | K83: 100 | L83: 100 | M83: 100 | N83: 100 | O83: 100 | P83: 100 | Q83: 100 | R83: 100 | S83: 100 | T83: 100
A84: Barbados | B84: BRB | C84: Inflation, consumer prices (annual %) | D84: FP.CPI.TOTL.ZG | E84: 2.435813 | F84: 2.5778349 | G84: 0.12524946 | H84: 1.6194332 | I84: 1.3944223 | J84: 6.0821873 | K84: 7.3076626 | L84: 4.0342298 | M84: 8.1081081 | N84: 4.6601846 | O84: 3.1060057 | P84: 1.6766247 | T84: 3.1871891 | U84: 1.4464366
A85: Barbados | B85: BRB | C85: Inflation, GDP deflator (annual %) | D85: NY.GDP.DEFL.KD.ZG | E85: -1.3228392 | F85: 2.2553897 | G85: 0.90785578 | H85: 1.1158721 | I85: 5.8281445 | J85: 6.667725 | K85: 4.0963702 | L85: 8.6122611 | M85: 1.8069353 | N85: -0.55379233 | O85: 6.9745867 | P85: 2.4308866 | Q85: 2.4699444 | R85: 10.102764 | S85: -1.2507344 | T85: 1.9433833 | U85: 1.290096
A86: Barbados | B86: BRB | C86: Trade in services (% of GDP) | D86: BG.GSR.NFSV.GD.ZS | E86: 47.949535 | F86: 44.939249 | G86: 45.175969 | H86: 48.881924 | I86: 44.328752 | J86: 46.517855 | K86: 45.242806 | L86: 43.462468 | M86: 45.535744 | N86: 38.88392
A87: Belarus | B87: BLR | C87: Broad money (% of GDP) | D87: FM.LBL.BMNY.GD.ZS | E87: 17.667502 | F87: 14.920271 | G87: 14.608985 | H87: 16.118616 | I87: 17.6819 | J87: 19.319424 | K87: 22.084683 | L87: 25.220956 | M87: 23.854619 | N87: 37.68248 | O87: 35.344191 | P87: 36.004556 | Q87: 33.930261 | R87: 30.728037
A88: Belarus | B88: BLR | C88: Access to electricity, rural (% of rural population) | D88: EG.ELC.ACCS.RU.ZS | E88: 79.4 | F88: 80.2 | G88: 81 | H88: 81.8 | I88: 82.6 | J88: 83.3 | K88: 84.2 | L88: 85 | M88: 85.9 | N88: 96.6 | O88: 98.2 | P88: 100 | Q88: 100 | R88: 100 | S88: 100 | T88: 100
A89: Belarus | B89: BLR | C89: Inflation, consumer prices (annual %) | D89: FP.CPI.TOTL.ZG | E89: 168.62024 | F89: 61.134933 | G89: 42.537548 | H89: 28.39784 | I89: 18.108242 | J89: 10.338879 | K89: 6.997129 | L89: 8.4267527 | M89: 14.837876 | N89: 6.0318373 | O89: 4.8723022 | P89: 5.598156 | Q89: 5.5481436 | R89: 9.4602839 | S89: 15.209675 | T89: 5.000599 | U89: 5.7853191
A90: Belarus | B90: BLR | C90: Inflation, GDP deflator (annual %) | D90: NY.GDP.DEFL.KD.ZG | E90: 185.29076 | F90: 79.534572 | G90: 44.893739 | H90: 30.685322 | I90: 22.675122 | J90: 18.972161 | K90: 10.748616 | L90: 12.872702 | M90: 21.213536 | N90: 8.6231474 | O90: 12.13923 | P90: 8.5769891 | Q90: 11.877465 | R90: 15.326574 | S90: 14.884862 | T90: 8.0467622 | U90: 8.7678713
A91: Belarus | B91: BLR | C91: Trade in services (% of GDP) | D91: BG.GSR.NFSV.GD.ZS | E91: 12.28325 | F91: 15.807596 | G91: 15.121034 | H91: 14.451813 | I91: 12.80164 | J91: 11.530253 | K91: 11.862487 | L91: 12.506043 | M91: 12.15678 | N91: 23.264149 | O91: 23.727897 | P91: 24.055362 | Q91: 22.216438 | R91: 22.977149 | S91: 20.019321 | T91: 20.463076 | U91: 22.408696
A92: Belgium | B92: BEL | C92: Broad money (% of GDP) | D92: FM.LBL.BMNY.GD.ZS
A93: Belgium | B93: BEL | C93: Access to electricity, rural (% of rural population) | D93: EG.ELC.ACCS.RU.ZS | E93: 100 | F93: 100 | G93: 100 | H93: 100 | I93: 100 | J93: 100 | K93: 100 | L93: 100 | M93: 100 | N93: 100 | O93: 100 | P93: 100 | Q93: 100 | R93: 100 | S93: 100 | T93: 100
A94: Belgium | B94: BEL | C94: Inflation, consumer prices (annual %) | D94: FP.CPI.TOTL.ZG | E94: 2.5445178 | F94: 2.4692582 | G94: 1.6452144 | H94: 1.588964 | I94: 2.0972831 | J94: 2.7814326 | K94: 1.7912077 | L94: 1.8230563 | M94: 4.4894442 | N94: 2.1259709 | O94: 2.053165 | P94: 1.4368196 | Q94: 0.74079181 | R94: 2.4402485 | S94: 9.5975117 | T94: 4.0490108 | U94: 3.1434914
A95: Belgium | B95: BEL | C95: Inflation, GDP deflator (annual %) | D95: NY.GDP.DEFL.KD.ZG | E95: 2.0145921 | F95: 1.9828181 | G95: 1.6399981 | H95: 1.8501163 | I95: 1.9149886 | J95: 2.0830733 | K95: 2.2647162 | L95: 1.9316784 | M95: 1.9088694 | N95: 1.9831634 | O95: 1.7172824 | P95: 1.8542408 | Q95: 1.5961167 | R95: 2.6973188 | S95: 6.6990376 | T95: 5.5077931 | U95: 1.8802362
A96: Belgium | B96: BEL | C96: Trade in services (% of GDP) | D96: BG.GSR.NFSV.GD.ZS | G96: 29.594875 | H96: 28.521764 | I96: 28.348006 | J96: 28.446724 | K96: 28.133863 | L96: 30.56666 | M96: 36.015103 | N96: 46.518834 | O96: 45.747488 | P96: 47.28094 | Q96: 45.028297 | R96: 45.668777 | S96: 47.751013 | T96: 46.50356 | U96: 46.878752
A97: Belize | B97: BLZ | C97: Broad money (% of GDP) | D97: FM.LBL.BMNY.GD.ZS | E97: 39.540149 | F97: 42.313643 | G97: 41.039959 | H97: 40.944744 | I97: 43.288718 | J97: 43.815655 | K97: 47.306861 | L97: 50.876505 | M97: 56.562765 | N97: 64.857323 | O97: 65.998068 | P97: 66.298033 | Q97: 86.30461 | R97: 81.768975 | S97: 72.190371 | T97: 72.854354 | U97: 75.911327
A98: Belize | B98: BLZ | C98: Access to electricity, rural (% of rural population) | D98: EG.ELC.ACCS.RU.ZS | E98: 65.7 | F98: 67.5 | G98: 68.9 | H98: 70.3 | I98: 71.7 | J98: 73.1 | K98: 85.1 | L98: 76 | M98: 77.5 | N98: 90.9 | O98: 86.5 | P98: 87.8 | Q98: 95.5 | R98: 97.1 | S98: 97.1 | T98: 99.4
A99: Belize | B99: BLZ | C99: Inflation, consumer prices (annual %) | D99: FP.CPI.TOTL.ZG | E99: 3.0674397 | F99: 3.6514179 | G99: 4.2402666 | H99: 2.3180827 | I99: 6.394431 | J99: -1.1043104 | K99: -7.1137677 | L99: 2.3180827 | M99: 6.394431 | N99: 1.1476534 | O99: 0.26998262 | P99: 0.18706939 | Q99: 0.12143464 | R99: 3.2356366 | S99: 6.2768932 | T99: 4.3898402 | U99: 3.2895599
A100: Belize | B100: BLZ | C100: Inflation, GDP deflator (annual %) | D100: NY.GDP.DEFL.KD.ZG | E100: 1.4307354 | F100: -1.9185878 | G100: 0.69514713 | H100: -4.0947969 | I100: 2.1430349 | J100: 3.0059384 | K100: 3.2224852 | L100: 3.8097116 | M100: 3.5766333 | N100: 3.069325 | O100: 0.05508458 | P100: -0.085143952 | Q100: -0.57778303 | R100: 0.53886215 | S100: 7.2868549 | T100: 6.6945921 | U100: 1.4020054
...

Sheet Long Format
A1: Country Name | B1: Country Code | C1: Series Name | D1: Series Code | E1: Year | F1: Value | G1: Gap Year
A2: Afghanistan | B2: AFG | C2: Broad money (% of GDP) | D2: FM.LBL.BMNY.GD.ZS | E2: 2006 | F2: 23.343865 | G2: No
A3: Afghanistan | B3: AFG | C3: Broad money (% of GDP) | D3: FM.LBL.BMNY.GD.ZS | E3: 2007 | F3: 23.833664 | G3: No
A4: Afghanistan | B4: AFG | C4: Broad money (% of GDP) | D4: FM.LBL.BMNY.GD.ZS | E4: 2008 | F4: 29.512281 | G4: No
A5: Afghanistan | B5: AFG | C5: Broad money (% of GDP) | D5: FM.LBL.BMNY.GD.ZS | E5: 2017 | F5: 36.861261 | G5: No
A6: Afghanistan | B6: AFG | C6: Broad money (% of GDP) | D6: FM.LBL.BMNY.GD.ZS | E6: 2018 | F6: 36.607494 | G6: No
A7: Afghanistan | B7: AFG | C7: Broad money (% of GDP) | D7: FM.LBL.BMNY.GD.ZS | E7: 2019 | F7: 34.959214 | G7: No
A8: Afghanistan | B8: AFG | C8: Broad money (% of GDP) | D8: FM.LBL.BMNY.GD.ZS | E8: 2020 | F8: 37.508189 | G8: No
A9: Afghanistan | B9: AFG | C9: Access to electricity, rural (% of rural population) | D9: EG.ELC.ACCS.RU.ZS | E9: 2003 | F9: 2.1 | G9: No
A10: Afghanistan | B10: AFG | C10: Access to electricity, rural (% of rural population) | D10: EG.ELC.ACCS.RU.ZS | E10: 2004 | F10: 7.8 | G10: No
A11: Afghanistan | B11: AFG | C11: Access to electricity, rural (% of rural population) | D11: EG.ELC.ACCS.RU.ZS | E11: 2005 | F11: 15.4 | G11: No
A12: Afghanistan | B12: AFG | C12: Access to electricity, rural (% of rural population) | D12: EG.ELC.ACCS.RU.ZS | E12: 2006 | F12: 19.3 | G12: No
A13: Afghanistan | B13: AFG | C13: Access to electricity, rural (% of rural population) | D13: EG.ELC.ACCS.RU.ZS | E13: 2007 | F13: 25 | G13: No
... A18253: World | B18253: WLD | C18253: Trade in services (% of GDP) | D18253: BG.GSR.NFSV.GD.ZS | E18253: 2024 | F18253: 15.237207 | G18253: No

Sheet Pivot Lab
A3: Average of Value | D3: Series Name
A4: Country Name | B4: Country Code | C4: Year | D4: Access to electricity, rural (% of rural population) | E4: Broad money (% of GDP) | F4: Inflation, consumer prices (annual %) | G4: Inflation, GDP deflator (annual %) | H4: Trade in services (% of GDP)
A5: Afghanistan | B5: AFG | C5: 2001 | G5: -11.774536
A6: Afghanistan | B6: AFG | C6: 2002 | G6: 6.125522
A7: Afghanistan | B7: AFG | C7: 2003 | D7: 2.1 | G7: 11.655238
A8: Afghanistan | B8: AFG | C8: 2004 | D8: 7.8 | G8: 11.271432
A9: Afghanistan | B9: AFG | C9: 2005 | D9: 15.4 | F9: 12.686269 | G9: 10.912774
A10: Afghanistan | B10: AFG | C10: 2006 | D10: 19.3 | E10: 23.343865 | F10: 6.7845966 | G10: 7.1997513
A11: Afghanistan | B11: AFG | C11: 2007 | D11: 25 | E11: 23.833664 | F11: 8.6805708 | G11: 22.527756
A12: Afghanistan | B12: AFG | C12: 2008 | D12: 28 | E12: 29.512281 | F12: 26.418664 | G12: 2.0962888 | H12: 20.211726
A13: Afghanistan | B13: AFG | C13: 2017 | D13: 97.1 | E13: 36.861261 | F13: 4.9759515 | G13: 2.4036562 | H13: 8.5806823
A14: Afghanistan | B14: AFG | C14: 2018 | D14: 91.6 | E14: 36.607494 | F14: 0.62614915 | G14: 2.0713486 | H14: 11.638305
A15: Afghanistan | B15: AFG | C15: 2019 | D15: 97.1 | E15: 34.959214 | F15: 2.3023725 | G15: 6.5214798 | H15: 9.918134
A16: Afghanistan | B16: AFG | C16: 2020 | D16: 97.1 | E16: 37.508189 | F16: 5.6018879 | G16: 6.9629463 | H16: 9.0438455
A17: Afghanistan | B17: AFG | C17: 2021 | D17: 97.1 | F17: 5.1332034 | G17: 2.8389963
A18: Afghanistan | B18: AFG | C18: 2022 | D18: 81.7 | F18: 13.712102 | G18: 9.4062393
A19: Afghanistan | B19: AFG | C19: 2023 | D19: 81.4 | F19: -4.6447087 | G19: 2.9236621
A20: Afghanistan | B20: AFG | C20: 2024 | F20: -6.6011856
A21: Africa Eastern and Southern | B21: AFE | C21: 2000 | D21: 8.6726535 | E21: 35.852469 | F21: 8.6014851 | G21: 11.117306 | H21: 10.502052
A22: Africa Eastern and Southern | B22: AFE | C22: 2001 | E22: 39.613793 | F22: 5.840354 | G22: 8.2433867 | H22: 11.24503
A23: Africa Eastern and Southern | B23: AFE | C23: 2002 | E23: 41.11137 | F23: 8.7637552 | G23: 9.1024145 | H23: 11.247821
A24: Africa Eastern and Southern | B24: AFE | C24: 2003 | D24: 9.7928108 | E24: 42.344633 | F24: 7.4497001 | G24: 7.8067409 | H24: 10.552602
A25: Africa Eastern and Southern | B25: AFE | C25: 2004 | D25: 10.890979 | E25: 43.032826 | F25: 5.0234207 | G25: 9.6003926 | H25: 10.505725
A26: Africa Eastern and Southern | B26: AFE | C26: 2005 | D26: 10.336474 | E26: 44.783676 | F26: 8.558038 | G26: 7.6236894 | H26: 10.722308
A27: Africa Eastern and Southern | B27: AFE | C27: 2006 | D27: 12.420047 | E27: 46.481186 | F27: 8.8981638 | G27: 7.6522543 | H27: 10.986198
A28: Africa Eastern and Southern | B28: AFE | C28: 2007 | D28: 12.364996 | E28: 48.717492 | F28: 8.4507748 | G28: 8.2457648 | H28: 11.714061
A29: Africa Eastern and Southern | B29: AFE | C29: 2008 | D29: 12.798477 | E29: 48.197285 | F29: 12.566645 | G29: 10.961412 | H29: 12.884239
A30: Africa Eastern and Southern | B30: AFE | C30: 2017 | D30: 25.375037 | E30: 44.865327 | F30: 6.2213753 | G30: 6.0750721 | H30: 10.824878
A31: Africa Eastern and Southern | B31: AFE | C31: 2018 | D31: 26.941984 | E31: 45.918925 | F31: 4.6898065 | G31: 4.3217587 | H31: 11.04845
A32: Africa Eastern and Southern | B32: AFE | C32: 2019 | D32: 28.983183 | E32: 46.33906 | F32: 4.1028508 | G32: 4.383673 | H32: 10.59159
A33: Africa Eastern and Southern | B33: AFE | C33: 2020 | D33: 30.909991 | E33: 50.315016 | F33: 5.1916294 | G33: 5.3752898 | H33: 8.3974362
A34: Africa Eastern and Southern | B34: AFE | C34: 2021 | D34: 32.709837 | E34: 48.316851 | F34: 6.8247271 | G34: 6.0881528 | H34: 8.3467495
A35: Africa Eastern and Southern | B35: AFE | C35: 2022 | D35: 33.747222 | E35: 46.410375 | F35: 10.883478 | G35: 9.0101345 | H35: 10.061505
A36: Africa Eastern and Southern | B36: AFE | C36: 2023 | D36: 35.240236 | E36: 47.987303 | F36: 7.3991856 | G36: 6.9213224 | H36: 10.879188
A37: Africa Eastern and Southern | B37: AFE | C37: 2024 | E37: 50.985869 | F37: 4.7708573 | G37: 6.077633 | H37: 10.83876
A38: Africa Western and Central | B38: AFW | C38: 2000 | D38: 16.389701 | E38: 15.195094 | F38: 2.5307752 | G38: 4.8154303 | H38: 10.761256
A39: Africa Western and Central | B39: AFW | C39: 2001 | D39: 15.831088 | E39: 111.93751 | F39: 4.3615291 | G39: 3.8617952 | H39: 11.657488
A40: Africa Western and Central | B40: AFW | C40: 2002 | D40: 15.314665 | E40: 113.34484 | F40: 3.1886933 | G40: 2.6733974 | H40: 10.67022
A41: Africa Western and Central | B41: AFW | C41: 2003 | D41: 20.585835 | E41: 107.4034 | F41: 1.7609041 | G41: 1.7188216 | H41: 10.752991
A42: Africa Western and Central | B42: AFW | C42: 2004 | D42: 16.824447 | E42: 92.25633 | F42: 0.69433631 | G42: 5.7241523 | H42: 9.9421539
A43: Africa Western and Central | B43: AFW | C43: 2005 | D43: 17.069797 | E43: 90.86939 | F43: 5.6316335 | G43: 7.2305211 | H43: 8.68849
A44: Africa Western and Central | B44: AFW | C44: 2006 | D44: 17.713585 | E44: 86.096998 | F44: 4.4158998 | G44: 5.1341037 | H44: 9.5951568
A45: Africa Western and Central | B45: AFW | C45: 2007 | D45: 17.216442 | E45: 90.560986 | F45: 3.6073677 | G45: 6.1632489 | H45: 9.9387676
A46: Africa Western and Central | B46: AFW | C46: 2008 | D46: 19.039791 | E46: 96.074461 | F46: 8.4529762 | G46: 9.6444581 | H46: 10.251422
A47: Africa Western and Central | B47: AFW | C47: 2017 | D47: 22.953401 | E47: 25.204742 | F47: 1.725486 | G47: 1.8680595 | H47: 9.7437368
A48: Africa Western and Central | B48: AFW | C48: 2018 | D48: 28.017409 | E48: 25.773212 | F48: 1.7840499 | G48: 2.1503389 | H48: 10.958693
A49: Africa Western and Central | B49: AFW | C49: 2019 | D49: 26.251358 | E49: 20.470556 | F49: 1.9830923 | G49: 1.3586285 | H49: 9.6775658
... A53: Africa Western and Central | B53: AFW | C53: 2023 | D53: 28.961344 | E53: 28.668858 | F53: 5.221168 | G53: 3.5738096 | H53: 8.6648477
A54: Africa Western and Central | B54: AFW | C54: 2024 | F54: 3.6080443 | G54: 4.0272448 | H54: 11.494902
A55: Albania | B55: ALB | C55: 2000 | D55: 100 | E55: 63.559947 | F55: 0.050018136 | G55: 5.9195735 | H55: 24.789583
A56: Albania | B56: ALB | C56: 2001 | D56: 100 | E56: 67.466477 | F56: 3.1075883 | G56: 3.7659453 | H56: 24.458841
A57: Albania | B57: ALB | C57: 2002 | D57: 100 | E57: 64.380525 | F57: 7.7705258 | G57: 3.9038814 | H57: 25.962551
A58: Albania | B58: ALB | C58: 2003 | D58: 100 | E58: 63.296713 | F58: 0.48400261 | G58: 4.9374926 | H58: 26.693325
A59: Albania | B59: ALB | C59: 2004 | D59: 100 | E59: 66.17596 | F59: 2.2800192 | G59: 3.0953665 | H59: 29.103663
A60: Albania | B60: ALB | C60: 2005 | D60: 100 | E60: 69.648068 | F60: 2.366582 | G60: 3.1437051 | H60: 32.089796
A61: Albania | B61: ALB | C61: 2006 | D61: 100 | E61: 74.242141 | F61: 2.3707283 | G61: 2.6847683 | H61: 35.181631
A62: Albania | B62: ALB | C62: 2007 | D62: 100 | E62: 75.362987 | F62: 2.9326825 | G62: 5.1495678 | H62: 36.241931
A63: Albania | B63: ALB | C63: 2008 | D63: 100 | E63: 73.333402 | F63: 3.3208709 | G63: 3.4986391 | H63: 38.528108
A64: Albania | B64: ALB | C64: 2017 | D64: 99.7 | E64: 80.23339 | F64: 1.9866613 | G64: 2.7250692 | H64: 39.667021
A65: Albania | B65: ALB | C65: 2018 | D65: 100 | E65: 76.114797 | F65: 2.0280596 | G65: 1.4532872 | H65: 38.560048
A66: Albania | B66: ALB | C66: 2019 | D66: 100 | E66: 77.022846 | F66: 1.4110908 | G66: 1.0006329 | H66: 39.790381
... A70: Albania | B70: ALB | C70: 2023 | D70: 100 | E70: 71.828751 | F70: 4.7583456 | G70: 5.733907 | H70: 45.057723
A71: Albania | B71: ALB | C71: 2024 | E71: 70.9046 | F71: 2.2158738 | G71: 2.3531809 | H71: 43.852188
A72: Algeria | B72: DZA | C72: 2000 | D72: 97.4 | E72: 37.829725 | F72: 0.33916319 | G72: 22.678009
A73: Algeria | B73: DZA | C73: 2001 | D73: 97.4 | E73: 52.381764 | F73: 4.2259883 | G73: 8.014363
A74: Algeria | B74: DZA | C74: 2002 | D74: 97.4 | E74: 57.87508 | F74: 1.4183019 | G74: 1.3728559
A75: Algeria | B75: DZA | C75: 2003 | D75: 97.4 | E75: 58.015964 | F75: 4.268954 | G75: 8.9424622
A76: Algeria | B76: DZA | C76: 2004 | D76: 97.4 | E76: 55.021864 | F76: 3.9618003 | G76: 11.446504
A77: Algeria | B77: DZA | C77: 2005 | D77: 97.4 | E77: 51.892561 | F77: 1.3824466 | G77: 12.361593 | H77: 6.8474839
A78: Algeria | B78: DZA | C78: 2006 | D78: 97.4 | E78: 54.464995 | F78: 2.3114992 | G78: 10.781184 | H78: 6.0129541
A79: Algeria | B79: DZA | C79: 2007 | D79: 97.4 | E79: 60.717363 | F79: 3.6789957 | G79: 7.0955158 | H79: 6.7620351
A80: Algeria | B80: DZA | C80: 2008 | D80: 97.9 | E80: 59.709446 | F80: 4.8585906 | G80: 15.117882 | H80: 8.0772087
A81: Algeria | B81: DZA | C81: 2017 | D81: 98.6 | E81: 71.063395 | F81: 5.5911159 | G81: 4.9380073 | H81: 7.5752446
A82: Algeria | B82: DZA | C82: 2018 | D82: 98.9 | E82: 73.341678 | F82: 4.2699902 | G82: 6.1646784 | H82: 7.7450915
A83: Algeria | B83: DZA | C83: 2019 | D83: 98.7 | E83: 71.505472 | F83: 1.9517682 | G83: 0.88299283 | H83: 6.8114722
A84: Algeria | B84: DZA | C84: 2020 | D84: 99.1 | E84: 84.871789 | F84: 2.4151309 | G84: -4.7113839 | H84: 6.3240803
A85: Algeria | B85: DZA | C85: 2021 | D85: 99.3 | E85: 79.826032 | F85: 7.2260631 | G85: 15.9326 | H85: 5.4285891
A86: Algeria | B86: DZA | C86: 2022 | D86: 99.3 | E86: 71.665003 | F86: 9.2655155 | G86: 22.920306 | H86: 5.0696726
A87: Algeria | B87: DZA | C87: 2023 | D87: 100 | E87: 72.243913 | F87: 9.3221738 | G87: 1.0015314 | H87: 4.8733878
A88: Algeria | B88: DZA | C88: 2024 | E88: 73.4802 | F88: 4.0461146 | G88: 3.3749774 | H88: 4.9582377
A89: American Samoa | B89: ASM | C89: 2003 | G89: 1.3650529
A90: American Samoa | B90: ASM | C90: 2004 | G90: -3.2590746
A91: American Samoa | B91: ASM | C91: 2005 | G91: -1.3655834
A92: American Samoa | B92: ASM | C92: 2006 | G92: 2.8136752
A93: American Samoa | B93: ASM | C93: 2007 | G93: 3.1606122
A94: American Samoa | B94: ASM | C94: 2008 | G94: 11.059335
A95: American Samoa | B95: ASM | C95: 2017 | G95: -1.9408901
A96: American Samoa | B96: ASM | C96: 2018 | G96: 1.6953611
A97: American Samoa | B97: ASM | C97: 2019 | G97: 1.7482893
A98: American Samoa | B98: ASM | C98: 2020 | G98: 6.7287807
A99: American Samoa | B99: ASM | C99: 2021 | G99: 4.8425557
A100: American Samoa | B100: ASM | C100: 2022 | G100: 14.152765
A101: Andorra | B101: AND | C101: 2000 | D101: 100 | G101: 28.741553
A102: Andorra | B102: AND | C102: 2001 | D102: 100 | G102: 3.0805352
A103: Andorra | B103: AND | C103: 2002 | D103: 100 | G103: 3.2395318
A104: Andorra | B104: AND | C104: 2003 | D104: 100 | G104: 3.1774842
A105: Andorra | B105: AND | C105: 2004 | D105: 100 | G105: 3.042424
A106: Andorra | B106: AND | C106: 2005 | D106: 100 | G106: 3.3961021
A107: Andorra | B107: AND | C107: 2006 | D107: 100 | G107: 3.4571841
A108: Andorra | B108: AND | C108: 2007 | D108: 100 | G108: 3.2112273
...

Sheet Wide Format
A1: Country Name | B1: Country Code | C1: Year | D1: Rural electricity | E1: Broad money | F1: Inflation CPI | G1: Inflation deflator | H1: Trade services
A2: Afghanistan | B2: AFG | C2: 2001 | G2: -11.774536
A3: Afghanistan | B3: AFG | C3: 2002 | G3: 6.125522
A4: Afghanistan | B4: AFG | C4: 2003 | D4: 2.1 | G4: 11.655238
A5: Afghanistan | B5: AFG | C5: 2004 | D5: 7.8 | G5: 11.271432
A6: Afghanistan | B6: AFG | C6: 2005 | D6: 15.4 | F6: 12.686269 | G6: 10.912774
A7: Afghanistan | B7: AFG | C7: 2006 | D7: 19.3 | E7: 23.343865 | F7: 6.7845966 | G7: 7.1997513
A8: Afghanistan | B8: AFG | C8: 2007 | D8: 25 | E8: 23.833664 | F8: 8.6805708 | G8: 22.527756
A9: Afghanistan | B9: AFG | C9: 2008 | D9: 28 | E9: 29.512281 | F9: 26.418664 | G9: 2.0962888 | H9: 20.211726
A10: Afghanistan | B10: AFG | C10: 2017 | D10: 97.1 | E10: 36.861261 | F10: 4.9759515 | G10: 2.4036562 | H10: 8.5806823
A11: Afghanistan | B11: AFG | C11: 2018 | D11: 91.6 | E11: 36.607494 | F11: 0.62614915 | G11: 2.0713486 | H11: 11.638305
A12: Afghanistan | B12: AFG | C12: 2019 | D12: 97.1 | E12: 34.959214 | F12: 2.3023725 | G12: 6.5214798 | H12: 9.918134
A13: Afghanistan | B13: AFG | C13: 2020 | D13: 97.1 | E13: 37.508189 | F13: 5.6018879 | G13: 6.9629463 | H13: 9.0438455
A14: Afghanistan | B14: AFG | C14: 2021 | D14: 97.1 | F14: 5.1332034 | G14: 2.8389963
A15: Afghanistan | B15: AFG | C15: 2022 | D15: 81.7 | F15: 13.712102 | G15: 9.4062393
A16: Afghanistan | B16: AFG | C16: 2023 | D16: 81.4 | F16: -4.6447087 | G16: 2.9236621
A17: Afghanistan | B17: AFG | C17: 2024 | F17: -6.6011856
A18: Africa Eastern and Southern | B18: AFE | C18: 2000 | D18: 8.6726535 | E18: 35.852469 | F18: 8.6014851 | G18: 11.117306 | H18: 10.502052
A19: Africa Eastern and Southern | B19: AFE | C19: 2001 | E19: 39.613793 | F19: 5.840354 | G19: 8.2433867 | H19: 11.24503
A20: Africa Eastern and Southern | B20: AFE | C20: 2002 | E20: 41.11137 | F20: 8.7637552 | G20: 9.1024145 | H20: 11.247821
A21: Africa Eastern and Southern | B21: AFE | C21: 2003 | D21: 9.7928108 | E21: 42.344633 | F21: 7.4497001 | G21: 7.8067409 | H21: 10.552602
A22: Africa Eastern and Southern | B22: AFE | C22: 2004 | D22: 10.890979 | E22: 43.032826 | F22: 5.0234207 | G22: 9.6003926 | H22: 10.505725
A23: Africa Eastern and Southern | B23: AFE | C23: 2005 | D23: 10.336474 | E23: 44.783676 | F23: 8.558038 | G23: 7.6236894 | H23: 10.722308
A24: Africa Eastern and Southern | B24: AFE | C24: 2006 | D24: 12.420047 | E24: 46.481186 | F24: 8.8981638 | G24: 7.6522543 | H24: 10.986198
A25: Africa Eastern and Southern | B25: AFE | C25: 2007 | D25: 12.364996 | E25: 48.717492 | F25: 8.4507748 | G25: 8.2457648 | H25: 11.714061
A26: Africa Eastern and Southern | B26: AFE | C26: 2008 | D26: 12.798477 | E26: 48.197285 | F26: 12.566645 | G26: 10.961412 | H26: 12.884239
A27: Africa Eastern and Southern | B27: AFE | C27: 2017 | D27: 25.375037 | E27: 44.865327 | F27: 6.2213753 | G27: 6.0750721 | H27: 10.824878
A28: Africa Eastern and Southern | B28: AFE | C28: 2018 | D28: 26.941984 | E28: 45.918925 | F28: 4.6898065 | G28: 4.3217587 | H28: 11.04845
A29: Africa Eastern and Southern | B29: AFE | C29: 2019 | D29: 28.983183 | E29: 46.33906 | F29: 4.1028508 | G29: 4.383673 | H29: 10.59159
A30: Africa Eastern and Southern | B30: AFE | C30: 2020 | D30: 30.909991 | E30: 50.315016 | F30: 5.1916294 | G30: 5.3752898 | H30: 8.3974362
A31: Africa Eastern and Southern | B31: AFE | C31: 2021 | D31: 32.709837 | E31: 48.316851 | F31: 6.8247271 | G31: 6.0881528 | H31: 8.3467495
A32: Africa Eastern and Southern | B32: AFE | C32: 2022 | D32: 33.747222 | E32: 46.410375 | F32: 10.883478 | G32: 9.0101345 | H32: 10.061505
A33: Africa Eastern and Southern | B33: AFE | C33: 2023 | D33: 35.240236 | E33: 47.987303 | F33: 7.3991856 | G33: 6.9213224 | H33: 10.879188
A34: Africa Eastern and Southern | B34: AFE | C34: 2024 | E34: 50.985869 | F34: 4.7708573 | G34: 6.077633 | H34: 10.83876
A35: Africa Western and Central | B35: AFW | C35: 2000 | D35: 16.389701 | E35: 15.195094 | F35: 2.5307752 | G35: 4.8154303 | H35: 10.761256
A36: Africa Western and Central | B36: AFW | C36: 2001 | D36: 15.831088 | E36: 111.93751 | F36: 4.3615291 | G36: 3.8617952 | H36: 11.657488
A37: Africa Western and Central | B37: AFW | C37: 2002 | D37: 15.314665 | E37: 113.34484 | F37: 3.1886933 | G37: 2.6733974 | H37: 10.67022
A38: Africa Western and Central | B38: AFW | C38: 2003 | D38: 20.585835 | E38: 107.4034 | F38: 1.7609041 | G38: 1.7188216 | H38: 10.752991
A39: Africa Western and Central | B39: AFW | C39: 2004 | D39: 16.824447 | E39: 92.25633 | F39: 0.69433631 | G39: 5.7241523 | H39: 9.9421539
A40: Africa Western and Central | B40: AFW | C40: 2005 | D40: 17.069797 | E40: 90.86939 | F40: 5.6316335 | G40: 7.2305211 | H40: 8.68849
A41: Africa Western and Central | B41: AFW | C41: 2006 | D41: 17.713585 | E41: 86.096998 | F41: 4.4158998 | G41: 5.1341037 | H41: 9.5951568
A42: Africa Western and Central | B42: AFW | C42: 2007 | D42: 17.216442 | E42: 90.560986 | F42: 3.6073677 | G42: 6.1632489 | H42: 9.9387676
A43: Africa Western and Central | B43: AFW | C43: 2008 | D43: 19.039791 | E43: 96.074461 | F43: 8.4529762 | G43: 9.6444581 | H43: 10.251422
A44: Africa Western and Central | B44: AFW | C44: 2017 | D44: 22.953401 | E44: 25.204742 | F44: 1.725486 | G44: 1.8680595 | H44: 9.7437368
A45: Africa Western and Central | B45: AFW | C45: 2018 | D45: 28.017409 | E45: 25.773212 | F45: 1.7840499 | G45: 2.1503389 | H45: 10.958693
A46: Africa Western and Central | B46: AFW | C46: 2019 | D46: 26.251358 | E46: 20.470556 | F46: 1.9830923 | G46: 1.3586285 | H46: 9.6775658
... A50: Africa Western and Central | B50: AFW | C50: 2023 | D50: 28.961344 | E50: 28.668858 | F50: 5.221168 | G50: 3.5738096 | H50: 8.6648477
A51: Africa Western and Central | B51: AFW | C51: 2024 | F51: 3.6080443 | G51: 4.0272448 | H51: 11.494902
A52: Albania | B52: ALB | C52: 2000 | D52: 100 | E52: 63.559947 | F52: 0.050018136 | G52: 5.9195735 | H52: 24.789583
A53: Albania | B53: ALB | C53: 2001 | D53: 100 | E53: 67.466477 | F53: 3.1075883 | G53: 3.7659453 | H53: 24.458841
A54: Albania | B54: ALB | C54: 2002 | D54: 100 | E54: 64.380525 | F54: 7.7705258 | G54: 3.9038814 | H54: 25.962551
A55: Albania | B55: ALB | C55: 2003 | D55: 100 | E55: 63.296713 | F55: 0.48400261 | G55: 4.9374926 | H55: 26.693325
A56: Albania | B56: ALB | C56: 2004 | D56: 100 | E56: 66.17596 | F56: 2.2800192 | G56: 3.0953665 | H56: 29.103663
A57: Albania | B57: ALB | C57: 2005 | D57: 100 | E57: 69.648068 | F57: 2.366582 | G57: 3.1437051 | H57: 32.089796
A58: Albania | B58: ALB | C58: 2006 | D58: 100 | E58: 74.242141 | F58: 2.3707283 | G58: 2.6847683 | H58: 35.181631
A59: Albania | B59: ALB | C59: 2007 | D59: 100 | E59: 75.362987 | F59: 2.9326825 | G59: 5.1495678 | H59: 36.241931
A60: Albania | B60: ALB | C60: 2008 | D60: 100 | E60: 73.333402 | F60: 3.3208709 | G60: 3.4986391 | H60: 38.528108
A61: Albania | B61: ALB | C61: 2017 | D61: 99.7 | E61: 80.23339 | F61: 1.9866613 | G61: 2.7250692 | H61: 39.667021
A62: Albania | B62: ALB | C62: 2018 | D62: 100 | E62: 76.114797 | F62: 2.0280596 | G62: 1.4532872 | H62: 38.560048
A63: Albania | B63: ALB | C63: 2019 | D63: 100 | E63: 77.022846 | F63: 1.4110908 | G63: 1.0006329 | H63: 39.790381
... A67: Albania | B67: ALB | C67: 2023 | D67: 100 | E67: 71.828751 | F67: 4.7583456 | G67: 5.733907 | H67: 45.057723
A68: Albania | B68: ALB | C68: 2024 | E68: 70.9046 | F68: 2.2158738 | G68: 2.3531809 | H68: 43.852188
A69: Algeria | B69: DZA | C69: 2000 | D69: 97.4 | E69: 37.829725 | F69: 0.33916319 | G69: 22.678009
A70: Algeria | B70: DZA | C70: 2001 | D70: 97.4 | E70: 52.381764 | F70: 4.2259883 | G70: 8.014363
A71: Algeria | B71: DZA | C71: 2002 | D71: 97.4 | E71: 57.87508 | F71: 1.4183019 | G71: 1.3728559
A72: Algeria | B72: DZA | C72: 2003 | D72: 97.4 | E72: 58.015964 | F72: 4.268954 | G72: 8.9424622
A73: Algeria | B73: DZA | C73: 2004 | D73: 97.4 | E73: 55.021864 | F73: 3.9618003 | G73: 11.446504
A74: Algeria | B74: DZA | C74: 2005 | D74: 97.4 | E74: 51.892561 | F74: 1.3824466 | G74: 12.361593 | H74: 6.8474839
A75: Algeria | B75: DZA | C75: 2006 | D75: 97.4 | E75: 54.464995 | F75: 2.3114992 | G75: 10.781184 | H75: 6.0129541
A76: Algeria | B76: DZA | C76: 2007 | D76: 97.4 | E76: 60.717363 | F76: 3.6789957 | G76: 7.0955158 | H76: 6.7620351
A77: Algeria | B77: DZA | C77: 2008 | D77: 97.9 | E77: 59.709446 | F77: 4.8585906 | G77: 15.117882 | H77: 8.0772087
A78: Algeria | B78: DZA | C78: 2017 | D78: 98.6 | E78: 71.063395 | F78: 5.5911159 | G78: 4.9380073 | H78: 7.5752446
A79: Algeria | B79: DZA | C79: 2018 | D79: 98.9 | E79: 73.341678 | F79: 4.2699902 | G79: 6.1646784 | H79: 7.7450915
A80: Algeria | B80: DZA | C80: 2019 | D80: 98.7 | E80: 71.505472 | F80: 1.9517682 | G80: 0.88299283 | H80: 6.8114722
A81: Algeria | B81: DZA | C81: 2020 | D81: 99.1 | E81: 84.871789 | F81: 2.4151309 | G81: -4.7113839 | H81: 6.3240803
A82: Algeria | B82: DZA | C82: 2021 | D82: 99.3 | E82: 79.826032 | F82: 7.2260631 | G82: 15.9326 | H82: 5.4285891
A83: Algeria | B83: DZA | C83: 2022 | D83: 99.3 | E83: 71.665003 | F83: 9.2655155 | G83: 22.920306 | H83: 5.0696726
A84: Algeria | B84: DZA | C84: 2023 | D84: 100 | E84: 72.243913 | F84: 9.3221738 | G84: 1.0015314 | H84: 4.8733878
A85: Algeria | B85: DZA | C85: 2024 | E85: 73.4802 | F85: 4.0461146 | G85: 3.3749774 | H85: 4.9582377
A86: American Samoa | B86: ASM | C86: 2003 | G86: 1.3650529
A87: American Samoa | B87: ASM | C87: 2004 | G87: -3.2590746
A88: American Samoa | B88: ASM | C88: 2005 | G88: -1.3655834
A89: American Samoa | B89: ASM | C89: 2006 | G89: 2.8136752
A90: American Samoa | B90: ASM | C90: 2007 | G90: 3.1606122
A91: American Samoa | B91: ASM | C91: 2008 | G91: 11.059335
A92: American Samoa | B92: ASM | C92: 2017 | G92: -1.9408901
A93: American Samoa | B93: ASM | C93: 2018 | G93: 1.6953611
A94: American Samoa | B94: ASM | C94: 2019 | G94: 1.7482893
A95: American Samoa | B95: ASM | C95: 2020 | G95: 6.7287807
A96: American Samoa | B96: ASM | C96: 2021 | G96: 4.8425557
A97: American Samoa | B97: ASM | C97: 2022 | G97: 14.152765
A98: Andorra | B98: AND | C98: 2000 | D98: 100 | G98: 28.741553
A99: Andorra | B99: AND | C99: 2001 | D99: 100 | G99: 3.0805352
A100: Andorra | B100: AND | C100: 2002 | D100: 100 | G100: 3.2395318
A101: Andorra | B101: AND | C101: 2003 | D101: 100 | G101: 3.1774842
A102: Andorra | B102: AND | C102: 2004 | D102: 100 | G102: 3.042424
A103: Andorra | B103: AND | C103: 2005 | D103: 100 | G103: 3.3961021
A104: Andorra | B104: AND | C104: 2006 | D104: 100 | G104: 3.4571841
A105: Andorra | B105: AND | C105: 2007 | D105: 100 | G105: 3.2112273
A106: Andorra | B106: AND | C106: 2008 | D106: 100 | G106: 2.2743383
...

Sheet Correlation Matrix
B1: Rural electricity | C1: Broad money | D1: Inflation CPI | E1: Inflation deflator | F1: Trade services
A2: Rural electricity | B2: =CORREL('Wide Format'!D2:D4432,'Wide Format'!D2:D4432) -> 1 | C2: =CORREL('Wide Format'!E2:E4432,'Wide Format'!D2:D4432) -> 0.031387031 | D2: =CORREL('Wide Format'!F2:F4432,'Wide Format'!D2:D4432) -> -0.10841764 | E2: =CORREL('Wide Format'!G2:G4432,'Wide Format'!D2:D4432) -> 0.011959459 | F2: =CORREL('Wide Format'!H2:H4432,'Wide Format'!D2:D4432) -> 0.22533959
A3: Broad money | B3: =CORREL('Wide Format'!D2:D4432,'Wide Format'!E2:E4432) -> 0.031387031 | C3: =CORREL('Wide Format'!E2:E4432,'Wide Format'!E2:E4432) -> 1 | D3: =CORREL('Wide Format'!F2:F4432,'Wide Format'!E2:E4432) -> -0.021993382 | E3: =CORREL('Wide Format'!G2:G4432,'Wide Format'!E2:E4432) -> 0.010764517 | F3: =CORREL('Wide Format'!H2:H4432,'Wide Format'!E2:E4432) -> -0.020127612
A4: Inflation CPI | B4: =CORREL('Wide Format'!D2:D4432,'Wide Format'!F2:F4432) -> -0.10841764 | C4: =CORREL('Wide Format'!E2:E4432,'Wide Format'!F2:F4432) -> -0.021993382 | D4: =CORREL('Wide Format'!F2:F4432,'Wide Format'!F2:F4432) -> 1 | E4: =CORREL('Wide Format'!G2:G4432,'Wide Format'!F2:F4432) -> 0.69869289 | F4: =CORREL('Wide Format'!H2:H4432,'Wide Format'!F2:F4432) -> -0.069494584
A5: Inflation deflator | B5: =CORREL('Wide Format'!D2:D4432,'Wide Format'!G2:G4432) -> 0.011959459 | C5: =CORREL('Wide Format'!E2:E4432,'Wide Format'!G2:G4432) -> 0.010764517 | D5: =CORREL('Wide Format'!F2:F4432,'Wide Format'!G2:G4432) -> 0.69869289 | E5: =CORREL('Wide Format'!G2:G4432,'Wide Format'!G2:G4432) -> 1 | F5: =CORREL('Wide Format'!H2:H4432,'Wide Format'!G2:G4432) -> -0.064449334
A6: Trade services | B6: =CORREL('Wide Format'!D2:D4432,'Wide Format'!H2:H4432) -> 0.22533959 | C6: =CORREL('Wide Format'!E2:E4432,'Wide Format'!H2:H4432) -> -0.020127612 | D6: =CORREL('Wide Format'!F2:F4432,'Wide Format'!H2:H4432) -> -0.069494584 | E6: =CORREL('Wide Format'!G2:G4432,'Wide Format'!H2:H4432) -> -0.064449334 | F6: =CORREL('Wide Format'!H2:H4432,'Wide Format'!H2:H4432) -> 1

Sheet Country Rankings
A1: Country Name | B1: Country Code | C1: Avg Rural Electricity | D1: Rank | E1: Tier | F1: Avg Trade Services | G1: Trade Services Rank | H1: Trade Services Tier
A2: Luxembourg | B2: =VLOOKUP(A2,'Wide Format'!A:B,2,0) -> LUX | C2: =IFERROR(AVERAGEIFS('Long Format'!F147:F18398,'Long Format'!A147:A18398,A2,'Long Format'!C147:C18398,"Access to electricity, rural (% of rural population)"),"No Data") -> 100 | D2: =IFERROR(RANK(C2,C$2:C$257,0),"") -> 1 | E2: =IF(C2="No Data","No Data",IF(C2>=75,"High",IF(C2>=50,"Medium",IF(C2>=25,"Low","Very Low")))) -> High | F2: =IFERROR(AVERAGEIFS('Long Format'!F41:F18292,'Long Format'!A41:A18292,A2,'Long Format'!C41:C18292,"Trade in services (% of GDP)"),"No Data") -> 234.64078 | G2: =IFERROR(RANK(F2,F$2:F$257,0),"") -> 1 | H2: =IF(F2="No Data","No Data",IF(F2>=50,"High",IF(F2>=25,"Medium",IF(F2>=10,"Low","Very Low")))) -> High
A3: Malta | B3: =VLOOKUP(A3,'Wide Format'!A:B,2,0) -> MLT | C3: =IFERROR(AVERAGEIFS('Long Format'!F154:F18405,'Long Format'!A154:A18405,A3,'Long Format'!C154:C18405,"Access to electricity, rural (% of rural population)"),"No Data") -> 100 | D3: =IFERROR(RANK(C3,C$2:C$257,0),"") -> 1 | E3: =IF(C3="No Data","No Data",IF(C3>=75,"High",IF(C3>=50,"Medium",IF(C3>=25,"Low","Very Low")))) -> High | F3: =IFERROR(AVERAGEIFS('Long Format'!F43:F18294,'Long Format'!A43:A18294,A3,'Long Format'!C43:C18294,"Trade in services (% of GDP)"),"No Data") -> 133.25236 | G3: =IFERROR(RANK(F3,F$2:F$257,0),"") -> 2 | H3: =IF(F3="No Data","No Data",IF(F3>=50,"High",IF(F3>=25,"Medium",IF(F3>=10,"Low","Very Low")))) -> High
A4: Ireland | B4: =VLOOKUP(A4,'Wide Format'!A:B,2,0) -> IRL | C4: =IFERROR(AVERAGEIFS('Long Format'!F117:F18368,'Long Format'!A117:A18368,A4,'Long Format'!C117:C18368,"Access to electricity, rural (% of rural population)"),"No Data") -> 100 | D4: =IFERROR(RANK(C4,C$2:C$257,0),"") -> 1 | E4: =IF(C4="No Data","No Data",IF(C4>=75,"High",IF(C4>=50,"Medium",IF(C4>=25,"Low","Very Low")))) -> High | F4: =IFERROR(AVERAGEIFS('Long Format'!F33:F18284,'Long Format'!A33:A18284,A4,'Long Format'!C33:C18284,"Trade in services (% of GDP)"),"No Data") -> 121.71304 | G4: =IFERROR(RANK(F4,F$2:F$257,0),"") -> 3 | H4: =IF(F4="No Data","No Data",IF(F4>=50,"High",IF(F4>=25,"Medium",IF(F4>=10,"Low","Very Low")))) -> High
A5: Aruba | B5: =VLOOKUP(A5,'Wide Format'!A:B,2,0) -> ABW | C5: =IFERROR(AVERAGEIFS('Long Format'!F14:F18265,'Long Format'!A14:A18265,A5,'Long Format'!C14:C18265,"Access to electricity, rural (% of rural population)"),"No Data") -> 100 | D5: =IFERROR(RANK(C5,C$2:C$257,0),"") -> 1 | E5: =IF(C5="No Data","No Data",IF(C5>=75,"High",IF(C5>=50,"Medium",IF(C5>=25,"Low","Very Low")))) -> High | F5: =IFERROR(AVERAGEIFS('Long Format'!F3:F18254,'Long Format'!A3:A18254,A5,'Long Format'!C3:C18254,"Trade in services (% of GDP)"),"No Data") -> 99.665337 | G5: =IFERROR(RANK(F5,F$2:F$257,0),"") -> 4 | H5: =IF(F5="No Data","No Data",IF(F5>=50,"High",IF(F5>=25,"Medium",IF(F5>=10,"Low","Very Low")))) -> High
A6: Singapore | B6: =VLOOKUP(A6,'Wide Format'!A:B,2,0) -> SGP | C6: =IFERROR(AVERAGEIFS('Long Format'!F212:F18463,'Long Format'!A212:A18463,A6,'Long Format'!C212:C18463,"Access to electricity, rural (% of rural population)"),"No Data") -> 100 | D6: =IFERROR(RANK(C6,C$2:C$257,0),"") -> 1 | E6: =IF(C6="No Data","No Data",IF(C6>=75,"High",IF(C6>=50,"Medium",IF(C6>=25,"Low","Very Low")))) -> High | F6: =IFERROR(AVERAGEIFS('Long Format'!F58:F18309,'Long Format'!A58:A18309,A6,'Long Format'!C58:C18309,"Trade in services (% of GDP)"),"No Data") -> 97.125778 | G6: =IFERROR(RANK(F6,F$2:F$257,0),"") -> 5 | H6: =IF(F6="No Data","No Data",IF(F6>=50,"High",IF(F6>=25,"Medium",IF(F6>=10,"Low","Very Low")))) -> High
A7: Seychelles | B7: =VLOOKUP(A7,'Wide Format'!A:B,2,0) -> SYC | C7: =IFERROR(AVERAGEIFS('Long Format'!F210:F18461,'Long Format'!A210:A18461,A7,'Long Format'!C210:C18461,"Access to electricity, rural (% of rural population)"),"No Data") -> 95.84375 | D7: =IFERROR(RANK(C7,C$2:C$257,0),"") -> 120 | E7: =IF(C7="No Data","No Data",IF(C7>=75,"High",IF(C7>=50,"Medium",IF(C7>=25,"Low","Very Low")))) -> High | F7: =IFERROR(AVERAGEIFS('Long Format'!F121:F18372,'Long Format'!A121:A18372,A7,'Long Format'!C121:C18372,"Trade in services (% of GDP)"),"No Data") -> 96.545031 | G7: =IFERROR(RANK(F7,F$2:F$257,0),"") -> 6 | H7: =IF(F7="No Data","No Data",IF(F7>=50,"High",IF(F7>=25,"Medium",IF(F7>=10,"Low","Very Low")))) -> High
A8: San Marino | B8: =VLOOKUP(A8,'Wide Format'!A:B,2,0) -> SMR | C8: =IFERROR(AVERAGEIFS('Long Format'!F205:F18456,'Long Format'!A205:A18456,A8,'Long Format'!C205:C18456,"Access to electricity, rural (% of rural population)"),"No Data") -> 100 | D8: =IFERROR(RANK(C8,C$2:C$257,0),"") -> 1 | E8: =IF(C8="No Data","No Data",IF(C8>=75,"High",IF(C8>=50,"Medium",IF(C8>=25,"Low","Very Low")))) -> High | F8: =IFERROR(AVERAGEIFS('Long Format'!F56:F18307,'Long Format'!A56:A18307,A8,'Long Format'!C56:C18307,"Trade in services (% of GDP)"),"No Data") -> 93.280293 | G8: =IFERROR(RANK(F8,F$2:F$257,0),"") -> 7 | H8: =IF(F8="No Data","No Data",IF(F8>=50,"High",IF(F8>=25,"Medium",IF(F8>=10,"Low","Very Low")))) -> High
A9: Andorra | B9: =VLOOKUP(A9,'Wide Format'!A:B,2,0) -> AND | C9: =IFERROR(AVERAGEIFS('Long Format'!F8:F18259,'Long Format'!A8:A18259,A9,'Long Format'!C8:C18259,"Access to electricity, rural (% of rural population)"),"No Data") -> 100 | D9: =IFERROR(RANK(C9,C$2:C$257,0),"") -> 1 | E9: =IF(C9="No Data","No Data",IF(C9>=75,"High",IF(C9>=50,"Medium",IF(C9>=25,"Low","Very Low")))) -> High | F9: =IFERROR(AVERAGEIFS('Long Format'!F2:F18253,'Long Format'!A2:A18253,A9,'Long Format'!C2:C18253,"Trade in services (% of GDP)"),"No Data") -> 92.268316 | G9: =IFERROR(RANK(F9,F$2:F$257,0),"") -> 8 | H9: =IF(F9="No Data","No Data",IF(F9>=50,"High",IF(F9>=25,"Medium",IF(F9>=10,"Low","Very Low")))) -> High
A10: Antigua and Barbuda | B10: =VLOOKUP(A10,'Wide Format'!A:B,2,0) -> ATG | C10: =IFERROR(AVERAGEIFS('Long Format'!F10:F18261,'Long Format'!A10:A18261,A10,'Long Format'!C10:C18261,"Access to electricity, rural (% of rural population)"),"No Data") -> 99.2125 | D10: =IFERROR(RANK(C10,C$2:C$257,0),"") -> 94 | E10: =IF(C10="No Data","No Data",IF(C10>=75,"High",IF(C10>=50,"Medium",IF(C10>=25,"Low","Very Low")))) -> High | F10: =IFERROR(AVERAGEIFS('Long Format'!F95:F18346,'Long Format'!A95:A18346,A10,'Long Format'!C95:C18346,"Trade in services (% of GDP)"),"No Data") -> 87.604985 | G10: =IFERROR(RANK(F10,F$2:F$257,0),"") -> 9 | H10: =IF(F10="No Data","No Data",IF(F10>=50,"High",IF(F10>=25,"Medium",IF(F10>=10,"Low","Very Low")))) -> High
A11: Cayman Islands | B11: =VLOOKUP(A11,'Wide Format'!A:B,2,0) -> CYM | C11: =IFERROR(AVERAGEIFS('Long Format'!F42:F18293,'Long Format'!A42:A18293,A11,'Long Format'!C42:C18293,"Access to electricity, rural (% of rural population)"),"No Data") -> 100 | D11: =IFERROR(RANK(C11,C$2:C$257,0),"") -> 1 | E11: =IF(C11="No Data","No Data",IF(C11>=75,"High",IF(C11>=50,"Medium",IF(C11>=25,"Low","Very Low")))) -> High | F11: =IFERROR(AVERAGEIFS('Long Format'!F12:F18263,'Long Format'!A12:A18263,A11,'Long Format'!C12:C18263,"Trade in services (% of GDP)"),"No Data") -> 86.511674 | G11: =IFERROR(RANK(F11,F$2:F$257,0),"") -> 10 | H11: =IF(F11="No Data","No Data",IF(F11>=50,"High",IF(F11>=25,"Medium",IF(F11>=10,"Low","Very Low")))) -> High
A12: Cyprus | B12: =VLOOKUP(A12,'Wide Format'!A:B,2,0) -> CYP | C12: =IFERROR(AVERAGEIFS('Long Format'!F58:F18309,'Long Format'!A58:A18309,A12,'Long Format'!C58:C18309,"Access to electricity, rural (% of rural population)"),"No Data") -> 100 | D12: =IFERROR(RANK(C12,C$2:C$257,0),"") -> 1 | E12: =IF(C12="No Data","No Data",IF(C12>=75,"High",IF(C12>=50,"Medium",IF(C12>=25,"Low","Very Low")))) -> High | F12: =IFERROR(AVERAGEIFS('Long Format'!F16:F18267,'Long Format'!A16:A18267,A12,'Long Format'!C16:C18267,"Trade in services (% of GDP)"),"No Data") -> 85.355031 | G12: =IFERROR(RANK(F12,F$2:F$257,0),"") -> 11 | H12: =IF(F12="No Data","No Data",IF(F12>=50,"High",IF(F12>=25,"Medium",IF(F12>=10,"Low","Very Low")))) -> High
A13: Macao SAR, China | B13: =VLOOKUP(A13,'Wide Format'!A:B,2,0) -> MAC | C13: =IFERROR(AVERAGEIFS('Long Format'!F148:F18399,'Long Format'!A148:A18399,A13,'Long Format'!C148:C18399,"Access to electricity, rural (% of rural population)"),"No Data") -> 100 | D13: =IFERROR(RANK(C13,C$2:C$257,0),"") -> 1 | E13: =IF(C13="No Data","No Data",IF(C13>=75,"High",IF(C13>=50,"Medium",IF(C13>=25,"Low","Very Low")))) -> High | F13: =IFERROR(AVERAGEIFS('Long Format'!F42:F18293,'Long Format'!A42:A18293,A13,'Long Format'!C42:C18293,"Trade in services (% of GDP)"),"No Data") -> 79.609077 | G13: =IFERROR(RANK(F13,F$2:F$257,0),"") -> 12 | H13: =IF(F13="No Data","No Data",IF(F13>=50,"High",IF(F13>=25,"Medium",IF(F13>=10,"Low","Very Low")))) -> High
A14: Tuvalu | B14: =VLOOKUP(A14,'Wide Format'!A:B,2,0) -> TUV | C14: =IFERROR(AVERAGEIFS('Long Format'!F248:F18499,'Long Format'!A248:A18499,A14,'Long Format'!C248:C18499,"Access to electricity, rural (% of rural population)"),"No Data") -> 96.09375 | D14: =IFERROR(RANK(C14,C$2:C$257,0),"") -> 117 | E14: =IF(C14="No Data","No Data",IF(C14>=75,"High",IF(C14>=50,"Medium",IF(C14>=25,"Low","Very Low")))) -> High | F14: =IFERROR(AVERAGEIFS('Long Format'!F118:F18369,'Long Format'!A118:A18369,A14,'Long Format'!C118:C18369,"Trade in services (% of GDP)"),"No Data") -> 77.755611 | G14: =IFERROR(RANK(F14,F$2:F$257,0),"") -> 13 | H14: =IF(F14="No Data","No Data",IF(F14>=50,"High",IF(F14>=25,"Medium",IF(F14>=10,"Low","Very Low")))) -> High
A15: Sint Maarten (Dutch part) | B15: =VLOOKUP(A15,'Wide Format'!A:B,2,0) -> SXM | C15: =IFERROR(AVERAGEIFS('Long Format'!F213:F18464,'Long Format'!A213:A18464,A15,'Long Format'!C213:C18464,"Access to electricity, rural (% of rural population)"),"No Data") -> 100 | D15: =IFERROR(RANK(C15,C$2:C$257,0),"") -> 1 | E15: =IF(C15="No Data","No Data",IF(C15>=75,"High",IF(C15>=50,"Medium",IF(C15>=25,"Low","Very Low")))) -> High | F15: =IFERROR(AVERAGEIFS('Long Format'!F59:F18310,'Long Format'!A59:A18310,A15,'Long Format'!C59:C18310,"Trade in services (% of GDP)"),"No Data") -> 76.654681 | G15: =IFERROR(RANK(F15,F$2:F$257,0),"") -> 14 | H15: =IF(F15="No Data","No Data",IF(F15>=50,"High",IF(F15>=25,"Medium",IF(F15>=10,"Low","Very Low")))) -> High
A16: Maldives | B16: =VLOOKUP(A16,'Wide Format'!A:B,2,0) -> MDV | C16: =IFERROR(AVERAGEIFS('Long Format'!F152:F18403,'Long Format'!A152:A18403,A16,'Long Format'!C152:C18403,"Access to electricity, rural (% of rural population)"),"No Data") -> 91.74375 | D16: =IFERROR(RANK(C16,C$2:C$257,0),"") -> 134 | E16: =IF(C16="No Data","No Data",IF(C16>=75,"High",IF(C16>=50,"Medium",IF(C16>=25,"Low","Very Low")))) -> High | F16: =IFERROR(AVERAGEIFS('Long Format'!F135:F18386,'Long Format'!A135:A18386,A16,'Long Format'!C135:C18386,"Trade in services (% of GDP)"),"No Data") -> 75.090492 | G16: =IFERROR(RANK(F16,F$2:F$257,0),"") -> 15 | H16: =IF(F16="No Data","No Data",IF(F16>=50,"High",IF(F16>=25,"Medium",IF(F16>=10,"Low","Very Low")))) -> High
A17: St. Kitts and Nevis | B17: =VLOOKUP(A17,'Wide Format'!A:B,2,0) -> KNA | C17: =IFERROR(AVERAGEIFS('Long Format'!F225:F18476,'Long Format'!A225:A18476,A17,'Long Format'!C225:C18476,"Access to electricity, rural (% of rural population)"),"No Data") -> 96.90625 | D17: =IFERROR(RANK(C17,C$2:C$257,0),"") -> 113 | E17: =IF(C17="No Data","No Data",IF(C17>=75,"High",IF(C17>=50,"Medium",IF(C17>=25,"Low","Very Low")))) -> High | F17: =IFERROR(AVERAGEIFS('Long Format'!F114:F18365,'Long Format'!A114:A18365,A17,'Long Format'!C114:C18365,"Trade in services (% of GDP)"),"No Data") -> 70.36268 | G17: =IFERROR(RANK(F17,F$2:F$257,0),"") -> 16 | H17: =IF(F17="No Data","No Data",IF(F17>=50,"High",IF(F17>=25,"Medium",IF(F17>=10,"Low","Very Low")))) -> High
A18: Lebanon | B18: =VLOOKUP(A18,'Wide Format'!A:B,2,0) -> LBN | C18: =IFERROR(AVERAGEIFS('Long Format'!F138:F18389,'Long Format'!A138:A18389,A18,'Long Format'!C138:C18389,"Access to electricity, rural (% of rural population)"),"No Data") -> 98.69375 | D18: =IFERROR(RANK(C18,C$2:C$257,0),"") -> 100 | E18: =IF(C18="No Data","No Data",IF(C18>=75,"High",IF(C18>=50,"Medium",IF(C18>=25,"Low","Very Low")))) -> High | F18: =IFERROR(AVERAGEIFS('Long Format'!F101:F18352,'Long Format'!A101:A18352,A18,'Long Format'!C101:C18352,"Trade in services (% of GDP)"),"No Data") -> 68.955053 | G18: =IFERROR(RANK(F18,F$2:F$257,0),"") -> 17 | H18: =IF(F18="No Data","No Data",IF(F18>=50,"High",IF(F18>=25,"Medium",IF(F18>=10,"Low","Very Low")))) -> High
A19: Curacao | B19: =VLOOKUP(A19,'Wide Format'!A:B,2,0) -> CUW | C19: =IFERROR(AVERAGEIFS('Long Format'!F57:F18308,'Long Format'!A57:A18308,A19,'Long Format'!C57:C18308,"Access to electricity, rural (% of rural population)"),"No Data") -> 100 | D19: =IFERROR(RANK(C19,C$2:C$257,0),"") -> 1 | E19: =IF(C19="No Data","No Data",IF(C19>=75,"High",IF(C19>=50,"Medium",IF(C19>=25,"Low","Very Low")))) -> High | F19: =IFERROR(AVERAGEIFS('Long Format'!F15:F18266,'Long Format'!A15:A18266,A19,'Long Format'!C15:C18266,"Trade in services (% of GDP)"),"No Data") -> 68.717399 | G19: =IFERROR(RANK(F19,F$2:F$257,0),"") -> 18 | H19: =IF(F19="No Data","No Data",IF(F19>=50,"High",IF(F19>=25,"Medium",IF(F19>=10,"Low","Very Low")))) -> High
A20: Nauru | B20: =VLOOKUP(A20,'Wide Format'!A:B,2,0) -> NRU | C20: =IFERROR(AVERAGEIFS('Long Format'!F172:F18423,'Long Format'!A172:A18423,A20,'Long Format'!C172:C18423,"Access to electricity, rural (% of rural population)"),"No Data") -> 100 | D20: =IFERROR(RANK(C20,C$2:C$257,0),"") -> 1 | E20: =IF(C20="No Data","No Data",IF(C20>=75,"High",IF(C20>=50,"Medium",IF(C20>=25,"Low","Very Low")))) -> High | F20: =IFERROR(AVERAGEIFS('Long Format'!F45:F18296,'Long Format'!A45:A18296,A20,'Long Format'!C45:C18296,"Trade in services (% of GDP)"),"No Data") -> 62.644675 | G20: =IFERROR(RANK(F20,F$2:F$257,0),"") -> 19 | H20: =IF(F20="No Data","No Data",IF(F20>=50,"High",IF(F20>=25,"Medium",IF(F20>=10,"Low","Very Low")))) -> High
A21: Turks and Caicos Islands | B21: =VLOOKUP(A21,'Wide Format'!A:B,2,0) -> TCA | C21: =IFERROR(AVERAGEIFS('Long Format'!F247:F18498,'Long Format'!A247:A18498,A21,'Long Format'!C247:C18498,"Access to electricity, rural (% of rural population)"),"No Data") -> 83.1875 | D21: =IFERROR(RANK(C21,C$2:C$257,0),"") -> 151 | E21: =IF(C21="No Data","No Data",IF(C21>=75,"High",IF(C21>=50,"Medium",IF(C21>=25,"Low","Very Low")))) -> High | F21: =IFERROR(AVERAGEIFS('Long Format'!F152:F18403,'Long Format'!A152:A18403,A21,'Long Format'!C152:C18403,"Trade in services (% of GDP)"),"No Data") -> 61.890459 | G21: =IFERROR(RANK(F21,F$2:F$257,0),"") -> 20 | H21: =IF(F21="No Data","No Data",IF(F21>=50,"High",IF(F21>=25,"Medium",IF(F21>=10,"Low","Very Low")))) -> High
A22: St. Lucia | B22: =VLOOKUP(A22,'Wide Format'!A:B,2,0) -> LCA | C22: =IFERROR(AVERAGEIFS('Long Format'!F226:F18477,'Long Format'!A226:A18477,A22,'Long Format'!C226:C18477,"Access to electricity, rural (% of rural population)"),"No Data") -> 93.125 | D22: =IFERROR(RANK(C22,C$2:C$257,0),"") -> 125 | E22: =IF(C22="No Data","No Data",IF(C22>=75,"High",IF(C22>=50,"Medium",IF(C22>=25,"Low","Very Low")))) -> High | F22: =IFERROR(AVERAGEIFS('Long Format'!F126:F18377,'Long Format'!A126:A18377,A22,'Long Format'!C126:C18377,"Trade in services (% of GDP)"),"No Data") -> 60.705632 | G22: =IFERROR(RANK(F22,F$2:F$257,0),"") -> 21 | H22: =IF(F22="No Data","No Data",IF(F22>=50,"High",IF(F22>=25,"Medium",IF(F22>=10,"Low","Very Low")))) -> High
A23: Grenada | B23: =VLOOKUP(A23,'Wide Format'!A:B,2,0) -> GRD | C23: =IFERROR(AVERAGEIFS('Long Format'!F95:F18346,'Long Format'!A95:A18346,A23,'Long Format'!C95:C18346,"Access to electricity, rural (% of rural population)"),"No Data") -> No Data | D23: =IFERROR(RANK(C23,C$2:C$257,0),"") | E23: =IF(C23="No Data","No Data",IF(C23>=75,"High",IF(C23>=50,"Medium",IF(C23>=25,"Low","Very Low")))) -> No Data | F23: =IFERROR(AVERAGEIFS('Long Format'!F257:F18508,'Long Format'!A257:A18508,A23,'Long Format'!C257:C18508,"Trade in services (% of GDP)"),"No Data") -> 59.026501 | G23: =IFERROR(RANK(F23,F$2:F$257,0),"") -> 22 | H23: =IF(F23="No Data","No Data",IF(F23>=50,"High",IF(F23>=25,"Medium",IF(F23>=10,"Low","Very Low")))) -> High
A24: Other small states | B24: =VLOOKUP(A24,'Wide Format'!A:B,2,0) -> OSS | C24: =IFERROR(AVERAGEIFS('Long Format'!F186:F18437,'Long Format'!A186:A18437,A24,'Long Format'!C186:C18437,"Access to electricity, rural (% of rural population)"),"No Data") -> 71.467218 | D24: =IFERROR(RANK(C24,C$2:C$257,0),"") -> 173 | E24: =IF(C24="No Data","No Data",IF(C24>=75,"High",IF(C24>=50,"Medium",IF(C24>=25,"Low","Very Low")))) -> Medium | F24: =IFERROR(AVERAGEIFS('Long Format'!F174:F18425,'Long Format'!A174:A18425,A24,'Long Format'!C174:C18425,"Trade in services (% of GDP)"),"No Data") -> 55.017908 | G24: =IFERROR(RANK(F24,F$2:F$257,0),"") -> 23 | H24: =IF(F24="No Data","No Data",IF(F24>=50,"High",IF(F24>=25,"Medium",IF(F24>=10,"Low","Very Low")))) -> High
A25: United Arab Emirates | B25: =VLOOKUP(A25,'Wide Format'!A:B,2,0) -> ARE | C25: =IFERROR(AVERAGEIFS('Long Format'!F251:F18502,'Long Format'!A251:A18502,A25,'Long Format'!C251:C18502,"Access to electricity, rural (% of rural population)"),"No Data") -> 100 | D25: =IFERROR(RANK(C25,C$2:C$257,0),"") -> 1 | E25: =IF(C25="No Data","No Data",IF(C25>=75,"High",IF(C25>=50,"Medium",IF(C25>=25,"Low","Very Low")))) -> High | F25: =IFERROR(AVERAGEIFS('Long Format'!F66:F18317,'Long Format'!A66:A18317,A25,'Long Format'!C66:C18317,"Trade in services (% of GDP)"),"No Data") -> 53.725812 | G25: =IFERROR(RANK(F25,F$2:F$257,0),"") -> 24 | H25: =IF(F25="No Data","No Data",IF(F25>=50,"High",IF(F25>=25,"Medium",IF(F25>=10,"Low","Very Low")))) -> High
A26: Dominica | B26: =VLOOKUP(A26,'Wide Format'!A:B,2,0) -> DMA | C26: =IFERROR(AVERAGEIFS('Long Format'!F62:F18313,'Long Format'!A62:A18313,A26,'Long Format'!C62:C18313,"Access to electricity, rural (% of rural population)"),"No Data") -> 100 | D26: =IFERROR(RANK(C26,C$2:C$257,0),"") -> 1 | E26: =IF(C26="No Data","No Data",IF(C26>=75,"High",IF(C26>=50,"Medium",IF(C26>=25,"Low","Very Low")))) -> High | F26: =IFERROR(AVERAGEIFS('Long Format'!F19:F18270,'Long Format'!A19:A18270,A26,'Long Format'!C19:C18270,"Trade in services (% of GDP)"),"No Data") -> 52.539618 | G26: =IFERROR(RANK(F26,F$2:F$257,0),"") -> 25 | H26: =IF(F26="No Data","No Data",IF(F26>=50,"High",IF(F26>=25,"Medium",IF(F26>=10,"Low","Very Low")))) -> High
A27: Vanuatu | B27: =VLOOKUP(A27,'Wide Format'!A:B,2,0) -> VUT | C27: =IFERROR(AVERAGEIFS('Long Format'!F257:F18508,'Long Format'!A257:A18508,A27,'Long Format'!C257:C18508,"Access to electricity, rural (% of rural population)"),"No Data") -> 31.75 | D27: =IFERROR(RANK(C27,C$2:C$257,0),"") -> 206 | E27: =IF(C27="No Data","No Data",IF(C27>=75,"High",IF(C27>=50,"Medium",IF(C27>=25,"Low","Very Low")))) -> Low | F27: =IFERROR(AVERAGEIFS('Long Format'!F207:F18458,'Long Format'!A207:A18458,A27,'Long Format'!C207:C18458,"Trade in services (% of GDP)"),"No Data") -> 52.208798 | G27: =IFERROR(RANK(F27,F$2:F$257,0),"") -> 26 | H27: =IF(F27="No Data","No Data",IF(F27>=50,"High",IF(F27>=25,"Medium",IF(F27>=10,"Low","Very Low")))) -> High
A28: Liberia | B28: =VLOOKUP(A28,'Wide Format'!A:B,2,0) -> LBR | C28: =IFERROR(AVERAGEIFS('Long Format'!F140:F18391,'Long Format'!A140:A18391,A28,'Long Format'!C140:C18391,"Access to electricity, rural (% of rural population)"),"No Data") -> 9.1142857 | D28: =IFERROR(RANK(C28,C$2:C$257,0),"") -> 240 | E28: =IF(C28="No Data","No Data",IF(C28>=75,"High",IF(C28>=50,"Medium",IF(C28>=25,"Low","Very Low")))) -> Very Low | F28: =IFERROR(AVERAGEIFS('Long Format'!F241:F18492,'Long Format'!A241:A18492,A28,'Long Format'!C241:C18492,"Trade in services (% of GDP)"),"No Data") -> 50.531563 | G28: =IFERROR(RANK(F28,F$2:F$257,0),"") -> 27 | H28: =IF(F28="No Data","No Data",IF(F28>=50,"High",IF(F28>=25,"Medium",IF(F28>=10,"Low","Very Low")))) -> High
A29: Palau | B29: =VLOOKUP(A29,'Wide Format'!A:B,2,0) -> PLW | C29: =IFERROR(AVERAGEIFS('Long Format'!F189:F18440,'Long Format'!A189:A18440,A29,'Long Format'!C189:C18440,"Access to electricity, rural (% of rural population)"),"No Data") -> 97.825 | D29: =IFERROR(RANK(C29,C$2:C$257,0),"") -> 109 | E29: =IF(C29="No Data","No Data",IF(C29>=75,"High",IF(C29>=50,"Medium",IF(C29>=25,"Low","Very Low")))) -> High | F29: =IFERROR(AVERAGEIFS('Long Format'!F110:F18361,'Long Format'!A110:A18361,A29,'Long Format'!C110:C18361,"Trade in services (% of GDP)"),"No Data") -> 50.112097 | G29: =IFERROR(RANK(F29,F$2:F$257,0),"") -> 28 | H29: =IF(F29="No Data","No Data",IF(F29>=50,"High",IF(F29>=25,"Medium",IF(F29>=10,"Low","Very Low")))) -> High
A30: Hong Kong SAR, China | B30: =VLOOKUP(A30,'Wide Format'!A:B,2,0) -> HKG | C30: =IFERROR(AVERAGEIFS('Long Format'!F105:F18356,'Long Format'!A105:A18356,A30,'Long Format'!C105:C18356,"Access to electricity, rural (% of rural population)"),"No Data") -> 100 | D30: =IFERROR(RANK(C30,C$2:C$257,0),"") -> 1 | E30: =IF(C30="No Data","No Data",IF(C30>=75,"High",IF(C30>=50,"Medium",IF(C30>=25,"Low","Very Low")))) -> High | F30: =IFERROR(AVERAGEIFS('Long Format'!F30:F18281,'Long Format'!A30:A18281,A30,'Long Format'!C30:C18281,"Trade in services (% of GDP)"),"No Data") -> 50.002677 | G30: =IFERROR(RANK(F30,F$2:F$257,0),"") -> 29 | H30: =IF(F30="No Data","No Data",IF(F30>=50,"High",IF(F30>=25,"Medium",IF(F30>=10,"Low","Very Low")))) -> High
A31: Small states | B31: =VLOOKUP(A31,'Wide Format'!A:B,2,0) -> SST | C31: =IFERROR(AVERAGEIFS('Long Format'!F216:F18467,'Long Format'!A216:A18467,A31,'Long Format'!C216:C18467,"Access to electricity, rural (% of rural population)"),"No Data") -> 74.43715 | D31: =IFERROR(RANK(C31,C$2:C$257,0),"") -> 166 | E31: =IF(C31="No Data","No Data",IF(C31>=75,"High",IF(C31>=50,"Medium",IF(C31>=25,"Low","Very Low")))) -> Medium | F31: =IFERROR(AVERAGEIFS('Long Format'!F167:F18418,'Long Format'!A167:A18418,A31,'Long Format'!C167:C18418,"Trade in services (% of GDP)"),"No Data") -> 47.741526 | G31: =IFERROR(RANK(F31,F$2:F$257,0),"") -> 30 | H31: =IF(F31="No Data","No Data",IF(F31>=50,"High",IF(F31>=25,"Medium",IF(F31>=10,"Low","Very Low")))) -> Medium
A32: Djibouti | B32: =VLOOKUP(A32,'Wide Format'!A:B,2,0) -> DJI | C32: =IFERROR(AVERAGEIFS('Long Format'!F61:F18312,'Long Format'!A61:A18312,A32,'Long Format'!C61:C18312,"Access to electricity, rural (% of rural population)"),"No Data") -> 40.753333 | D32: =IFERROR(RANK(C32,C$2:C$257,0),"") -> 201 | E32: =IF(C32="No Data","No Data",IF(C32>=75,"High",IF(C32>=50,"Medium",IF(C32>=25,"Low","Very Low")))) -> Low | F32: =IFERROR(AVERAGEIFS('Long Format'!F202:F18453,'Long Format'!A202:A18453,A32,'Long Format'!C202:C18453,"Trade in services (% of GDP)"),"No Data") -> 47.542629 | G32: =IFERROR(RANK(F32,F$2:F$257,0),"") -> 31 | H32: =IF(F32="No Data","No Data",IF(F32>=50,"High",IF(F32>=25,"Medium",IF(F32>=10,"Low","Very Low")))) -> Medium
A33: Barbados | B33: =VLOOKUP(A33,'Wide Format'!A:B,2,0) -> BRB | C33: =IFERROR(AVERAGEIFS('Long Format'!F21:F18272,'Long Format'!A21:A18272,A33,'Long Format'!C21:C18272,"Access to electricity, rural (% of rural population)"),"No Data") -> 99.99375 | D33: =IFERROR(RANK(C33,C$2:C$257,0),"") -> 70 | E33: =IF(C33="No Data","No Data",IF(C33>=75,"High",IF(C33>=50,"Medium",IF(C33>=25,"Low","Very Low")))) -> High | F33: =IFERROR(AVERAGEIFS('Long Format'!F71:F18322,'Long Format'!A71:A18322,A33,'Long Format'!C71:C18322,"Trade in services (% of GDP)"),"No Data") -> 45.091822 | G33: =IFERROR(RANK(F33,F$2:F$257,0),"") -> 32 | H33: =IF(F33="No Data","No Data",IF(F33>=50,"High",IF(F33>=25,"Medium",IF(F33>=10,"Low","Very Low")))) -> Medium
A34: Montenegro | B34: =VLOOKUP(A34,'Wide Format'!A:B,2,0) -> MNE | C34: =IFERROR(AVERAGEIFS('Long Format'!F167:F18418,'Long Format'!A167:A18418,A34,'Long Format'!C167:C18418,"Access to electricity, rural (% of rural population)"),"No Data") -> 98.9625 | D34: =IFERROR(RANK(C34,C$2:C$257,0),"") -> 97 | E34: =IF(C34="No Data","No Data",IF(C34>=75,"High",IF(C34>=50,"Medium",IF(C34>=25,"Low","Very Low")))) -> High | F34: =IFERROR(AVERAGEIFS('Long Format'!F98:F18349,'Long Format'!A98:A18349,A34,'Long Format'!C98:C18349,"Trade in services (% of GDP)"),"No Data") -> 44.95942 | G34: =IFERROR(RANK(F34,F$2:F$257,0),"") -> 33 | H34: =IF(F34="No Data","No Data",IF(F34>=50,"High",IF(F34>=25,"Medium",IF(F34>=10,"Low","Very Low")))) -> Medium
A35: South Sudan | B35: =VLOOKUP(A35,'Wide Format'!A:B,2,0) -> SSD | C35: =IFERROR(AVERAGEIFS('Long Format'!F222:F18473,'Long Format'!A222:A18473,A35,'Long Format'!C222:C18473,"Access to electricity, rural (% of rural population)"),"No Data") -> 4.4857143 | D35: =IFERROR(RANK(C35,C$2:C$257,0),"") -> 245 | E35: =IF(C35="No Data","No Data",IF(C35>=75,"High",IF(C35>=50,"Medium",IF(C35>=25,"Low","Very Low")))) -> Very Low | F35: =IFERROR(AVERAGEIFS('Long Format'!F246:F18497,'Long Format'!A246:A18497,A35,'Long Format'!C246:C18497,"Trade in services (% of GDP)"),"No Data") -> 44.673554 | G35: =IFERROR(RANK(F35,F$2:F$257,0),"") -> 34 | H35: =IF(F35="No Data","No Data",IF(F35>=50,"High",IF(F35>=25,"Medium",IF(F35>=10,"Low","Very Low")))) -> Medium
A36: Cabo Verde | B36: =VLOOKUP(A36,'Wide Format'!A:B,2,0) -> CPV | C36: =IFERROR(AVERAGEIFS('Long Format'!F37:F18288,'Long Format'!A37:A18288,A36,'Long Format'!C37:C18288,"Access to electricity, rural (% of rural population)"),"No Data") -> 62.39375 | D36: =IFERROR(RANK(C36,C$2:C$257,0),"") -> 180 | E36: =IF(C36="No Data","No Data",IF(C36>=75,"High",IF(C36>=50,"Medium",IF(C36>=25,"Low","Very Low")))) -> Medium | F36: =IFERROR(AVERAGEIFS('Long Format'!F181:F18432,'Long Format'!A181:A18432,A36,'Long Format'!C181:C18432,"Trade in services (% of GDP)"),"No Data") -> 44.245148 | G36: =IFERROR(RANK(F36,F$2:F$257,0),"") -> 35 | H36: =IF(F36="No Data","No Data",IF(F36>=50,"High",IF(F36>=25,"Medium",IF(F36>=10,"Low","Very Low")))) -> Medium
A37: Estonia | B37: =VLOOKUP(A37,'Wide Format'!A:B,2,0) -> EST | C37: =IFERROR(AVERAGEIFS('Long Format'!F73:F18324,'Long Format'!A73:A18324,A37,'Long Format'!C73:C18324,"Access to electricity, rural (% of rural population)"),"No Data") -> 100 | D37: =IFERROR(RANK(C37,C$2:C$257,0),"") -> 1 | E37: =IF(C37="No Data","No Data",IF(C37>=75,"High",IF(C37>=50,"Medium",IF(C37>=25,"Low","Very Low")))) -> High | F37: =IFERROR(AVERAGEIFS('Long Format'!F20:F18271,'Long Format'!A20:A18271,A37,'Long Format'!C20:C18271,"Trade in services (% of GDP)"),"No Data") -> 43.78372 | G37: =IFERROR(RANK(F37,F$2:F$257,0),"") -> 36 | H37: =IF(F37="No Data","No Data",IF(F37>=50,"High",IF(F37>=25,"Medium",IF(F37>=10,"Low","Very Low")))) -> Medium
A38: St. Vincent and the Grenadines | B38: =VLOOKUP(A38,'Wide Format'!A:B,2,0) -> VCT | C38: =IFERROR(AVERAGEIFS('Long Format'!F228:F18479,'Long Format'!A228:A18479,A38,'Long Format'!C228:C18479,"Access to electricity, rural (% of rural population)"),"No Data") -> 89.76875 | D38: =IFERROR(RANK(C38,C$2:C$257,0),"") -> 140 | E38: =IF(C38="No Data","No Data",IF(C38>=75,"High",IF(C38>=50,"Medium",IF(C38>=25,"Low","Very Low")))) -> High | F38: =IFERROR(AVERAGEIFS('Long Format'!F141:F18392,'Long Format'!A141:A18392,A38,'Long Format'!C141:C18392,"Trade in services (% of GDP)"),"No Data") -> 43.586585 | G38: =IFERROR(RANK(F38,F$2:F$257,0),"") -> 37 | H38: =IF(F38="No Data","No Data",IF(F38>=50,"High",IF(F38>=25,"Medium",IF(F38>=10,"Low","Very Low")))) -> Medium
A39: Fiji | B39: =VLOOKUP(A39,'Wide Format'!A:B,2,0) -> FJI | C39: =IFERROR(AVERAGEIFS('Long Format'!F82:F18333,'Long Format'!A82:A18333,A39,'Long Format'!C82:C18333,"Access to electricity, rural (% of rural population)"),"No Data") -> 80.09375 | D39: =IFERROR(RANK(C39,C$2:C$257,0),"") -> 157 | E39: =IF(C39="No Data","No Data",IF(C39>=75,"High",IF(C39>=50,"Medium",IF(C39>=25,"Low","Very Low")))) -> High | F39: =IFERROR(AVERAGEIFS('Long Format'!F158:F18409,'Long Format'!A158:A18409,A39,'Long Format'!C158:C18409,"Trade in services (% of GDP)"),"No Data") -> 43.502131 | G39: =IFERROR(RANK(F39,F$2:F$257,0),"") -> 38 | H39: =IF(F39="No Data","No Data",IF(F39>=50,"High",IF(F39>=25,"Medium",IF(F39>=10,"Low","Very Low")))) -> Medium
A40: Denmark | B40: =VLOOKUP(A40,'Wide Format'!A:B,2,0) -> DNK | C40: =IFERROR(AVERAGEIFS('Long Format'!F60:F18311,'Long Format'!A60:A18311,A40,'Long Format'!C60:C18311,"Access to electricity, rural (% of rural population)"),"No Data") -> 100 | D40: =IFERROR(RANK(C40,C$2:C$257,0),"") -> 1 | E40: =IF(C40="No Data","No Data",IF(C40>=75,"High",IF(C40>=50,"Medium",IF(C40>=25,"Low","Very Low")))) -> High | F40: =IFERROR(AVERAGEIFS('Long Format'!F18:F18269,'Long Format'!A18:A18269,A40,'Long Format'!C18:C18269,"Trade in services (% of GDP)"),"No Data") -> 40.259702 | G40: =IFERROR(RANK(F40,F$2:F$257,0),"") -> 39 | H40: =IF(F40="No Data","No Data",IF(F40>=50,"High",IF(F40>=25,"Medium",IF(F40>=10,"Low","Very Low")))) -> Medium
A41: Mauritius | B41: =VLOOKUP(A41,'Wide Format'!A:B,2,0) -> MUS | C41: =IFERROR(AVERAGEIFS('Long Format'!F157:F18408,'Long Format'!A157:A18408,A41,'Long Format'!C157:C18408,"Access to electricity, rural (% of rural population)"),"No Data") -> 99.15625 | D41: =IFERROR(RANK(C41,C$2:C$257,0),"") -> 95 | E41: =IF(C41="No Data","No Data",IF(C41>=75,"High",IF(C41>=50,"Medium",IF(C41>=25,"Low","Very Low")))) -> High | F41: =IFERROR(AVERAGEIFS('Long Format'!F96:F18347,'Long Format'!A96:A18347,A41,'Long Format'!C96:C18347,"Trade in services (% of GDP)"),"No Data") -> 40.247599 | G41: =IFERROR(RANK(F41,F$2:F$257,0),"") -> 40 | H41: =IF(F41="No Data","No Data",IF(F41>=50,"High",IF(F41>=25,"Medium",IF(F41>=10,"Low","Very Low")))) -> Medium
A42: Pacific island small states | B42: =VLOOKUP(A42,'Wide Format'!A:B,2,0) -> PSS | C42: =IFERROR(AVERAGEIFS('Long Format'!F187:F18438,'Long Format'!A187:A18438,A42,'Long Format'!C187:C18438,"Access to electricity, rural (% of rural population)"),"No Data") -> 63.561278 | D42: =IFERROR(RANK(C42,C$2:C$257,0),"") -> 178 | E42: =IF(C42="No Data","No Data",IF(C42>=75,"High",IF(C42>=50,"Medium",IF(C42>=25,"Low","Very Low")))) -> Medium | F42: =IFERROR(AVERAGEIFS('Long Format'!F179:F18430,'Long Format'!A179:A18430,A42,'Long Format'!C179:C18430,"Trade in services (% of GDP)"),"No Data") -> 40.199785 | G42: =IFERROR(RANK(F42,F$2:F$257,0),"") -> 41 | H42: =IF(F42="No Data","No Data",IF(F42>=50,"High",IF(F42>=25,"Medium",IF(F42>=10,"Low","Very Low")))) -> Medium
A43: Bahamas, The | B43: =VLOOKUP(A43,'Wide Format'!A:B,2,0) -> BHS | C43: =IFERROR(AVERAGEIFS('Long Format'!F18:F18269,'Long Format'!A18:A18269,A43,'Long Format'!C18:C18269,"Access to electricity, rural (% of rural population)"),"No Data") -> 100 | D43: =IFERROR(RANK(C43,C$2:C$257,0),"") -> 1 | E43: =IF(C43="No Data","No Data",IF(C43>=75,"High",IF(C43>=50,"Medium",IF(C43>=25,"Low","Very Low")))) -> High | F43: =IFERROR(AVERAGEIFS('Long Format'!F6:F18257,'Long Format'!A6:A18257,A43,'Long Format'!C6:C18257,"Trade in services (% of GDP)"),"No Data") -> 39.88746 | G43: =IFERROR(RANK(F43,F$2:F$257,0),"") -> 42 | H43: =IF(F43="No Data","No Data",IF(F43>=50,"High",IF(F43>=25,"Medium",IF(F43>=10,"Low","Very Low")))) -> Medium
A44: Timor-Leste | B44: =VLOOKUP(A44,'Wide Format'!A:B,2,0) -> TLS | C44: =IFERROR(AVERAGEIFS('Long Format'!F240:F18491,'Long Format'!A240:A18491,A44,'Long Format'!C240:C18491,"Access to electricity, rural (% of rural population)"),"No Data") -> 47.7875 | D44: =IFERROR(RANK(C44,C$2:C$257,0),"") -> 195 | E44: =IF(C44="No Data","No Data",IF(C44>=75,"High",IF(C44>=50,"Medium",IF(C44>=25,"Low","Very Low")))) -> Low | F44: =IFERROR(AVERAGEIFS('Long Format'!F196:F18447,'Long Format'!A196:A18447,A44,'Long Format'!C196:C18447,"Trade in services (% of GDP)"),"No Data") -> 39.577008 | G44: =IFERROR(RANK(F44,F$2:F$257,0),"") -> 43 | H44: =IF(F44="No Data","No Data",IF(F44>=50,"High",IF(F44>=25,"Medium",IF(F44>=10,"Low","Very Low")))) -> Medium
A45: Bahrain | B45: =VLOOKUP(A45,'Wide Format'!A:B,2,0) -> BHR | C45: =IFERROR(AVERAGEIFS('Long Format'!F19:F18270,'Long Format'!A19:A18270,A45,'Long Format'!C19:C18270,"Access to electricity, rural (% of rural population)"),"No Data") -> 100 | D45: =IFERROR(RANK(C45,C$2:C$257,0),"") -> 1 | E45: =IF(C45="No Data","No Data",IF(C45>=75,"High",IF(C45>=50,"Medium",IF(C45>=25,"Low","Very Low")))) -> High | F45: =IFERROR(AVERAGEIFS('Long Format'!F7:F18258,'Long Format'!A7:A18258,A45,'Long Format'!C7:C18258,"Trade in services (% of GDP)"),"No Data") -> 38.966252 | G45: =IFERROR(RANK(F45,F$2:F$257,0),"") -> 44 | H45: =IF(F45="No Data","No Data",IF(F45>=50,"High",IF(F45>=25,"Medium",IF(F45>=10,"Low","Very Low")))) -> Medium
A46: Belgium | B46: =VLOOKUP(A46,'Wide Format'!A:B,2,0) -> BEL | C46: =IFERROR(AVERAGEIFS('Long Format'!F23:F18274,'Long Format'!A23:A18274,A46,'Long Format'!C23:C18274,"Access to electricity, rural (% of rural population)"),"No Data") -> 100 | D46: =IFERROR(RANK(C46,C$2:C$257,0),"") -> 1 | E46: =IF(C46="No Data","No Data",IF(C46>=75,"High",IF(C46>=50,"Medium",IF(C46>=25,"Low","Very Low")))) -> High | F46: =IFERROR(AVERAGEIFS('Long Format'!F8:F18259,'Long Format'!A8:A18259,A46,'Long Format'!C8:C18259,"Trade in services (% of GDP)"),"No Data") -> 38.733644 | G46: =IFERROR(RANK(F46,F$2:F$257,0),"") -> 45 | H46: =IF(F46="No Data","No Data",IF(F46>=50,"High",IF(F46>=25,"Medium",IF(F46>=10,"Low","Very Low")))) -> Medium
A47: Jamaica | B47: =VLOOKUP(A47,'Wide Format'!A:B,2,0) -> JAM | C47: =IFERROR(AVERAGEIFS('Long Format'!F121:F18372,'Long Format'!A121:A18372,A47,'Long Format'!C121:C18372,"Access to electricity, rural (% of rural population)"),"No Data") -> 88.53125 | D47: =IFERROR(RANK(C47,C$2:C$257,0),"") -> 142 | E47: =IF(C47="No Data","No Data",IF(C47>=75,"High",IF(C47>=50,"Medium",IF(C47>=25,"Low","Very Low")))) -> High | F47: =IFERROR(AVERAGEIFS('Long Format'!F143:F18394,'Long Format'!A143:A18394,A47,'Long Format'!C143:C18394,"Trade in services (% of GDP)"),"No Data") -> 37.740904 | G47: =IFERROR(RANK(F47,F$2:F$257,0),"") -> 46 | H47: =IF(F47="No Data","No Data",IF(F47>=50,"High",IF(F47>=25,"Medium",IF(F47>=10,"Low","Very Low")))) -> Medium
A48: Netherlands | B48: =VLOOKUP(A48,'Wide Format'!A:B,2,0) -> NLD | C48: =IFERROR(AVERAGEIFS('Long Format'!F174:F18425,'Long Format'!A174:A18425,A48,'Long Format'!C174:C18425,"Access to electricity, rural (% of rural population)"),"No Data") -> 100 | D48: =IFERROR(RANK(C48,C$2:C$257,0),"") -> 1 | E48: =IF(C48="No Data","No Data",IF(C48>=75,"High",IF(C48>=50,"Medium",IF(C48>=25,"Low","Very Low")))) -> High | F48: =IFERROR(AVERAGEIFS('Long Format'!F46:F18297,'Long Format'!A46:A18297,A48,'Long Format'!C46:C18297,"Trade in services (% of GDP)"),"No Data") -> 36.134212 | G48: =IFERROR(RANK(F48,F$2:F$257,0),"") -> 47 | H48: =IF(F48="No Data","No Data",IF(F48>=50,"High",IF(F48>=25,"Medium",IF(F48>=10,"Low","Very Low")))) -> Medium
A49: Kiribati | B49: =VLOOKUP(A49,'Wide Format'!A:B,2,0) -> KIR | C49: =IFERROR(AVERAGEIFS('Long Format'!F126:F18377,'Long Format'!A126:A18377,A49,'Long Format'!C126:C18377,"Access to electricity, rural (% of rural population)"),"No Data") -> 50.190909 | D49: =IFERROR(RANK(C49,C$2:C$257,0),"") -> 194 | E49: =IF(C49="No Data","No Data",IF(C49>=75,"High",IF(C49>=50,"Medium",IF(C49>=25,"Low","Very Low")))) -> Medium | F49: =IFERROR(AVERAGEIFS('Long Format'!F195:F18446,'Long Format'!A195:A18446,A49,'Long Format'!C195:C18446,"Trade in services (% of GDP)"),"No Data") -> 35.883133 | G49: =IFERROR(RANK(F49,F$2:F$257,0),"") -> 48 | H49: =IF(F49="No Data","No Data",IF(F49>=50,"High",IF(F49>=25,"Medium",IF(F49>=10,"Low","Very Low")))) -> Medium
A50: Samoa | B50: =VLOOKUP(A50,'Wide Format'!A:B,2,0) -> WSM | C50: =IFERROR(AVERAGEIFS('Long Format'!F204:F18455,'Long Format'!A204:A18455,A50,'Long Format'!C204:C18455,"Access to electricity, rural (% of rural population)"),"No Data") -> 93.66875 | D50: =IFERROR(RANK(C50,C$2:C$257,0),"") -> 122 | E50: =IF(C50="No Data","No Data",IF(C50>=75,"High",IF(C50>=50,"Medium",IF(C50>=25,"Low","Very Low")))) -> High | F50: =IFERROR(AVERAGEIFS('Long Format'!F123:F18374,'Long Format'!A123:A18374,A50,'Long Format'!C123:C18374,"Trade in services (% of GDP)"),"No Data") -> 35.498679 | G50: =IFERROR(RANK(F50,F$2:F$257,0),"") -> 49 | H50: =IF(F50="No Data","No Data",IF(F50>=50,"High",IF(F50>=25,"Medium",IF(F50>=10,"Low","Very Low")))) -> Medium
A51: Marshall Islands | B51: =VLOOKUP(A51,'Wide Format'!A:B,2,0) -> MHL | C51: =IFERROR(AVERAGEIFS('Long Format'!F155:F18406,'Long Format'!A155:A18406,A51,'Long Format'!C155:C18406,"Access to electricity, rural (% of rural population)"),"No Data") -> 61.75625 | D51: =IFERROR(RANK(C51,C$2:C$257,0),"") -> 182 | E51: =IF(C51="No Data","No Data",IF(C51>=75,"High",IF(C51>=50,"Medium",IF(C51>=25,"Low","Very Low")))) -> Medium | F51: =IFERROR(AVERAGEIFS('Long Format'!F183:F18434,'Long Format'!A183:A18434,A51,'Long Format'!C183:C18434,"Trade in services (% of GDP)"),"No Data") -> 35.309259 | G51: =IFERROR(RANK(F51,F$2:F$257,0),"") -> 50 | H51: =IF(F51="No Data","No Data",IF(F51>=50,"High",IF(F51>=25,"Medium",IF(F51>=10,"Low","Very Low")))) -> Medium
A52: Guyana | B52: =VLOOKUP(A52,'Wide Format'!A:B,2,0) -> GUY | C52: =IFERROR(AVERAGEIFS('Long Format'!F100:F18351,'Long Format'!A100:A18351,A52,'Long Format'!C100:C18351,"Access to electricity, rural (% of rural population)"),"No Data") -> 80.1875 | D52: =IFERROR(RANK(C52,C$2:C$257,0),"") -> 156 | E52: =IF(C52="No Data","No Data",IF(C52>=75,"High",IF(C52>=50,"Medium",IF(C52>=25,"Low","Very Low")))) -> High | F52: =IFERROR(AVERAGEIFS('Long Format'!F157:F18408,'Long Format'!A157:A18408,A52,'Long Format'!C157:C18408,"Trade in services (% of GDP)"),"No Data") -> 34.816026 | G52: =IFERROR(RANK(F52,F$2:F$257,0),"") -> 51 | H52: =IF(F52="No Data","No Data",IF(F52>=50,"High",IF(F52>=25,"Medium",IF(F52>=10,"Low","Very Low")))) -> Medium
A53: Switzerland | B53: =VLOOKUP(A53,'Wide Format'!A:B,2,0) -> CHE | C53: =IFERROR(AVERAGEIFS('Long Format'!F235:F18486,'Long Format'!A235:A18486,A53,'Long Format'!C235:C18486,"Access to electricity, rural (% of rural population)"),"No Data") -> 100 | D53: =IFERROR(RANK(C53,C$2:C$257,0),"") -> 1 | E53: =IF(C53="No Data","No Data",IF(C53>=75,"High",IF(C53>=50,"Medium",IF(C53>=25,"Low","Very Low")))) -> High | F53: =IFERROR(AVERAGEIFS('Long Format'!F65:F18316,'Long Format'!A65:A18316,A53,'Long Format'!C65:C18316,"Trade in services (% of GDP)"),"No Data") -> 34.400999 | G53: =IFERROR(RANK(F53,F$2:F$257,0),"") -> 52 | H53: =IF(F53="No Data","No Data",IF(F53>=50,"High",IF(F53>=25,"Medium",IF(F53>=10,"Low","Very Low")))) -> Medium
A54: Albania | B54: =VLOOKUP(A54,'Wide Format'!A:B,2,0) -> ALB | C54: =IFERROR(AVERAGEIFS('Long Format'!F5:F18256,'Long Format'!A5:A18256,A54,'Long Format'!C5:C18256,"Access to electricity, rural (% of rural population)"),"No Data") -> 99.98125 | D54: =IFERROR(RANK(C54,C$2:C$257,0),"") -> 74 | E54: =IF(C54="No Data","No Data",IF(C54>=75,"High",IF(C54>=50,"Medium",IF(C54>=25,"Low","Very Low")))) -> High | F54: =IFERROR(AVERAGEIFS('Long Format'!F75:F18326,'Long Format'!A75:A18326,A54,'Long Format'!C75:C18326,"Trade in services (% of GDP)"),"No Data") -> 34.059989 | G54: =IFERROR(RANK(F54,F$2:F$257,0),"") -> 53 | H54: =IF(F54="No Data","No Data",IF(F54>=50,"High",IF(F54>=25,"Medium",IF(F54>=10,"Low","Very Low")))) -> Medium
A55: Belize | B55: =VLOOKUP(A55,'Wide Format'!A:B,2,0) -> BLZ | C55: =IFERROR(AVERAGEIFS('Long Format'!F24:F18275,'Long Format'!A24:A18275,A55,'Long Format'!C24:C18275,"Access to electricity, rural (% of rural population)"),"No Data") -> 81.88125 | D55: =IFERROR(RANK(C55,C$2:C$257,0),"") -> 155 | E55: =IF(C55="No Data","No Data",IF(C55>=75,"High",IF(C55>=50,"Medium",IF(C55>=25,"Low","Very Low")))) -> High | F55: =IFERROR(AVERAGEIFS('Long Format'!F156:F18407,'Long Format'!A156:A18407,A55,'Long Format'!C156:C18407,"Trade in services (% of GDP)"),"No Data") -> 33.647598 | G55: =IFERROR(RANK(F55,F$2:F$257,0),"") -> 54 | H55: =IF(F55="No Data","No Data",IF(F55>=50,"High",IF(F55>=25,"Medium",IF(F55>=10,"Low","Very Low")))) -> Medium
A56: Bermuda | B56: =VLOOKUP(A56,'Wide Format'!A:B,2,0) -> BMU | C56: =IFERROR(AVERAGEIFS('Long Format'!F26:F18277,'Long Format'!A26:A18277,A56,'Long Format'!C26:C18277,"Access to electricity, rural (% of rural population)"),"No Data") -> 100 | D56: =IFERROR(RANK(C56,C$2:C$257,0),"") -> 1 | E56: =IF(C56="No Data","No Data",IF(C56>=75,"High",IF(C56>=50,"Medium",IF(C56>=25,"Low","Very Low")))) -> High | F56: =IFERROR(AVERAGEIFS('Long Format'!F9:F18260,'Long Format'!A9:A18260,A56,'Long Format'!C9:C18260,"Trade in services (% of GDP)"),"No Data") -> 33.627792 | G56: =IFERROR(RANK(F56,F$2:F$257,0),"") -> 55 | H56: =IF(F56="No Data","No Data",IF(F56>=50,"High",IF(F56>=25,"Medium",IF(F56>=10,"Low","Very Low")))) -> Medium
A57: Jordan | B57: =VLOOKUP(A57,'Wide Format'!A:B,2,0) -> JOR | C57: =IFERROR(AVERAGEIFS('Long Format'!F123:F18374,'Long Format'!A123:A18374,A57,'Long Format'!C123:C18374,"Access to electricity, rural (% of rural population)"),"No Data") -> 98.5375 | D57: =IFERROR(RANK(C57,C$2:C$257,0),"") -> 103 | E57: =IF(C57="No Data","No Data",IF(C57>=75,"High",IF(C57>=50,"Medium",IF(C57>=25,"Low","Very Low")))) -> High | F57: =IFERROR(AVERAGEIFS('Long Format'!F104:F18355,'Long Format'!A104:A18355,A57,'Long Format'!C104:C18355,"Trade in services (% of GDP)"),"No Data") -> 32.470485 | G57: =IFERROR(RANK(F57,F$2:F$257,0),"") -> 56 | H57: =IF(F57="No Data","No Data",IF(F57>=50,"High",IF(F57>=25,"Medium",IF(F57>=10,"Low","Very Low")))) -> Medium
A58: Croatia | B58: =VLOOKUP(A58,'Wide Format'!A:B,2,0) -> HRV | C58: =IFERROR(AVERAGEIFS('Long Format'!F55:F18306,'Long Format'!A55:A18306,A58,'Long Format'!C55:C18306,"Access to electricity, rural (% of rural population)"),"No Data") -> 100 | D58: =IFERROR(RANK(C58,C$2:C$257,0),"") -> 1 | E58: =IF(C58="No Data","No Data",IF(C58>=75,"High",IF(C58>=50,"Medium",IF(C58>=25,"Low","Very Low")))) -> High | F58: =IFERROR(AVERAGEIFS('Long Format'!F14:F18265,'Long Format'!A14:A18265,A58,'Long Format'!C14:C18265,"Trade in services (% of GDP)"),"No Data") -> 31.715938 | G58: =IFERROR(RANK(F58,F$2:F$257,0),"") -> 57 | H58: =IF(F58="No Data","No Data",IF(F58>=50,"High",IF(F58>=25,"Medium",IF(F58>=10,"Low","Very Low")))) -> Medium
A59: Qatar | B59: =VLOOKUP(A59,'Wide Format'!A:B,2,0) -> QAT | C59: =IFERROR(AVERAGEIFS('Long Format'!F200:F18451,'Long Format'!A200:A18451,A59,'Long Format'!C200:C18451,"Access to electricity, rural (% of rural population)"),"No Data") -> 100 | D59: =IFERROR(RANK(C59,C$2:C$257,0),"") -> 1 | E59: =IF(C59="No Data","No Data",IF(C59>=75,"High",IF(C59>=50,"Medium",IF(C59>=25,"Low","Very Low")))) -> High | F59: =IFERROR(AVERAGEIFS('Long Format'!F55:F18306,'Long Format'!A55:A18306,A59,'Long Format'!C55:C18306,"Trade in services (% of GDP)"),"No Data") -> 31.368648 | G59: =IFERROR(RANK(F59,F$2:F$257,0),"") -> 58 | H59: =IF(F59="No Data","No Data",IF(F59>=50,"High",IF(F59>=25,"Medium",IF(F59>=10,"Low","Very Low")))) -> Medium
A60: Tonga | B60: =VLOOKUP(A60,'Wide Format'!A:B,2,0) -> TON | C60: =IFERROR(AVERAGEIFS('Long Format'!F242:F18493,'Long Format'!A242:A18493,A60,'Long Format'!C242:C18493,"Access to electricity, rural (% of rural population)"),"No Data") -> 91.85625 | D60: =IFERROR(RANK(C60,C$2:C$257,0),"") -> 133 | E60: =IF(C60="No Data","No Data",IF(C60>=75,"High",IF(C60>=50,"Medium",IF(C60>=25,"Low","Very Low")))) -> High | F60: =IFERROR(AVERAGEIFS('Long Format'!F134:F18385,'Long Format'!A134:A18385,A60,'Long Format'!C134:C18385,"Trade in services (% of GDP)"),"No Data") -> 30.114051 | G60: =IFERROR(RANK(F60,F$2:F$257,0),"") -> 59 | H60: =IF(F60="No Data","No Data",IF(F60>=50,"High",IF(F60>=25,"Medium",IF(F60>=10,"Low","Very Low")))) -> Medium
A61: Iceland | B61: =VLOOKUP(A61,'Wide Format'!A:B,2,0) -> ISL | C61: =IFERROR(AVERAGEIFS('Long Format'!F108:F18359,'Long Format'!A108:A18359,A61,'Long Format'!C108:C18359,"Access to electricity, rural (% of rural population)"),"No Data") -> 100 | D61: =IFERROR(RANK(C61,C$2:C$257,0),"") -> 1 | E61: =IF(C61="No Data","No Data",IF(C61>=75,"High",IF(C61>=50,"Medium",IF(C61>=25,"Low","Very Low")))) -> High | F61: =IFERROR(AVERAGEIFS('Long Format'!F32:F18283,'Long Format'!A32:A18283,A61,'Long Format'!C32:C18283,"Trade in services (% of GDP)"),"No Data") -> 30.081914 | G61: =IFERROR(RANK(F61,F$2:F$257,0),"") -> 60 | H61: =IF(F61="No Data","No Data",IF(F61>=50,"High",IF(F61>=25,"Medium",IF(F61>=10,"Low","Very Low")))) -> Medium
A62: Caribbean small states | B62: =VLOOKUP(A62,'Wide Format'!A:B,2,0) -> CSS | C62: =IFERROR(AVERAGEIFS('Long Format'!F41:F18292,'Long Format'!A41:A18292,A62,'Long Format'!C41:C18292,"Access to electricity, rural (% of rural population)"),"No Data") -> 90.032117 | D62: =IFERROR(RANK(C62,C$2:C$257,0),"") -> 138 | E62: =IF(C62="No Data","No Data",IF(C62>=75,"High",IF(C62>=50,"Medium",IF(C62>=25,"Low","Very Low")))) -> High | F62: =IFERROR(AVERAGEIFS('Long Format'!F139:F18390,'Long Format'!A139:A18390,A62,'Long Format'!C139:C18390,"Trade in services (% of GDP)"),"No Data") -> 29.648885 | G62: =IFERROR(RANK(F62,F$2:F$257,0),"") -> 61 | H62: =IF(F62="No Data","No Data",IF(F62>=50,"High",IF(F62>=25,"Medium",IF(F62>=10,"Low","Very Low")))) -> Medium
A63: French Polynesia | B63: =VLOOKUP(A63,'Wide Format'!A:B,2,0) -> PYF | C63: =IFERROR(AVERAGEIFS('Long Format'!F86:F18337,'Long Format'!A86:A18337,A63,'Long Format'!C86:C18337,"Access to electricity, rural (% of rural population)"),"No Data") -> 100 | D63: =IFERROR(RANK(C63,C$2:C$257,0),"") -> 1 | E63: =IF(C63="No Data","No Data",IF(C63>=75,"High",IF(C63>=50,"Medium",IF(C63>=25,"Low","Very Low")))) -> High | F63: =IFERROR(AVERAGEIFS('Long Format'!F24:F18275,'Long Format'!A24:A18275,A63,'Long Format'!C24:C18275,"Trade in services (% of GDP)"),"No Data") -> 29.614772 | G63: =IFERROR(RANK(F63,F$2:F$257,0),"") -> 62 | H63: =IF(F63="No Data","No Data",IF(F63>=50,"High",IF(F63>=25,"Medium",IF(F63>=10,"Low","Very Low")))) -> Medium
A64: Austria | B64: =VLOOKUP(A64,'Wide Format'!A:B,2,0) -> AUT | C64: =IFERROR(AVERAGEIFS('Long Format'!F16:F18267,'Long Format'!A16:A18267,A64,'Long Format'!C16:C18267,"Access to electricity, rural (% of rural population)"),"No Data") -> 100 | D64: =IFERROR(RANK(C64,C$2:C$257,0),"") -> 1 | E64: =IF(C64="No Data","No Data",IF(C64>=75,"High",IF(C64>=50,"Medium",IF(C64>=25,"Low","Very Low")))) -> High | F64: =IFERROR(AVERAGEIFS('Long Format'!F5:F18256,'Long Format'!A5:A18256,A64,'Long Format'!C5:C18256,"Trade in services (% of GDP)"),"No Data") -> 29.316752 | G64: =IFERROR(RANK(F64,F$2:F$257,0),"") -> 63 | H64: =IF(F64="No Data","No Data",IF(F64>=50,"High",IF(F64>=25,"Medium",IF(F64>=10,"Low","Very Low")))) -> Medium
A65: Lithuania | B65: =VLOOKUP(A65,'Wide Format'!A:B,2,0) -> LTU | C65: =IFERROR(AVERAGEIFS('Long Format'!F143:F18394,'Long Format'!A143:A18394,A65,'Long Format'!C143:C18394,"Access to electricity, rural (% of rural population)"),"No Data") -> 99.95 | D65: =IFERROR(RANK(C65,C$2:C$257,0),"") -> 75 | E65: =IF(C65="No Data","No Data",IF(C65>=75,"High",IF(C65>=50,"Medium",IF(C65>=25,"Low","Very Low")))) -> High | F65: =IFERROR(AVERAGEIFS('Long Format'!F76:F18327,'Long Format'!A76:A18327,A65,'Long Format'!C76:C18327,"Trade in services (% of GDP)"),"No Data") -> 28.223324 | G65: =IFERROR(RANK(F65,F$2:F$257,0),"") -> 64 | H65: =IF(F65="No Data","No Data",IF(F65>=50,"High",IF(F65>=25,"Medium",IF(F65>=10,"Low","Very Low")))) -> Medium
A66: Panama | B66: =VLOOKUP(A66,'Wide Format'!A:B,2,0) -> PAN | C66: =IFERROR(AVERAGEIFS('Long Format'!F190:F18441,'Long Format'!A190:A18441,A66,'Long Format'!C190:C18441,"Access to electricity, rural (% of rural population)"),"No Data") -> 71.207692 | D66: =IFERROR(RANK(C66,C$2:C$257,0),"") -> 174 | E66: =IF(C66="No Data","No Data",IF(C66>=75,"High",IF(C66>=50,"Medium",IF(C66>=25,"Low","Very Low")))) -> Medium | F66: =IFERROR(AVERAGEIFS('Long Format'!F175:F18426,'Long Format'!A175:A18426,A66,'Long Format'!C175:C18426,"Trade in services (% of GDP)"),"No Data") -> 27.800217 | G66: =IFERROR(RANK(F66,F$2:F$257,0),"") -> 65 | H66: =IF(F66="No Data","No Data",IF(F66>=50,"High",IF(F66>=25,"Medium",IF(F66>=10,"Low","Very Low")))) -> Medium
A67: Mongolia | B67: =VLOOKUP(A67,'Wide Format'!A:B,2,0) -> MNG | C67: =IFERROR(AVERAGEIFS('Long Format'!F166:F18417,'Long Format'!A166:A18417,A67,'Long Format'!C166:C18417,"Access to electricity, rural (% of rural population)"),"No Data") -> 65.41875 | D67: =IFERROR(RANK(C67,C$2:C$257,0),"") -> 176 | E67: =IF(C67="No Data","No Data",IF(C67>=75,"High",IF(C67>=50,"Medium",IF(C67>=25,"Low","Very Low")))) -> Medium | F67: =IFERROR(AVERAGEIFS('Long Format'!F177:F18428,'Long Format'!A177:A18428,A67,'Long Format'!C177:C18428,"Trade in services (% of GDP)"),"No Data") -> 27.509919 | G67: =IFERROR(RANK(F67,F$2:F$257,0),"") -> 66 | H67: =IF(F67="No Data","No Data",IF(F67>=50,"High",IF(F67>=25,"Medium",IF(F67>=10,"Low","Very Low")))) -> Medium
A68: Hungary | B68: =VLOOKUP(A68,'Wide Format'!A:B,2,0) -> HUN | C68: =IFERROR(AVERAGEIFS('Long Format'!F106:F18357,'Long Format'!A106:A18357,A68,'Long Format'!C106:C18357,"Access to electricity, rural (% of rural population)"),"No Data") -> 100 | D68: =IFERROR(RANK(C68,C$2:C$257,0),"") -> 1 | E68: =IF(C68="No Data","No Data",IF(C68>=75,"High",IF(C68>=50,"Medium",IF(C68>=25,"Low","Very Low")))) -> High | F68: =IFERROR(AVERAGEIFS('Long Format'!F31:F18282,'Long Format'!A31:A18282,A68,'Long Format'!C31:C18282,"Trade in services (% of GDP)"),"No Data") -> 26.710166 | G68: =IFERROR(RANK(F68,F$2:F$257,0),"") -> 67 | H68: =IF(F68="No Data","No Data",IF(F68>=50,"High",IF(F68>=25,"Medium",IF(F68>=10,"Low","Very Low")))) -> Medium
A69: Georgia | B69: =VLOOKUP(A69,'Wide Format'!A:B,2,0) -> GEO | C69: =IFERROR(AVERAGEIFS('Long Format'!F89:F18340,'Long Format'!A89:A18340,A69,'Long Format'!C89:C18340,"Access to electricity, rural (% of rural population)"),"No Data") -> 99.7875 | D69: =IFERROR(RANK(C69,C$2:C$257,0),"") -> 78 | E69: =IF(C69="No Data","No Data",IF(C69>=75,"High",IF(C69>=50,"Medium",IF(C69>=25,"Low","Very Low")))) -> High | F69: =IFERROR(AVERAGEIFS('Long Format'!F79:F18330,'Long Format'!A79:A18330,A69,'Long Format'!C79:C18330,"Trade in services (% of GDP)"),"No Data") -> 26.503791 | G69: =IFERROR(RANK(F69,F$2:F$257,0),"") -> 68 | H69: =IF(F69="No Data","No Data",IF(F69>=50,"High",IF(F69>=25,"Medium",IF(F69>=10,"Low","Very Low")))) -> Medium
A70: Latvia | B70: =VLOOKUP(A70,'Wide Format'!A:B,2,0) -> LVA | C70: =IFERROR(AVERAGEIFS('Long Format'!F136:F18387,'Long Format'!A136:A18387,A70,'Long Format'!C136:C18387,"Access to electricity, rural (% of rural population)"),"No Data") -> 99.99375 | D70: =IFERROR(RANK(C70,C$2:C$257,0),"") -> 70 | E70: =IF(C70="No Data","No Data",IF(C70>=75,"High",IF(C70>=50,"Medium",IF(C70>=25,"Low","Very Low")))) -> High | F70: =IFERROR(AVERAGEIFS('Long Format'!F72:F18323,'Long Format'!A72:A18323,A70,'Long Format'!C72:C18323,"Trade in services (% of GDP)"),"No Data") -> 26.419849 | G70: =IFERROR(RANK(F70,F$2:F$257,0),"") -> 69 | H70: =IF(F70="No Data","No Data",IF(F70>=50,"High",IF(F70>=25,"Medium",IF(F70>=10,"Low","Very Low")))) -> Medium
A71: Moldova | B71: =VLOOKUP(A71,'Wide Format'!A:B,2,0) -> MDA | C71: =IFERROR(AVERAGEIFS('Long Format'!F164:F18415,'Long Format'!A164:A18415,A71,'Long Format'!C164:C18415,"Access to electricity, rural (% of rural population)"),"No Data") -> 99.24375 | D71: =IFERROR(RANK(C71,C$2:C$257,0),"") -> 92 | E71: =IF(C71="No Data","No Data",IF(C71>=75,"High",IF(C71>=50,"Medium",IF(C71>=25,"Low","Very Low")))) -> High | F71: =IFERROR(AVERAGEIFS('Long Format'!F93:F18344,'Long Format'!A93:A18344,A71,'Long Format'!C93:C18344,"Trade in services (% of GDP)"),"No Data") -> 26.299221 | G71: =IFERROR(RANK(F71,F$2:F$257,0),"") -> 70 | H71: =IF(F71="No Data","No Data",IF(F71>=50,"High",IF(F71>=25,"Medium",IF(F71>=10,"Low","Very Low")))) -> Medium
A72: Armenia | B72: =VLOOKUP(A72,'Wide Format'!A:B,2,0) -> ARM | C72: =IFERROR(AVERAGEIFS('Long Format'!F13:F18264,'Long Format'!A13:A18264,A72,'Long Format'!C13:C18264,"Access to electricity, rural (% of rural population)"),"No Data") -> 99.2375 | D72: =IFERROR(RANK(C72,C$2:C$257,0),"") -> 93 | E72: =IF(C72="No Data","No Data",IF(C72>=75,"High",IF(C72>=50,"Medium",IF(C72>=25,"Low","Very Low")))) -> High | F72: =IFERROR(AVERAGEIFS('Long Format'!F94:F18345,'Long Format'!A94:A18345,A72,'Long Format'!C94:C18345,"Trade in services (% of GDP)"),"No Data") -> 26.177026 | G72: =IFERROR(RANK(F72,F$2:F$257,0),"") -> 71 | H72: =IF(F72="No Data","No Data",IF(F72>=50,"High",IF(F72>=25,"Medium",IF(F72>=10,"Low","Very Low")))) -> Medium
A73: Congo, Rep. | B73: =VLOOKUP(A73,'Wide Format'!A:B,2,0) -> COG | C73: =IFERROR(AVERAGEIFS('Long Format'!F52:F18303,'Long Format'!A52:A18303,A73,'Long Format'!C52:C18303,"Access to electricity, rural (% of rural population)"),"No Data") -> 9.14375 | D73: =IFERROR(RANK(C73,C$2:C$257,0),"") -> 239 | E73: =IF(C73="No Data","No Data",IF(C73>=75,"High",IF(C73>=50,"Medium",IF(C73>=25,"Low","Very Low")))) -> Very Low | F73: =IFERROR(AVERAGEIFS('Long Format'!F240:F18491,'Long Format'!A240:A18491,A73,'Long Format'!C240:C18491,"Trade in services (% of GDP)"),"No Data") -> 25.945668 | G73: =IFERROR(RANK(F73,F$2:F$257,0),"") -> 72 | H73: =IF(F73="No Data","No Data",IF(F73>=50,"High",IF(F73>=25,"Medium",IF(F73>=10,"Low","Very Low")))) -> Medium
A74: Malaysia | B74: =VLOOKUP(A74,'Wide Format'!A:B,2,0) -> MYS | C74: =IFERROR(AVERAGEIFS('Long Format'!F151:F18402,'Long Format'!A151:A18402,A74,'Long Format'!C151:C18402,"Access to electricity, rural (% of rural population)"),"No Data") -> 98.7375 | D74: =IFERROR(RANK(C74,C$2:C$257,0),"") -> 99 | E74: =IF(C74="No Data","No Data",IF(C74>=75,"High",IF(C74>=50,"Medium",IF(C74>=25,"Low","Very Low")))) -> High | F74: =IFERROR(AVERAGEIFS('Long Format'!F100:F18351,'Long Format'!A100:A18351,A74,'Long Format'!C100:C18351,"Trade in services (% of GDP)"),"No Data") -> 25.913352 | G74: =IFERROR(RANK(F74,F$2:F$257,0),"") -> 73 | H74: =IF(F74="No Data","No Data",IF(F74>=50,"High",IF(F74>=25,"Medium",IF(F74>=10,"Low","Very Low")))) -> Medium
A75: Greece | B75: =VLOOKUP(A75,'Wide Format'!A:B,2,0) -> GRC | C75: =IFERROR(AVERAGEIFS('Long Format'!F93:F18344,'Long Format'!A93:A18344,A75,'Long Format'!C93:C18344,"Access to electricity, rural (% of rural population)"),"No Data") -> 100 | D75: =IFERROR(RANK(C75,C$2:C$257,0),"") -> 1 | E75: =IF(C75="No Data","No Data",IF(C75>=75,"High",IF(C75>=50,"Medium",IF(C75>=25,"Low","Very Low")))) -> High | F75: =IFERROR(AVERAGEIFS('Long Format'!F27:F18278,'Long Format'!A27:A18278,A75,'Long Format'!C27:C18278,"Trade in services (% of GDP)"),"No Data") -> 25.678812 | G75: =IFERROR(RANK(F75,F$2:F$257,0),"") -> 74 | H75: =IF(F75="No Data","No Data",IF(F75>=50,"High",IF(F75>=25,"Medium",IF(F75>=10,"Low","Very Low")))) -> Medium
A76: Sao Tome and Principe | B76: =VLOOKUP(A76,'Wide Format'!A:B,2,0) -> STP | C76: =IFERROR(AVERAGEIFS('Long Format'!F206:F18457,'Long Format'!A206:A18457,A76,'Long Format'!C206:C18457,"Access to electricity, rural (% of rural population)"),"No Data") -> 52.99375 | D76: =IFERROR(RANK(C76,C$2:C$257,0),"") -> 190 | E76: =IF(C76="No Data","No Data",IF(C76>=75,"High",IF(C76>=50,"Medium",IF(C76>=25,"Low","Very Low")))) -> Medium | F76: =IFERROR(AVERAGEIFS('Long Format'!F191:F18442,'Long Format'!A191:A18442,A76,'Long Format'!C191:C18442,"Trade in services (% of GDP)"),"No Data") -> 25.336408 | G76: =IFERROR(RANK(F76,F$2:F$257,0),"") -> 75 | H76: =IF(F76="No Data","No Data",IF(F76>=50,"High",IF(F76>=25,"Medium",IF(F76>=10,"Low","Very Low")))) -> Medium
A77: Bulgaria | B77: =VLOOKUP(A77,'Wide Format'!A:B,2,0) -> BGR | C77: =IFERROR(AVERAGEIFS('Long Format'!F34:F18285,'Long Format'!A34:A18285,A77,'Long Format'!C34:C18285,"Access to electricity, rural (% of rural population)"),"No Data") -> 88.81875 | D77: =IFERROR(RANK(C77,C$2:C$257,0),"") -> 141 | E77: =IF(C77="No Data","No Data",IF(C77>=75,"High",IF(C77>=50,"Medium",IF(C77>=25,"Low","Very Low")))) -> High | F77: =IFERROR(AVERAGEIFS('Long Format'!F142:F18393,'Long Format'!A142:A18393,A77,'Long Format'!C142:C18393,"Trade in services (% of GDP)"),"No Data") -> 25.192519 | G77: =IFERROR(RANK(F77,F$2:F$257,0),"") -> 76 | H77: =IF(F77="No Data","No Data",IF(F77>=50,"High",IF(F77>=25,"Medium",IF(F77>=10,"Low","Very Low")))) -> Medium
A78: Sweden | B78: =VLOOKUP(A78,'Wide Format'!A:B,2,0) -> SWE | C78: =IFERROR(AVERAGEIFS('Long Format'!F234:F18485,'Long Format'!A234:A18485,A78,'Long Format'!C234:C18485,"Access to electricity, rural (% of rural population)"),"No Data") -> 100 | D78: =IFERROR(RANK(C78,C$2:C$257,0),"") -> 1 | E78: =IF(C78="No Data","No Data",IF(C78>=75,"High",IF(C78>=50,"Medium",IF(C78>=25,"Low","Very Low")))) -> High | F78: =IFERROR(AVERAGEIFS('Long Format'!F64:F18315,'Long Format'!A64:A18315,A78,'Long Format'!C64:C18315,"Trade in services (% of GDP)"),"No Data") -> 25.185309 | G78: =IFERROR(RANK(F78,F$2:F$257,0),"") -> 77 | H78: =IF(F78="No Data","No Data",IF(F78>=50,"High",IF(F78>=25,"Medium",IF(F78>=10,"Low","Very Low")))) -> Medium
A79: Serbia | B79: =VLOOKUP(A79,'Wide Format'!A:B,2,0) -> SRB | C79: =IFERROR(AVERAGEIFS('Long Format'!F209:F18460,'Long Format'!A209:A18460,A79,'Long Format'!C209:C18460,"Access to electricity, rural (% of rural population)"),"No Data") -> 99.875 | D79: =IFERROR(RANK(C79,C$2:C$257,0),"") -> 76 | E79: =IF(C79="No Data","No Data",IF(C79>=75,"High",IF(C79>=50,"Medium",IF(C79>=25,"Low","Very Low")))) -> High | F79: =IFERROR(AVERAGEIFS('Long Format'!F77:F18328,'Long Format'!A77:A18328,A79,'Long Format'!C77:C18328,"Trade in services (% of GDP)"),"No Data") -> 24.683284 | G79: =IFERROR(RANK(F79,F$2:F$257,0),"") -> 78 | H79: =IF(F79="No Data","No Data",IF(F79>=50,"High",IF(F79>=25,"Medium",IF(F79>=10,"Low","Very Low")))) -> Low
A80: Slovenia | B80: =VLOOKUP(A80,'Wide Format'!A:B,2,0) -> SVN | C80: =IFERROR(AVERAGEIFS('Long Format'!F215:F18466,'Long Format'!A215:A18466,A80,'Long Format'!C215:C18466,"Access to electricity, rural (% of rural population)"),"No Data") -> 100 | D80: =IFERROR(RANK(C80,C$2:C$257,0),"") -> 1 | E80: =IF(C80="No Data","No Data",IF(C80>=75,"High",IF(C80>=50,"Medium",IF(C80>=25,"Low","Very Low")))) -> High | F80: =IFERROR(AVERAGEIFS('Long Format'!F61:F18312,'Long Format'!A61:A18312,A80,'Long Format'!C61:C18312,"Trade in services (% of GDP)"),"No Data") -> 23.939392 | G80: =IFERROR(RANK(F80,F$2:F$257,0),"") -> 79 | H80: =IF(F80="No Data","No Data",IF(F80>=50,"High",IF(F80>=25,"Medium",IF(F80>=10,"Low","Very Low")))) -> Low
A81: Lesotho | B81: =VLOOKUP(A81,'Wide Format'!A:B,2,0) -> LSO | C81: =IFERROR(AVERAGEIFS('Long Format'!F139:F18390,'Long Format'!A139:A18390,A81,'Long Format'!C139:C18390,"Access to electricity, rural (% of rural population)"),"No Data") -> 19.483333 | D81: =IFERROR(RANK(C81,C$2:C$257,0),"") -> 227 | E81: =IF(C81="No Data","No Data",IF(C81>=75,"High",IF(C81>=50,"Medium",IF(C81>=25,"Low","Very Low")))) -> Very Low | F81: =IFERROR(AVERAGEIFS('Long Format'!F228:F18479,'Long Format'!A228:A18479,A81,'Long Format'!C228:C18479,"Trade in services (% of GDP)"),"No Data") -> 23.669621 | G81: =IFERROR(RANK(F81,F$2:F$257,0),"") -> 80 | H81: =IF(F81="No Data","No Data",IF(F81>=50,"High",IF(F81>=25,"Medium",IF(F81>=10,"Low","Very Low")))) -> Low
A82: Thailand | B82: =VLOOKUP(A82,'Wide Format'!A:B,2,0) -> THA | C82: =IFERROR(AVERAGEIFS('Long Format'!F239:F18490,'Long Format'!A239:A18490,A82,'Long Format'!C239:C18490,"Access to electricity, rural (% of rural population)"),"No Data") -> 93.20625 | D82: =IFERROR(RANK(C82,C$2:C$257,0),"") -> 123 | E82: =IF(C82="No Data","No Data",IF(C82>=75,"High",IF(C82>=50,"Medium",IF(C82>=25,"Low","Very Low")))) -> High | F82: =IFERROR(AVERAGEIFS('Long Format'!F124:F18375,'Long Format'!A124:A18375,A82,'Long Format'!C124:C18375,"Trade in services (% of GDP)"),"No Data") -> 23.59738 | G82: =IFERROR(RANK(F82,F$2:F$257,0),"") -> 81 | H82: =IF(F82="No Data","No Data",IF(F82>=50,"High",IF(F82>=25,"Medium",IF(F82>=10,"Low","Very Low")))) -> Low
A83: Honduras | B83: =VLOOKUP(A83,'Wide Format'!A:B,2,0) -> HND | C83: =IFERROR(AVERAGEIFS('Long Format'!F104:F18355,'Long Format'!A104:A18355,A83,'Long Format'!C104:C18355,"Access to electricity, rural (% of rural population)"),"No Data") -> 60.74375 | D83: =IFERROR(RANK(C83,C$2:C$257,0),"") -> 183 | E83: =IF(C83="No Data","No Data",IF(C83>=75,"High",IF(C83>=50,"Medium",IF(C83>=25,"Low","Very Low")))) -> Medium | F83: =IFERROR(AVERAGEIFS('Long Format'!F184:F18435,'Long Format'!A184:A18435,A83,'Long Format'!C184:C18435,"Trade in services (% of GDP)"),"No Data") -> 23.470262 | G83: =IFERROR(RANK(F83,F$2:F$257,0),"") -> 82 | H83: =IF(F83="No Data","No Data",IF(F83>=50,"High",IF(F83>=25,"Medium",IF(F83>=10,"Low","Very Low")))) -> Low
A84: North Macedonia | B84: =VLOOKUP(A84,'Wide Format'!A:B,2,0) -> MKD | C84: =IFERROR(AVERAGEIFS('Long Format'!F181:F18432,'Long Format'!A181:A18432,A84,'Long Format'!C181:C18432,"Access to electricity, rural (% of rural population)"),"No Data") -> 99.575 | D84: =IFERROR(RANK(C84,C$2:C$257,0),"") -> 83 | E84: =IF(C84="No Data","No Data",IF(C84>=75,"High",IF(C84>=50,"Medium",IF(C84>=25,"Low","Very Low")))) -> High | F84: =IFERROR(AVERAGEIFS('Long Format'!F84:F18335,'Long Format'!A84:A18335,A84,'Long Format'!C84:C18335,"Trade in services (% of GDP)"),"No Data") -> 23.030483 | G84: =IFERROR(RANK(F84,F$2:F$257,0),"") -> 83 | H84: =IF(F84="No Data","No Data",IF(F84>=50,"High",IF(F84>=25,"Medium",IF(F84>=10,"Low","Very Low")))) -> Low
A85: Costa Rica | B85: =VLOOKUP(A85,'Wide Format'!A:B,2,0) -> CRI | C85: =IFERROR(AVERAGEIFS('Long Format'!F53:F18304,'Long Format'!A53:A18304,A85,'Long Format'!C53:C18304,"Access to electricity, rural (% of rural population)"),"No Data") -> 97.8625 | D85: =IFERROR(RANK(C85,C$2:C$257,0),"") -> 108 | E85: =IF(C85="No Data","No Data",IF(C85>=75,"High",IF(C85>=50,"Medium",IF(C85>=25,"Low","Very Low")))) -> High | F85: =IFERROR(AVERAGEIFS('Long Format'!F109:F18360,'Long Format'!A109:A18360,A85,'Long Format'!C109:C18360,"Trade in services (% of GDP)"),"No Data") -> 22.762518 | G85: =IFERROR(RANK(F85,F$2:F$257,0),"") -> 84 | H85: =IF(F85="No Data","No Data",IF(F85>=50,"High",IF(F85>=25,"Medium",IF(F85>=10,"Low","Very Low")))) -> Low
A86: Ghana | B86: =VLOOKUP(A86,'Wide Format'!A:B,2,0) -> GHA | C86: =IFERROR(AVERAGEIFS('Long Format'!F91:F18342,'Long Format'!A91:A18342,A86,'Long Format'!C91:C18342,"Access to electricity, rural (% of rural population)"),"No Data") -> 44.3375 | D86: =IFERROR(RANK(C86,C$2:C$257,0),"") -> 198 | E86: =IF(C86="No Data","No Data",IF(C86>=75,"High",IF(C86>=50,"Medium",IF(C86>=25,"Low","Very Low")))) -> Low | F86: =IFERROR(AVERAGEIFS('Long Format'!F199:F18450,'Long Format'!A199:A18450,A86,'Long Format'!C199:C18450,"Trade in services (% of GDP)"),"No Data") -> 22.688022 | G86: =IFERROR(RANK(F86,F$2:F$257,0),"") -> 85 | H86: =IF(F86="No Data","No Data",IF(F86>=50,"High",IF(F86>=25,"Medium",IF(F86>=10,"Low","Very Low")))) -> Low
A87: Suriname | B87: =VLOOKUP(A87,'Wide Format'!A:B,2,0) -> SUR | C87: =IFERROR(AVERAGEIFS('Long Format'!F233:F18484,'Long Format'!A233:A18484,A87,'Long Format'!C233:C18484,"Access to electricity, rural (% of rural population)"),"No Data") -> 91.93125 | D87: =IFERROR(RANK(C87,C$2:C$257,0),"") -> 132 | E87: =IF(C87="No Data","No Data",IF(C87>=75,"High",IF(C87>=50,"Medium",IF(C87>=25,"Low","Very Low")))) -> High | F87: =IFERROR(AVERAGEIFS('Long Format'!F133:F18384,'Long Format'!A133:A18384,A87,'Long Format'!C133:C18384,"Trade in services (% of GDP)"),"No Data") -> 22.29917 | G87: =IFERROR(RANK(F87,F$2:F$257,0),"") -> 86 | H87: =IF(F87="No Data","No Data",IF(F87>=50,"High",IF(F87>=25,"Medium",IF(F87>=10,"Low","Very Low")))) -> Low
A88: Azerbaijan | B88: =VLOOKUP(A88,'Wide Format'!A:B,2,0) -> AZE | C88: =IFERROR(AVERAGEIFS('Long Format'!F17:F18268,'Long Format'!A17:A18268,A88,'Long Format'!C17:C18268,"Access to electricity, rural (% of rural population)"),"No Data") -> 99.29375 | D88: =IFERROR(RANK(C88,C$2:C$257,0),"") -> 90 | E88: =IF(C88="No Data","No Data",IF(C88>=75,"High",IF(C88>=50,"Medium",IF(C88>=25,"Low","Very Low")))) -> High | F88: =IFERROR(AVERAGEIFS('Long Format'!F91:F18342,'Long Format'!A91:A18342,A88,'Long Format'!C91:C18342,"Trade in services (% of GDP)"),"No Data") -> 22.075572 | G88: =IFERROR(RANK(F88,F$2:F$257,0),"") -> 87 | H88: =IF(F88="No Data","No Data",IF(F88>=50,"High",IF(F88>=25,"Medium",IF(F88>=10,"Low","Very Low")))) -> Low
A89: Kuwait | B89: =VLOOKUP(A89,'Wide Format'!A:B,2,0) -> KWT | C89: =IFERROR(AVERAGEIFS('Long Format'!F129:F18380,'Long Format'!A129:A18380,A89,'Long Format'!C129:C18380,"Access to electricity, rural (% of rural population)"),"No Data") -> 100 | D89: =IFERROR(RANK(C89,C$2:C$257,0),"") -> 1 | E89: =IF(C89="No Data","No Data",IF(C89>=75,"High",IF(C89>=50,"Medium",IF(C89>=25,"Low","Very Low")))) -> High | F89: =IFERROR(AVERAGEIFS('Long Format'!F39:F18290,'Long Format'!A39:A18290,A89,'Long Format'!C39:C18290,"Trade in services (% of GDP)"),"No Data") -> 22.004149 | G89: =IFERROR(RANK(F89,F$2:F$257,0),"") -> 88 | H89: =IF(F89="No Data","No Data",IF(F89>=50,"High",IF(F89>=25,"Medium",IF(F89>=10,"Low","Very Low")))) -> Low
A90: European Union | B90: =VLOOKUP(A90,'Wide Format'!A:B,2,0) -> EUU | C90: =IFERROR(AVERAGEIFS('Long Format'!F80:F18331,'Long Format'!A80:A18331,A90,'Long Format'!C80:C18331,"Access to electricity, rural (% of rural population)"),"No Data") -> 99.525974 | D90: =IFERROR(RANK(C90,C$2:C$257,0),"") -> 84 | E90: =IF(C90="No Data","No Data",IF(C90>=75,"High",IF(C90>=50,"Medium",IF(C90>=25,"Low","Very Low")))) -> High | F90: =IFERROR(AVERAGEIFS('Long Format'!F85:F18336,'Long Format'!A85:A18336,A90,'Long Format'!C85:C18336,"Trade in services (% of GDP)"),"No Data") -> 21.991892 | G90: =IFERROR(RANK(F90,F$2:F$257,0),"") -> 89 | H90: =IF(F90="No Data","No Data",IF(F90>=50,"High",IF(F90>=25,"Medium",IF(F90>=10,"Low","Very Low")))) -> Low
A91: Euro area | B91: =VLOOKUP(A91,'Wide Format'!A:B,2,0) -> EMU | C91: =IFERROR(AVERAGEIFS('Long Format'!F76:F18327,'Long Format'!A76:A18327,A91,'Long Format'!C76:C18327,"Access to electricity, rural (% of rural population)"),"No Data") -> 99.999314 | D91: =IFERROR(RANK(C91,C$2:C$257,0),"") -> 69 | E91: =IF(C91="No Data","No Data",IF(C91>=75,"High",IF(C91>=50,"Medium",IF(C91>=25,"Low","Very Low")))) -> High | F91: =IFERROR(AVERAGEIFS('Long Format'!F70:F18321,'Long Format'!A70:A18321,A91,'Long Format'!C70:C18321,"Trade in services (% of GDP)"),"No Data") -> 21.782507 | G91: =IFERROR(RANK(F91,F$2:F$257,0),"") -> 90 | H91: =IF(F91="No Data","No Data",IF(F91>=50,"High",IF(F91>=25,"Medium",IF(F91>=10,"Low","Very Low")))) -> Low
A92: Kyrgyz Republic | B92: =VLOOKUP(A92,'Wide Format'!A:B,2,0) -> KGZ | C92: =IFERROR(AVERAGEIFS('Long Format'!F130:F18381,'Long Format'!A130:A18381,A92,'Long Format'!C130:C18381,"Access to electricity, rural (% of rural population)"),"No Data") -> 99.6375 | D92: =IFERROR(RANK(C92,C$2:C$257,0),"") -> 80 | E92: =IF(C92="No Data","No Data",IF(C92>=75,"High",IF(C92>=50,"Medium",IF(C92>=25,"Low","Very Low")))) -> High | F92: =IFERROR(AVERAGEIFS('Long Format'!F81:F18332,'Long Format'!A81:A18332,A92,'Long Format'!C81:C18332,"Trade in services (% of GDP)"),"No Data") -> 21.244302 | G92: =IFERROR(RANK(F92,F$2:F$257,0),"") -> 91 | H92: =IF(F92="No Data","No Data",IF(F92>=50,"High",IF(F92>=25,"Medium",IF(F92>=10,"Low","Very Low")))) -> Low
A93: Solomon Islands | B93: =VLOOKUP(A93,'Wide Format'!A:B,2,0) -> SLB | C93: =IFERROR(AVERAGEIFS('Long Format'!F217:F18468,'Long Format'!A217:A18468,A93,'Long Format'!C217:C18468,"Access to electricity, rural (% of rural population)"),"No Data") -> 41.530769 | D93: =IFERROR(RANK(C93,C$2:C$257,0),"") -> 200 | E93: =IF(C93="No Data","No Data",IF(C93>=75,"High",IF(C93>=50,"Medium",IF(C93>=25,"Low","Very Low")))) -> Low | F93: =IFERROR(AVERAGEIFS('Long Format'!F201:F18452,'Long Format'!A201:A18452,A93,'Long Format'!C201:C18452,"Trade in services (% of GDP)"),"No Data") -> 21.192708 | G93: =IFERROR(RANK(F93,F$2:F$257,0),"") -> 92 | H93: =IF(F93="No Data","No Data",IF(F93>=50,"High",IF(F93>=25,"Medium",IF(F93>=10,"Low","Very Low")))) -> Low
A94: Ukraine | B94: =VLOOKUP(A94,'Wide Format'!A:B,2,0) -> UKR | C94: =IFERROR(AVERAGEIFS('Long Format'!F250:F18501,'Long Format'!A250:A18501,A94,'Long Format'!C250:C18501,"Access to electricity, rural (% of rural population)"),"No Data") -> 99.475 | D94: =IFERROR(RANK(C94,C$2:C$257,0),"") -> 85 | E94: =IF(C94="No Data","No Data",IF(C94>=75,"High",IF(C94>=50,"Medium",IF(C94>=25,"Low","Very Low")))) -> High | F94: =IFERROR(AVERAGEIFS('Long Format'!F86:F18337,'Long Format'!A86:A18337,A94,'Long Format'!C86:C18337,"Trade in services (% of GDP)"),"No Data") -> 21.086652 | G94: =IFERROR(RANK(F94,F$2:F$257,0),"") -> 93 | H94: =IF(F94="No Data","No Data",IF(F94>=50,"High",IF(F94>=25,"Medium",IF(F94>=10,"Low","Very Low")))) -> Low
A95: Israel | B95: =VLOOKUP(A95,'Wide Format'!A:B,2,0) -> ISR | C95: =IFERROR(AVERAGEIFS('Long Format'!F119:F18370,'Long Format'!A119:A18370,A95,'Long Format'!C119:C18370,"Access to electricity, rural (% of rural population)"),"No Data") -> 100 | D95: =IFERROR(RANK(C95,C$2:C$257,0),"") -> 1 | E95: =IF(C95="No Data","No Data",IF(C95>=75,"High",IF(C95>=50,"Medium",IF(C95>=25,"Low","Very Low")))) -> High | F95: =IFERROR(AVERAGEIFS('Long Format'!F35:F18286,'Long Format'!A35:A18286,A95,'Long Format'!C35:C18286,"Trade in services (% of GDP)"),"No Data") -> 21.072906 | G95: =IFERROR(RANK(F95,F$2:F$257,0),"") -> 94 | H95: =IF(F95="No Data","No Data",IF(F95>=50,"High",IF(F95>=25,"Medium",IF(F95>=10,"Low","Very Low")))) -> Low
A96: Tunisia | B96: =VLOOKUP(A96,'Wide Format'!A:B,2,0) -> TUN | C96: =IFERROR(AVERAGEIFS('Long Format'!F244:F18495,'Long Format'!A244:A18495,A96,'Long Format'!C244:C18495,"Access to electricity, rural (% of rural population)"),"No Data") -> 97.61875 | D96: =IFERROR(RANK(C96,C$2:C$257,0),"") -> 110 | E96: =IF(C96="No Data","No Data",IF(C96>=75,"High",IF(C96>=50,"Medium",IF(C96>=25,"Low","Very Low")))) -> High | F96: =IFERROR(AVERAGEIFS('Long Format'!F111:F18362,'Long Format'!A111:A18362,A96,'Long Format'!C111:C18362,"Trade in services (% of GDP)"),"No Data") -> 20.787514 | G96: =IFERROR(RANK(F96,F$2:F$257,0),"") -> 95 | H96: =IF(F96="No Data","No Data",IF(F96>=50,"High",IF(F96>=25,"Medium",IF(F96>=10,"Low","Very Low")))) -> Low
A97: United Kingdom | B97: =VLOOKUP(A97,'Wide Format'!A:B,2,0) -> GBR | C97: =IFERROR(AVERAGEIFS('Long Format'!F252:F18503,'Long Format'!A252:A18503,A97,'Long Format'!C252:C18503,"Access to electricity, rural (% of rural population)"),"No Data") -> 100 | D97: =IFERROR(RANK(C97,C$2:C$257,0),"") -> 1 | E97: =IF(C97="No Data","No Data",IF(C97>=75,"High",IF(C97>=50,"Medium",IF(C97>=25,"Low","Very Low")))) -> High | F97: =IFERROR(AVERAGEIFS('Long Format'!F67:F18318,'Long Format'!A67:A18318,A97,'Long Format'!C67:C18318,"Trade in services (% of GDP)"),"No Data") -> 20.651223 | G97: =IFERROR(RANK(F97,F$2:F$257,0),"") -> 96 | H97: =IF(F97="No Data","No Data",IF(F97>=50,"High",IF(F97>=25,"Medium",IF(F97>=10,"Low","Very Low")))) -> Low
A98: Europe & Central Asia | B98: =VLOOKUP(A98,'Wide Format'!A:B,2,0) -> ECS | C98: =IFERROR(AVERAGEIFS('Long Format'!F77:F18328,'Long Format'!A77:A18328,A98,'Long Format'!C77:C18328,"Access to electricity, rural (% of rural population)"),"No Data") -> 99.32355 | D98: =IFERROR(RANK(C98,C$2:C$257,0),"") -> 89 | E98: =IF(C98="No Data","No Data",IF(C98>=75,"High",IF(C98>=50,"Medium",IF(C98>=25,"Low","Very Low")))) -> High | F98: =IFERROR(AVERAGEIFS('Long Format'!F90:F18341,'Long Format'!A90:A18341,A98,'Long Format'!C90:C18341,"Trade in services (% of GDP)"),"No Data") -> 20.63233 | G98: =IFERROR(RANK(F98,F$2:F$257,0),"") -> 97 | H98: =IF(F98="No Data","No Data",IF(F98>=50,"High",IF(F98>=25,"Medium",IF(F98>=10,"Low","Very Low")))) -> Low
A99: Czechia | B99: =VLOOKUP(A99,'Wide Format'!A:B,2,0) -> CZE | C99: =IFERROR(AVERAGEIFS('Long Format'!F59:F18310,'Long Format'!A59:A18310,A99,'Long Format'!C59:C18310,"Access to electricity, rural (% of rural population)"),"No Data") -> 100 | D99: =IFERROR(RANK(C99,C$2:C$257,0),"") -> 1 | E99: =IF(C99="No Data","No Data",IF(C99>=75,"High",IF(C99>=50,"Medium",IF(C99>=25,"Low","Very Low")))) -> High | F99: =IFERROR(AVERAGEIFS('Long Format'!F17:F18268,'Long Format'!A17:A18268,A99,'Long Format'!C17:C18268,"Trade in services (% of GDP)"),"No Data") -> 20.495941 | G99: =IFERROR(RANK(F99,F$2:F$257,0),"") -> 98 | H99: =IF(F99="No Data","No Data",IF(F99>=50,"High",IF(F99>=25,"Medium",IF(F99>=10,"Low","Very Low")))) -> Low
A100: Norway | B100: =VLOOKUP(A100,'Wide Format'!A:B,2,0) -> NOR | C100: =IFERROR(AVERAGEIFS('Long Format'!F183:F18434,'Long Format'!A183:A18434,A100,'Long Format'!C183:C18434,"Access to electricity, rural (% of rural population)"),"No Data") -> 100 | D100: =IFERROR(RANK(C100,C$2:C$257,0),"") -> 1 | E100: =IF(C100="No Data","No Data",IF(C100>=75,"High",IF(C100>=50,"Medium",IF(C100>=25,"Low","Very Low")))) -> High | F100: =IFERROR(AVERAGEIFS('Long Format'!F51:F18302,'Long Format'!A51:A18302,A100,'Long Format'!C51:C18302,"Trade in services (% of GDP)"),"No Data") -> 20.324771 | G100: =IFERROR(RANK(F100,F$2:F$257,0),"") -> 99 | H100: =IF(F100="No Data","No Data",IF(F100>=50,"High",IF(F100>=25,"Medium",IF(F100>=10,"Low","Very Low")))) -> Low
...

Sheet Series - Metadata
A1: Code | B1: License Type | C1: Indicator Name | D1: Long definition | E1: Source | F1: Topic | G1: Dataset | H1: Unit of measure | I1: Periodicity | J1: Reference period | K1: Aggregation method | L1: Statistical concept and methodology | M1: Development relevance | N1: Other notes | O1: License URL
A2: FM.LBL.BMNY.GD.ZS | B2: CC BY-4.0 | C2: Broad money (% of GDP) | D2: Broad money is the sum of all liquid financial instruments held by money-holding sectors that are widely accepted in an economy as a medium of exchange, plus those that can be converted into a medium of exchange at short notice at, or close to, their full nominal value. This indicator is expressed as a percentage of Gross Domestic Product (GDP) which is the total income earned through the production of goods and services in an economic territory during an accounting period. | E2: International Financial Statistics database, International Monetary Fund (IMF); World Development Indicators Database, World Bank (WB); National Accounts data files, Organisation for Economic Co-operation and Development (OECD) | F2: Financial Sector: Monetary holdings (liabilities) | G2: WB_WDI | H2: % | I2: Annual | J2: 1960-2024 | K2: Weighted average | L2: Methodology: Monetary and Financial statistics are compiled in accordance with international standards: Monetary and Financial Statistics Manual, 2018 or 2004 versions. Specific information on how countries compile their Monetary and Finance statistics can be found on the IMF website: https://dsbb.imf.org/ Statistical concept(s): The conceptual framework comes from the Monetary and Financial Statistic Manual which outlines the analytical presentation of monetary statistics, which provide critical inputs for monetary policy formulation and monitoring. The statistics covered in this Manual also support the assessment of financial system stability. | M2: This indicator is related the monetary and financial statistics. Monetary and financial statistics are crucial as they offer a detailed picture of a country's financial condition and the workings of its monetary system. This encompasses information on the money supply, prevailing interest rates, and the activities of financial institutions. Central banks and policymakers rely on these statistics to craft monetary policy, manage interest rates, and regulate inflation. For investors and market analysts, these figures provide a window into the financial sector's stability and performance, guiding investment decisions and risk evaluations. They also shed light on the circulation of money within the economy, which has direct implications for consumer spending, business investments, and the overall trajectory of economic growth. Ultimately, these statistics play a pivotal role in ensuring economic stability and promoting sustainable development. | N2: The derivation of this indicator was simplified in September 2012 to be current-year broad money divided by current-year GDP times 100. | O2: https://datacatalog.worldbank.org/public-licenses#cc-by
A3: EG.ELC.ACCS.RU.ZS | B3: CC BY-4.0 | C3: Access to electricity, rural (% of rural population) | D3: Access to electricity, rural is the percentage of rural population with access to electricity. | E3: SDG 7.1.1 Electrification Dataset, World Bank (WB), uri: https://trackingsdg7.esmap.org/downloads, note: Data is downloaded from ESMAP website. Data is released when a new Tracking SDG7 report is released., publisher: World Bank (WB), date accessed: 2024-05-16, date published: 2023 | F3: Environment: Energy production & use | G3: WB_WDI | H3: % (share) of rural population | I3: Annual | J3: 1990-2023 | K3: Weighted average | L3: Methodology: The World Bank’s Global Electrification Database (GED) compiles nationally representative household survey data, and occasionally census data, from sources going back as far as 1990. The database also incorporates data from the Socio-Economic Database for Latin America and the Caribbean (SEDLAC), Middle East and North Africa Poverty Database (MNAPOV) and the Europe and Central Asia Poverty Database (ECAPOV), which are based on similar surveys. At the time of this analysis, the GED contained 1,375 surveys for 149 countries in 1990-2021. Statistical concept(s): | M3: Maintaining reliable and secure electricity services while seeking to rapidly decarbonize power systems is a key challenge for countries throughout the world. More and more countries are becoming increasing dependent on reliable and secure electricity supplies to underpin economic growth and community prosperity. This reliance is set to grow as more efficient and less carbon intensive forms of power are developed and deployed to help decarbonize economies. Energy is necessary for creating the conditions for economic growth. It is impossible to operate a factory, run a shop, grow crops or deliver goods to consumers without using some form of energy. Access to electricity is particularly crucial to human development as electricity is, in practice, indispensable for certain basic activities, such as lighting, refrigeration and the running of household appliances, and cannot easily be replaced by other forms of energy. Individuals' access to electricity is one of the most clear and un-distorted indication of a country's energy poverty status. Electricity access is increasingly at the forefront of governments' preoccupations, especially in the developing countries. As a consequence, a lot of rural electrification programs and national electrification agencies have been created in these countries to monitor more accurately the needs and the status of rural development and electrification. Use of energy is important in improving people's standard of living. But electricity generation also can damage the environment. Whether such damage occurs depends largely on how electricity is generated. For example, burning coal releases twice as much carbon dioxide - a major contributor to global warming - as does burning an equivalent amount of natural gas. | O3: https://datacatalog.worldbank.org/public-licenses#cc-by
A4: FP.CPI.TOTL.ZG | B4: CC BY-4.0 | C4: Inflation, consumer prices (annual % growth) | D4: Inflation as measured by the consumer price index reflects the annual percentage change in the cost to the average consumer of acquiring a basket of goods and services that may be fixed or changed at specified intervals, such as yearly. This indicator denotes the percentage change over each previous year of the constant price (base year 2015) series in United States dollars. | E4: International Financial Statistics database, International Monetary Fund (IMF) | F4: Financial Sector: Exchange rates & prices | G4: WB_WDI | H4: % | I4: Annual | J4: 1960-2024 | K4: Median | L4: Methodology: Consumer Prices Indices are compiled in accordance with international standards: Consumer Price Index Manual, 2020 or 2004 version. Specific information on how countries compile their CPI statistics can be found on the IMF website: https://dsbb.imf.org/ Statistical concept(s): The conceptual basis of a consumer price index series is to measure the rate at which prices of consumption goods and services are changing from one period to another. | M4: A general and continuing increase in an economy’s price level is called inflation. The increase in the average prices of goods and services in the economy should be distinguished from a change in the relative prices of individual goods and services. Generally accompanying an overall increase in the price level is a change in the structure of relative prices, but it is only the average increase, not the relative price changes, that constitutes inflation. A commonly used measure of inflation is the consumer price index, which measures the prices of a representative basket of goods and services purchased by a typical household. The consumer price index is usually calculated on the basis of periodic surveys of consumer prices. Other price indices are derived implicitly from indexes of current and constant price series. | O4: https://datacatalog.worldbank.org/public-licenses#cc-by
A5: NY.GDP.DEFL.KD.ZG | B5: CC BY-4.0 | C5: Inflation, GDP deflator (annual % growth) | D5: Inflation as measured by the annual growth rate of the GDP implicit deflator shows the rate of price change in the economy as a whole. The GDP implicit deflator is the ratio of GDP in current local currency to GDP in constant local currency. | E5: Country official statistics, National Statistical Organizations and/or Central Banks; National Accounts data files, Organisation for Economic Co-operation and Development (OECD); Staff estimates, World Bank (WB) | F5: Financial Sector: Exchange rates & prices | G5: WB_WDI | H5: % | I5: Annual | J5: 1961-2024 | K5: Median | L5: Methodology: National accounts are compiled in accordance with international standards: System of National Accounts, 2008 or 1993 versions. Specific information on how countries compile their national accounts can be found on the IMF website: https://dsbb.imf.org/ Statistical concept(s): The conceptual elements of the SNA (System of National Accounts) measure what takes place in the economy, between which agents, and for what purpose. At the heart of the SNA is the production of goods and services. These may be used for consumption in the period to which the accounts relate or may be accumulated for use in a later period. In simple terms, the amount of value added generated by production represents GDP. The income corresponding to GDP is distributed to the various agents or groups of agents as income and it is the process of distributing and redistributing income that allows one agent to consume the goods and services produced by another agent or to acquire goods and services for later consumption. The way in which the SNA captures this pattern of economic flows is to identify the activities concerned by recognizing the institutional units in the economy and by specifying the structure of accounts capturing the transactions relevant to one stage or another of the process by which goods and services are produced and ultimately consumed. | M5: This indicator is related to the national accounts, which are critical for understanding and managing a country's economy. They provide a framework for the analysis of economic performance. National accounts are the basis for estimating the Gross Domestic Product (GDP) and Gross National Income (GNI), which are the most widely used indicator of economic performance. They are essential for government policymakers, providing the data needed to design and assess fiscal and monetary policies; and are also used by businesses and investors to assess the economic climate and make investment decisions. NAS enable comparison between economies, which is crucial for international trade, investment decisions, and economic competitiveness. More specifically, this indicator is related to national accounts aggregates. Gross Domestic Product (GDP), Gross National Income (GNI), and other aggregates provide a snapshot of the size and health of an economy by measuring the total economic activity within a country. They can thus be used by policymakers to design and implement economic policies, as they reflect the overall economic performance and can indicate the need for intervention in certain areas. Aggregates also allow for comparisons between different economies, which can be useful for trade negotiations, investment decisions, and economic benchmarking. By examining aggregates over time, economists and analysts can identify trends, cycles, and potential areas of concern within an economy, and investors can use national accounts aggregates to assess the potential risks and returns of investing in a particular country. Overall, national accounts aggregates are fundamental tools for economic analysis, policy formulation, and decision-making at both the national and international levels. | O5: https://datacatalog.worldbank.org/public-licenses#cc-by
A6: BG.GSR.NFSV.GD.ZS | B6: CC BY-4.0 | C6: Trade in services (% of GDP) | D6: Total trade in services includes services provided by residents to non-residents plus services provided by non-residents to residents. This indicator is expressed as a percentage of Gross Domestic Product (GDP) which is the total income earned through the production of goods and services in an economic territory during an accounting period. | E6: Balance of Payments Statistics Yearbook and data files, International Monetary Fund (IMF); World Development Indicators Database, World Bank (WB); National Accounts data files, Organisation for Economic Co-operation and Development (OECD) | F6: Economic Policy & Debt: Balance of payments: Current account: Goods, services & income | G6: WB_WDI | H6: % | I6: Annual | J6: 1960-2024 | K6: Weighted average | L6: Methodology: Balance of payments statistics are compiled in accordance with international standards: Balance of Payments and International Investment Position Manual, 6th or 5th editions. Specific information on how countries compile their balance of payments statistics can be found on the IMF website: https://dsbb.imf.org/ Statistical concept(s): The international accounts for an economy summarize the economic relationships between residents of that economy and nonresidents. They comprise the following: (a) the international investment position (IIP)—a statement that shows at a point in time the value of: financial assets of residents of an economy that are claims on nonresidents or are gold bullion held as reserve assets; and the liabilities of residents of an economy to nonresidents; (b) the balance of payments—a statement that summarizes economic transactions between residents and nonresidents during a specific time period; and (c) the other changes in financial assets and liabilities accounts—a statement that shows other flows, such as valuation changes, that reconciles the balance of payments and IIP for a specific period, by showing changes due to economic events other than transactions between residents and nonresidents. | M6: This indicator is related to the balance of payments, which is a statement that summarizes economic transactions between residents and nonresidents during a specific time period. It consists of the goods and services account (the trade balance), the primary account, the secondary income account, the capital account, and the financial account. It is useful for policymakers, economists, and analysts as it provides insights into a country's financial stability, the effectiveness of its fiscal and monetary policies, and its economic relationship with other countries. Understanding the balance of payments can help in making informed decisions regarding economic policies and strategies for sustainable growth. More specifically, this indicator is related to the goods and services accounts of the balance of payments, which records the value of a country's exports and imports of goods and services over a period of time. It helps in understanding the trade balance, which is a key indicator of a country's economic health. This information is valuable for policymakers, economists, investors, and businesses in making informed decisions related to trade policies, investment strategies, and economic planning. | N6: Note: Data are based on the sixth edition of the IMF's Balance of Payments Manual (BPM6) and are only available from 2005 onwards. | O6: https://datacatalog.worldbank.org/public-licenses#cc-by
